{"format":"kore-hd-voxels-v1","palette":["#b54294","#ffb5e7","#ffdeff","#ef7bbd","#101021","#cecece","#5a0894","#ffffff","#ffff00","#ffbd00","#d68400","#a5b5ad","#848484"],"voxels":[{"part":"head","x":-0.8564,"y":1.45811,"z":-0.012,"w":0.03167,"h":0.03167,"d":0.24,"c":0,"s":0},{"part":"head","x":-0.82409,"y":1.45811,"z":-0.012,"w":0.03167,"h":0.03167,"d":0.24,"c":0,"s":0},{"part":"head","x":-0.79177,"y":1.45811,"z":-0.012,"w":0.03167,"h":0.03167,"d":0.24,"c":0,"s":0},{"part":"head","x":-0.75945,"y":1.45811,"z":-0.012,"w":0.03167,"h":0.03167,"d":0.24,"c":0,"s":0},{"part":"head","x":-0.72713,"y":1.45811,"z":-0.012,"w":0.03167,"h":0.03167,"d":0.24,"c":0,"s":0},{"part":"head","x":-0.92104,"y":1.42579,"z":0.018,"w":0.03167,"h":0.03167,"d":0.24,"c":1,"s":1},{"part":"head","x":-0.88872,"y":1.42579,"z":0.018,"w":0.03167,"h":0.03167,"d":0.24,"c":1,"s":1},{"part":"head","x":-0.8564,"y":1.42579,"z":0.018,"w":0.03167,"h":0.03167,"d":0.24,"c":2,"s":2},{"part":"head","x":-0.82409,"y":1.42579,"z":0.018,"w":0.03167,"h":0.03167,"d":0.24,"c":2,"s":2},{"part":"head","x":-0.79177,"y":1.42579,"z":0.018,"w":0.03167,"h":0.03167,"d":0.24,"c":2,"s":2},{"part":"head","x":-0.75945,"y":1.42579,"z":0.018,"w":0.03167,"h":0.03167,"d":0.24,"c":2,"s":2},{"part":"head","x":-0.72713,"y":1.42579,"z":0.018,"w":0.03167,"h":0.03167,"d":0.24,"c":2,"s":2},{"part":"head","x":-0.69482,"y":1.42579,"z":-0.012,"w":0.03167,"h":0.03167,"d":0.24,"c":0,"s":0},{"part":"head","x":-0.6625,"y":1.42579,"z":-0.012,"w":0.03167,"h":0.03167,"d":0.24,"c":0,"s":0},{"part":"head","x":-0.98567,"y":1.39348,"z":-0.012,"w":0.03167,"h":0.03167,"d":0.24,"c":0,"s":0},{"part":"head","x":-0.95335,"y":1.39348,"z":0.018,"w":0.03167,"h":0.03167,"d":0.24,"c":1,"s":1},{"part":"head","x":-0.92104,"y":1.39348,"z":-0.012,"w":0.03167,"h":0.03167,"d":0.24,"c":0,"s":0},{"part":"head","x":-0.75945,"y":1.39348,"z":-0.012,"w":0.03167,"h":0.03167,"d":0.24,"c":0,"s":0},{"part":"head","x":-0.72713,"y":1.39348,"z":0.018,"w":0.03167,"h":0.03167,"d":0.24,"c":3,"s":3},{"part":"head","x":-0.69482,"y":1.39348,"z":0.018,"w":0.03167,"h":0.03167,"d":0.24,"c":2,"s":2},{"part":"head","x":-0.6625,"y":1.39348,"z":0.018,"w":0.03167,"h":0.03167,"d":0.24,"c":2,"s":2},{"part":"head","x":-0.63018,"y":1.39348,"z":-0.012,"w":0.03167,"h":0.03167,"d":0.24,"c":0,"s":0},{"part":"head","x":-0.72713,"y":1.36116,"z":-0.012,"w":0.03167,"h":0.03167,"d":0.24,"c":0,"s":0},{"part":"head","x":-0.69482,"y":1.36116,"z":0.018,"w":0.03167,"h":0.03167,"d":0.24,"c":3,"s":3},{"part":"head","x":-0.6625,"y":1.36116,"z":0.018,"w":0.03167,"h":0.03167,"d":0.24,"c":1,"s":1},{"part":"head","x":-0.63018,"y":1.36116,"z":0.018,"w":0.03167,"h":0.03167,"d":0.24,"c":3,"s":3},{"part":"head","x":-0.79177,"y":1.32884,"z":-0.012,"w":0.03167,"h":0.03167,"d":0.24,"c":0,"s":0},{"part":"head","x":-0.75945,"y":1.32884,"z":0.018,"w":0.03167,"h":0.03167,"d":0.24,"c":3,"s":3},{"part":"head","x":-0.72713,"y":1.32884,"z":-0.012,"w":0.03167,"h":0.03167,"d":0.24,"c":4,"s":4},{"part":"head","x":-0.69482,"y":1.32884,"z":-0.012,"w":0.03167,"h":0.03167,"d":0.24,"c":4,"s":4},{"part":"head","x":-0.6625,"y":1.32884,"z":0.018,"w":0.03167,"h":0.03167,"d":0.24,"c":3,"s":3},{"part":"head","x":-0.63018,"y":1.32884,"z":0.018,"w":0.03167,"h":0.03167,"d":0.24,"c":1,"s":1},{"part":"head","x":-0.59787,"y":1.32884,"z":0.018,"w":0.03167,"h":0.03167,"d":0.24,"c":3,"s":3},{"part":"head","x":-0.82409,"y":1.29652,"z":-0.012,"w":0.03167,"h":0.03167,"d":0.24,"c":0,"s":0},{"part":"head","x":-0.79177,"y":1.29652,"z":0.018,"w":0.03167,"h":0.03167,"d":0.24,"c":1,"s":1},{"part":"head","x":-0.75945,"y":1.29652,"z":0.018,"w":0.03167,"h":0.03167,"d":0.24,"c":1,"s":1},{"part":"head","x":-0.72713,"y":1.29652,"z":0.018,"w":0.03167,"h":0.03167,"d":0.24,"c":1,"s":1},{"part":"head","x":-0.69482,"y":1.29652,"z":0.018,"w":0.03167,"h":0.03167,"d":0.24,"c":3,"s":3},{"part":"head","x":-0.6625,"y":1.29652,"z":-0.012,"w":0.03167,"h":0.03167,"d":0.24,"c":0,"s":0},{"part":"head","x":-0.63018,"y":1.29652,"z":0.018,"w":0.03167,"h":0.03167,"d":0.24,"c":1,"s":1},{"part":"head","x":-0.59787,"y":1.29652,"z":0.018,"w":0.03167,"h":0.03167,"d":0.24,"c":1,"s":1},{"part":"head","x":-0.82409,"y":1.26421,"z":0.018,"w":0.03167,"h":0.03167,"d":0.24,"c":1,"s":1},{"part":"head","x":-0.79177,"y":1.26421,"z":0.018,"w":0.03167,"h":0.03167,"d":0.24,"c":1,"s":1},{"part":"head","x":-0.75945,"y":1.26421,"z":-0.012,"w":0.03167,"h":0.03167,"d":0.24,"c":0,"s":0},{"part":"head","x":-0.72713,"y":1.26421,"z":0.018,"w":0.03167,"h":0.03167,"d":0.24,"c":2,"s":2},{"part":"head","x":-0.69482,"y":1.26421,"z":0.018,"w":0.03167,"h":0.03167,"d":0.24,"c":1,"s":1},{"part":"head","x":-0.6625,"y":1.26421,"z":0.018,"w":0.03167,"h":0.03167,"d":0.24,"c":1,"s":1},{"part":"head","x":-0.63018,"y":1.26421,"z":0.018,"w":0.03167,"h":0.03167,"d":0.24,"c":3,"s":3},{"part":"head","x":-0.59787,"y":1.26421,"z":0.018,"w":0.03167,"h":0.03167,"d":0.24,"c":1,"s":1},{"part":"head","x":-0.56555,"y":1.26421,"z":-0.012,"w":0.03167,"h":0.03167,"d":0.24,"c":0,"s":0},{"part":"head","x":-0.8564,"y":1.23189,"z":-0.012,"w":0.03167,"h":0.03167,"d":0.24,"c":0,"s":0},{"part":"head","x":-0.82409,"y":1.23189,"z":0.018,"w":0.03167,"h":0.03167,"d":0.24,"c":1,"s":1},{"part":"head","x":-0.79177,"y":1.23189,"z":0.018,"w":0.03167,"h":0.03167,"d":0.24,"c":1,"s":1},{"part":"head","x":-0.75945,"y":1.23189,"z":0.018,"w":0.03167,"h":0.03167,"d":0.24,"c":1,"s":1},{"part":"head","x":-0.72713,"y":1.23189,"z":0.018,"w":0.03167,"h":0.03167,"d":0.24,"c":2,"s":2},{"part":"head","x":-0.69482,"y":1.23189,"z":-0.012,"w":0.03167,"h":0.03167,"d":0.24,"c":0,"s":0},{"part":"head","x":-0.6625,"y":1.23189,"z":0.018,"w":0.03167,"h":0.03167,"d":0.24,"c":1,"s":1},{"part":"head","x":-0.63018,"y":1.23189,"z":0.018,"w":0.03167,"h":0.03167,"d":0.24,"c":1,"s":1},{"part":"head","x":-0.59787,"y":1.23189,"z":0.018,"w":0.03167,"h":0.03167,"d":0.24,"c":3,"s":3},{"part":"head","x":-0.56555,"y":1.23189,"z":0.018,"w":0.03167,"h":0.03167,"d":0.24,"c":3,"s":3},{"part":"head","x":-0.8564,"y":1.19957,"z":0.018,"w":0.03167,"h":0.03167,"d":0.24,"c":1,"s":1},{"part":"head","x":-0.82409,"y":1.19957,"z":0.018,"w":0.03167,"h":0.03167,"d":0.24,"c":2,"s":2},{"part":"head","x":-0.79177,"y":1.19957,"z":0.018,"w":0.03167,"h":0.03167,"d":0.24,"c":2,"s":2},{"part":"head","x":-0.75945,"y":1.19957,"z":0.018,"w":0.03167,"h":0.03167,"d":0.24,"c":3,"s":3},{"part":"head","x":-0.72713,"y":1.19957,"z":0.018,"w":0.03167,"h":0.03167,"d":0.24,"c":2,"s":2},{"part":"head","x":-0.69482,"y":1.19957,"z":0.018,"w":0.03167,"h":0.03167,"d":0.24,"c":2,"s":2},{"part":"head","x":-0.6625,"y":1.19957,"z":0.018,"w":0.03167,"h":0.03167,"d":0.24,"c":1,"s":1},{"part":"head","x":-0.63018,"y":1.19957,"z":0.018,"w":0.03167,"h":0.03167,"d":0.24,"c":1,"s":1},{"part":"head","x":-0.59787,"y":1.19957,"z":0.018,"w":0.03167,"h":0.03167,"d":0.24,"c":3,"s":3},{"part":"head","x":-0.56555,"y":1.19957,"z":0.018,"w":0.03167,"h":0.03167,"d":0.24,"c":3,"s":3},{"part":"head","x":-1.27652,"y":1.16726,"z":0.018,"w":0.03167,"h":0.03167,"d":0.24,"c":1,"s":1},{"part":"head","x":-1.24421,"y":1.16726,"z":0.018,"w":0.03167,"h":0.03167,"d":0.24,"c":2,"s":2},{"part":"head","x":-0.88872,"y":1.16726,"z":0.018,"w":0.03167,"h":0.03167,"d":0.24,"c":3,"s":3},{"part":"head","x":-0.8564,"y":1.16726,"z":0.018,"w":0.03167,"h":0.03167,"d":0.24,"c":1,"s":1},{"part":"head","x":-0.82409,"y":1.16726,"z":-0.012,"w":0.03167,"h":0.03167,"d":0.24,"c":0,"s":0},{"part":"head","x":-0.79177,"y":1.16726,"z":0.018,"w":0.03167,"h":0.03167,"d":0.24,"c":2,"s":2},{"part":"head","x":-0.75945,"y":1.16726,"z":0.018,"w":0.03167,"h":0.03167,"d":0.24,"c":3,"s":3},{"part":"head","x":-0.72713,"y":1.16726,"z":0.018,"w":0.03167,"h":0.03167,"d":0.24,"c":1,"s":1},{"part":"head","x":-0.69482,"y":1.16726,"z":0.018,"w":0.03167,"h":0.03167,"d":0.24,"c":1,"s":1},{"part":"head","x":-0.6625,"y":1.16726,"z":0.018,"w":0.03167,"h":0.03167,"d":0.24,"c":3,"s":3},{"part":"head","x":-0.63018,"y":1.16726,"z":0.018,"w":0.03167,"h":0.03167,"d":0.24,"c":1,"s":1},{"part":"head","x":-0.59787,"y":1.16726,"z":0.018,"w":0.03167,"h":0.03167,"d":0.24,"c":3,"s":3},{"part":"head","x":-0.56555,"y":1.16726,"z":0.018,"w":0.03167,"h":0.03167,"d":0.24,"c":3,"s":3},{"part":"head","x":-1.30884,"y":1.13494,"z":0.018,"w":0.03167,"h":0.03167,"d":0.24,"c":3,"s":3},{"part":"head","x":-1.27652,"y":1.13494,"z":0.018,"w":0.03167,"h":0.03167,"d":0.24,"c":3,"s":3},{"part":"head","x":-0.88872,"y":1.13494,"z":-0.012,"w":0.03167,"h":0.03167,"d":0.24,"c":0,"s":0},{"part":"head","x":-0.8564,"y":1.13494,"z":0.018,"w":0.03167,"h":0.03167,"d":0.24,"c":3,"s":3},{"part":"head","x":-0.82409,"y":1.13494,"z":-0.012,"w":0.03167,"h":0.03167,"d":0.24,"c":4,"s":4},{"part":"head","x":-0.79177,"y":1.13494,"z":0.018,"w":0.03167,"h":0.03167,"d":0.24,"c":1,"s":1},{"part":"head","x":-0.75945,"y":1.13494,"z":-0.012,"w":0.03167,"h":0.03167,"d":0.24,"c":4,"s":4},{"part":"head","x":-0.72713,"y":1.13494,"z":-0.012,"w":0.03167,"h":0.03167,"d":0.24,"c":4,"s":4},{"part":"head","x":-0.69482,"y":1.13494,"z":0.018,"w":0.03167,"h":0.03167,"d":0.24,"c":2,"s":2},{"part":"head","x":-0.6625,"y":1.13494,"z":0.018,"w":0.03167,"h":0.03167,"d":0.24,"c":2,"s":2},{"part":"head","x":-0.63018,"y":1.13494,"z":0.018,"w":0.03167,"h":0.03167,"d":0.24,"c":3,"s":3},{"part":"head","x":-0.59787,"y":1.13494,"z":-0.012,"w":0.03167,"h":0.03167,"d":0.24,"c":0,"s":0},{"part":"head","x":-0.56555,"y":1.13494,"z":0.018,"w":0.03167,"h":0.03167,"d":0.24,"c":3,"s":3},{"part":"head","x":-1.30884,"y":1.10262,"z":0.018,"w":0.03167,"h":0.03167,"d":0.24,"c":3,"s":3},{"part":"head","x":-1.27652,"y":1.10262,"z":-0.012,"w":0.03167,"h":0.03167,"d":0.24,"c":0,"s":0},{"part":"head","x":-1.24421,"y":1.10262,"z":0.018,"w":0.03167,"h":0.03167,"d":0.24,"c":3,"s":3},{"part":"head","x":-0.98567,"y":1.10262,"z":0.018,"w":0.03167,"h":0.03167,"d":0.24,"c":3,"s":3},{"part":"head","x":-0.95335,"y":1.10262,"z":0.018,"w":0.03167,"h":0.03167,"d":0.24,"c":2,"s":2},{"part":"head","x":-0.92104,"y":1.10262,"z":0.018,"w":0.03167,"h":0.03167,"d":0.24,"c":1,"s":1},{"part":"head","x":-0.88872,"y":1.10262,"z":-0.012,"w":0.03167,"h":0.03167,"d":0.24,"c":4,"s":4},{"part":"head","x":-0.8564,"y":1.10262,"z":0.018,"w":0.03167,"h":0.03167,"d":0.24,"c":3,"s":3},{"part":"head","x":-0.82409,"y":1.10262,"z":-0.012,"w":0.03167,"h":0.03167,"d":0.24,"c":0,"s":0},{"part":"head","x":-0.79177,"y":1.10262,"z":0.018,"w":0.03167,"h":0.03167,"d":0.24,"c":1,"s":1},{"part":"head","x":-0.75945,"y":1.10262,"z":0.018,"w":0.03167,"h":0.03167,"d":0.24,"c":3,"s":3},{"part":"head","x":-0.72713,"y":1.10262,"z":-0.012,"w":0.03167,"h":0.03167,"d":0.24,"c":0,"s":0},{"part":"head","x":-0.69482,"y":1.10262,"z":-0.012,"w":0.03167,"h":0.03167,"d":0.24,"c":4,"s":4},{"part":"head","x":-0.6625,"y":1.10262,"z":-0.012,"w":0.03167,"h":0.03167,"d":0.24,"c":4,"s":4},{"part":"head","x":-0.63018,"y":1.10262,"z":0.018,"w":0.03167,"h":0.03167,"d":0.24,"c":3,"s":3},{"part":"head","x":-0.59787,"y":1.10262,"z":-0.012,"w":0.03167,"h":0.03167,"d":0.24,"c":0,"s":0},{"part":"head","x":-1.30884,"y":1.0703,"z":0.018,"w":0.03167,"h":0.03167,"d":0.24,"c":3,"s":3},{"part":"head","x":-1.27652,"y":1.0703,"z":0.018,"w":0.03167,"h":0.03167,"d":0.24,"c":1,"s":1},{"part":"head","x":-1.24421,"y":1.0703,"z":0.018,"w":0.03167,"h":0.03167,"d":0.24,"c":1,"s":1},{"part":"head","x":-1.17957,"y":1.0703,"z":0.018,"w":0.03167,"h":0.03167,"d":0.24,"c":2,"s":2},{"part":"head","x":-1.01799,"y":1.0703,"z":0.018,"w":0.03167,"h":0.03167,"d":0.24,"c":3,"s":3},{"part":"head","x":-0.98567,"y":1.0703,"z":-0.012,"w":0.03167,"h":0.03167,"d":0.24,"c":0,"s":0},{"part":"head","x":-0.95335,"y":1.0703,"z":0.018,"w":0.03167,"h":0.03167,"d":0.24,"c":1,"s":1},{"part":"head","x":-0.92104,"y":1.0703,"z":0.018,"w":0.03167,"h":0.03167,"d":0.24,"c":1,"s":1},{"part":"head","x":-0.88872,"y":1.0703,"z":0.018,"w":0.03167,"h":0.03167,"d":0.24,"c":3,"s":3},{"part":"head","x":-0.8564,"y":1.0703,"z":-0.012,"w":0.03167,"h":0.03167,"d":0.24,"c":4,"s":4},{"part":"head","x":-0.82409,"y":1.0703,"z":-0.012,"w":0.03167,"h":0.03167,"d":0.24,"c":4,"s":4},{"part":"head","x":-0.79177,"y":1.0703,"z":0.018,"w":0.03167,"h":0.03167,"d":0.24,"c":1,"s":1},{"part":"head","x":-0.75945,"y":1.0703,"z":0.018,"w":0.03167,"h":0.03167,"d":0.24,"c":1,"s":1},{"part":"head","x":-0.72713,"y":1.0703,"z":0.018,"w":0.03167,"h":0.03167,"d":0.24,"c":3,"s":3},{"part":"head","x":-0.69482,"y":1.0703,"z":-0.012,"w":0.03167,"h":0.03167,"d":0.24,"c":4,"s":4},{"part":"head","x":-0.6625,"y":1.0703,"z":0.018,"w":0.03167,"h":0.03167,"d":0.24,"c":5,"s":5},{"part":"head","x":-1.30884,"y":1.03799,"z":0.018,"w":0.03167,"h":0.03167,"d":0.24,"c":3,"s":3},{"part":"head","x":-1.27652,"y":1.03799,"z":0.018,"w":0.03167,"h":0.03167,"d":0.24,"c":1,"s":1},{"part":"head","x":-1.24421,"y":1.03799,"z":0.018,"w":0.03167,"h":0.03167,"d":0.24,"c":3,"s":3},{"part":"head","x":-1.17957,"y":1.03799,"z":0.018,"w":0.03167,"h":0.03167,"d":0.24,"c":1,"s":1},{"part":"head","x":-1.0503,"y":1.03799,"z":-0.012,"w":0.03167,"h":0.03167,"d":0.24,"c":0,"s":0},{"part":"head","x":-1.01799,"y":1.03799,"z":0.018,"w":0.03167,"h":0.03167,"d":0.24,"c":3,"s":3},{"part":"head","x":-0.98567,"y":1.03799,"z":0.018,"w":0.03167,"h":0.03167,"d":0.24,"c":1,"s":1},{"part":"head","x":-0.95335,"y":1.03799,"z":0.018,"w":0.03167,"h":0.03167,"d":0.24,"c":1,"s":1},{"part":"head","x":-0.92104,"y":1.03799,"z":0.018,"w":0.03167,"h":0.03167,"d":0.24,"c":3,"s":3},{"part":"head","x":-0.88872,"y":1.03799,"z":0.018,"w":0.03167,"h":0.03167,"d":0.24,"c":1,"s":1},{"part":"head","x":-0.8564,"y":1.03799,"z":0.018,"w":0.03167,"h":0.03167,"d":0.24,"c":2,"s":2},{"part":"head","x":-0.82409,"y":1.03799,"z":0.018,"w":0.03167,"h":0.03167,"d":0.24,"c":3,"s":3},{"part":"head","x":-0.79177,"y":1.03799,"z":-0.012,"w":0.03167,"h":0.03167,"d":0.24,"c":4,"s":4},{"part":"head","x":-0.75945,"y":1.03799,"z":0.018,"w":0.03167,"h":0.03167,"d":0.24,"c":1,"s":1},{"part":"head","x":-0.72713,"y":1.03799,"z":-0.012,"w":0.03167,"h":0.03167,"d":0.24,"c":0,"s":0},{"part":"head","x":-0.69482,"y":1.03799,"z":0.018,"w":0.03167,"h":0.03167,"d":0.24,"c":3,"s":3},{"part":"head","x":-0.6625,"y":1.03799,"z":0.018,"w":0.03167,"h":0.03167,"d":0.24,"c":3,"s":3},{"part":"head","x":-0.63018,"y":1.03799,"z":-0.012,"w":0.03167,"h":0.03167,"d":0.24,"c":0,"s":0},{"part":"rearArm","x":-1.30884,"y":1.00567,"z":-0.012,"w":0.03167,"h":0.03167,"d":0.24,"c":0,"s":0},{"part":"rearArm","x":-1.27652,"y":1.00567,"z":0.018,"w":0.03167,"h":0.03167,"d":0.24,"c":1,"s":1},{"part":"rearArm","x":-1.24421,"y":1.00567,"z":-0.012,"w":0.03167,"h":0.03167,"d":0.24,"c":4,"s":4},{"part":"rearArm","x":-1.21189,"y":1.00567,"z":-0.012,"w":0.03167,"h":0.03167,"d":0.24,"c":0,"s":0},{"part":"rearArm","x":-1.17957,"y":1.00567,"z":0.018,"w":0.03167,"h":0.03167,"d":0.24,"c":3,"s":3},{"part":"rearArm","x":-1.0503,"y":1.00567,"z":0.018,"w":0.03167,"h":0.03167,"d":0.24,"c":3,"s":3},{"part":"rearArm","x":-1.01799,"y":1.00567,"z":-0.012,"w":0.03167,"h":0.03167,"d":0.24,"c":0,"s":0},{"part":"rearArm","x":-0.98567,"y":1.00567,"z":0.018,"w":0.03167,"h":0.03167,"d":0.24,"c":3,"s":3},{"part":"rearArm","x":-0.95335,"y":1.00567,"z":0.018,"w":0.03167,"h":0.03167,"d":0.24,"c":3,"s":3},{"part":"rearArm","x":-0.92104,"y":1.00567,"z":-0.012,"w":0.03167,"h":0.03167,"d":0.24,"c":0,"s":0},{"part":"rearArm","x":-0.88872,"y":1.00567,"z":0.018,"w":0.03167,"h":0.03167,"d":0.24,"c":3,"s":3},{"part":"rearArm","x":-0.8564,"y":1.00567,"z":0.018,"w":0.03167,"h":0.03167,"d":0.24,"c":1,"s":1},{"part":"rearArm","x":-0.82409,"y":1.00567,"z":0.018,"w":0.03167,"h":0.03167,"d":0.24,"c":1,"s":1},{"part":"rearArm","x":-0.79177,"y":1.00567,"z":0.018,"w":0.03167,"h":0.03167,"d":0.24,"c":3,"s":3},{"part":"rearArm","x":-0.75945,"y":1.00567,"z":-0.012,"w":0.03167,"h":0.03167,"d":0.24,"c":4,"s":4},{"part":"rearArm","x":-0.72713,"y":1.00567,"z":-0.012,"w":0.03167,"h":0.03167,"d":0.24,"c":6,"s":6},{"part":"rearArm","x":-0.69482,"y":1.00567,"z":0.018,"w":0.03167,"h":0.03167,"d":0.24,"c":7,"s":7},{"part":"torso","x":-0.6625,"y":1.00567,"z":0.018,"w":0.03167,"h":0.03167,"d":0.24,"c":5,"s":5},{"part":"rearArm","x":-1.27652,"y":0.97335,"z":0.018,"w":0.03167,"h":0.03167,"d":0.24,"c":3,"s":3},{"part":"rearArm","x":-1.24421,"y":0.97335,"z":-0.012,"w":0.03167,"h":0.03167,"d":0.24,"c":0,"s":0},{"part":"rearArm","x":-1.21189,"y":0.97335,"z":0.018,"w":0.03167,"h":0.03167,"d":0.24,"c":3,"s":3},{"part":"rearArm","x":-1.17957,"y":0.97335,"z":0.018,"w":0.03167,"h":0.03167,"d":0.24,"c":8,"s":8},{"part":"rearArm","x":-1.08262,"y":0.97335,"z":-0.012,"w":0.03167,"h":0.03167,"d":0.24,"c":0,"s":0},{"part":"rearArm","x":-1.0503,"y":0.97335,"z":0.018,"w":0.03167,"h":0.03167,"d":0.24,"c":1,"s":1},{"part":"rearArm","x":-1.01799,"y":0.97335,"z":0.018,"w":0.03167,"h":0.03167,"d":0.24,"c":1,"s":1},{"part":"rearArm","x":-0.98567,"y":0.97335,"z":0.018,"w":0.03167,"h":0.03167,"d":0.24,"c":3,"s":3},{"part":"rearArm","x":-0.95335,"y":0.97335,"z":-0.012,"w":0.03167,"h":0.03167,"d":0.24,"c":0,"s":0},{"part":"rearArm","x":-0.92104,"y":0.97335,"z":-0.012,"w":0.03167,"h":0.03167,"d":0.24,"c":4,"s":4},{"part":"rearArm","x":-0.88872,"y":0.97335,"z":-0.012,"w":0.03167,"h":0.03167,"d":0.24,"c":0,"s":0},{"part":"rearArm","x":-0.8564,"y":0.97335,"z":0.018,"w":0.03167,"h":0.03167,"d":0.24,"c":1,"s":1},{"part":"rearArm","x":-0.82409,"y":0.97335,"z":-0.012,"w":0.03167,"h":0.03167,"d":0.24,"c":0,"s":0},{"part":"rearArm","x":-0.79177,"y":0.97335,"z":0.018,"w":0.03167,"h":0.03167,"d":0.24,"c":1,"s":1},{"part":"rearArm","x":-0.75945,"y":0.97335,"z":0.018,"w":0.03167,"h":0.03167,"d":0.24,"c":3,"s":3},{"part":"rearArm","x":-0.72713,"y":0.97335,"z":-0.012,"w":0.03167,"h":0.03167,"d":0.24,"c":4,"s":4},{"part":"rearArm","x":-0.69482,"y":0.97335,"z":-0.012,"w":0.03167,"h":0.03167,"d":0.24,"c":4,"s":4},{"part":"torso","x":-0.6625,"y":0.97335,"z":-0.012,"w":0.03167,"h":0.03167,"d":0.24,"c":4,"s":4},{"part":"torso","x":-0.63018,"y":0.97335,"z":0.018,"w":0.03167,"h":0.03167,"d":0.24,"c":3,"s":3},{"part":"torso","x":-0.50091,"y":0.97335,"z":0.018,"w":0.03167,"h":0.03167,"d":0.24,"c":1,"s":1},{"part":"torso","x":-0.4686,"y":0.97335,"z":0.018,"w":0.03167,"h":0.03167,"d":0.24,"c":1,"s":1},{"part":"rearArm","x":-1.27652,"y":0.94104,"z":-0.012,"w":0.03167,"h":0.03167,"d":0.24,"c":0,"s":0},{"part":"rearArm","x":-1.24421,"y":0.94104,"z":0.018,"w":0.03167,"h":0.03167,"d":0.24,"c":3,"s":3},{"part":"rearArm","x":-1.21189,"y":0.94104,"z":0.018,"w":0.03167,"h":0.03167,"d":0.24,"c":3,"s":3},{"part":"rearArm","x":-1.17957,"y":0.94104,"z":-0.012,"w":0.03167,"h":0.03167,"d":0.24,"c":9,"s":9},{"part":"rearArm","x":-1.08262,"y":0.94104,"z":0.018,"w":0.03167,"h":0.03167,"d":0.24,"c":3,"s":3},{"part":"rearArm","x":-1.0503,"y":0.94104,"z":-0.012,"w":0.03167,"h":0.03167,"d":0.24,"c":0,"s":0},{"part":"rearArm","x":-1.01799,"y":0.94104,"z":0.018,"w":0.03167,"h":0.03167,"d":0.24,"c":1,"s":1},{"part":"rearArm","x":-0.98567,"y":0.94104,"z":-0.012,"w":0.03167,"h":0.03167,"d":0.24,"c":0,"s":0},{"part":"rearArm","x":-0.92104,"y":0.94104,"z":-0.012,"w":0.03167,"h":0.03167,"d":0.24,"c":0,"s":0},{"part":"rearArm","x":-0.88872,"y":0.94104,"z":-0.012,"w":0.03167,"h":0.03167,"d":0.24,"c":0,"s":0},{"part":"rearArm","x":-0.8564,"y":0.94104,"z":0.018,"w":0.03167,"h":0.03167,"d":0.24,"c":3,"s":3},{"part":"rearArm","x":-0.82409,"y":0.94104,"z":0.018,"w":0.03167,"h":0.03167,"d":0.24,"c":1,"s":1},{"part":"rearArm","x":-0.79177,"y":0.94104,"z":0.018,"w":0.03167,"h":0.03167,"d":0.24,"c":1,"s":1},{"part":"rearArm","x":-0.75945,"y":0.94104,"z":-0.012,"w":0.03167,"h":0.03167,"d":0.24,"c":0,"s":0},{"part":"rearArm","x":-0.72713,"y":0.94104,"z":0.018,"w":0.03167,"h":0.03167,"d":0.24,"c":2,"s":2},{"part":"rearArm","x":-0.69482,"y":0.94104,"z":0.018,"w":0.03167,"h":0.03167,"d":0.24,"c":1,"s":1},{"part":"torso","x":-0.6625,"y":0.94104,"z":0.018,"w":0.03167,"h":0.03167,"d":0.24,"c":3,"s":3},{"part":"torso","x":-0.63018,"y":0.94104,"z":-0.012,"w":0.03167,"h":0.03167,"d":0.24,"c":0,"s":0},{"part":"torso","x":-0.59787,"y":0.94104,"z":-0.012,"w":0.03167,"h":0.03167,"d":0.24,"c":0,"s":0},{"part":"torso","x":-0.53323,"y":0.94104,"z":-0.012,"w":0.03167,"h":0.03167,"d":0.24,"c":0,"s":0},{"part":"torso","x":-0.50091,"y":0.94104,"z":0.018,"w":0.03167,"h":0.03167,"d":0.24,"c":3,"s":3},{"part":"torso","x":-0.4686,"y":0.94104,"z":0.018,"w":0.03167,"h":0.03167,"d":0.24,"c":1,"s":1},{"part":"rearArm","x":-1.24421,"y":0.90872,"z":-0.012,"w":0.03167,"h":0.03167,"d":0.24,"c":0,"s":0},{"part":"rearArm","x":-1.21189,"y":0.90872,"z":-0.012,"w":0.03167,"h":0.03167,"d":0.24,"c":10,"s":10},{"part":"rearArm","x":-1.0503,"y":0.90872,"z":0.018,"w":0.03167,"h":0.03167,"d":0.24,"c":3,"s":3},{"part":"rearArm","x":-1.01799,"y":0.90872,"z":0.018,"w":0.03167,"h":0.03167,"d":0.24,"c":3,"s":3},{"part":"rearArm","x":-0.92104,"y":0.90872,"z":-0.012,"w":0.03167,"h":0.03167,"d":0.24,"c":0,"s":0},{"part":"rearArm","x":-0.88872,"y":0.90872,"z":-0.012,"w":0.03167,"h":0.03167,"d":0.24,"c":0,"s":0},{"part":"rearArm","x":-0.8564,"y":0.90872,"z":-0.012,"w":0.03167,"h":0.03167,"d":0.24,"c":0,"s":0},{"part":"rearArm","x":-0.82409,"y":0.90872,"z":0.018,"w":0.03167,"h":0.03167,"d":0.24,"c":3,"s":3},{"part":"rearArm","x":-0.79177,"y":0.90872,"z":0.018,"w":0.03167,"h":0.03167,"d":0.24,"c":3,"s":3},{"part":"rearArm","x":-0.75945,"y":0.90872,"z":0.018,"w":0.03167,"h":0.03167,"d":0.24,"c":1,"s":1},{"part":"rearArm","x":-0.72713,"y":0.90872,"z":0.018,"w":0.03167,"h":0.03167,"d":0.24,"c":1,"s":1},{"part":"rearArm","x":-0.69482,"y":0.90872,"z":0.018,"w":0.03167,"h":0.03167,"d":0.24,"c":2,"s":2},{"part":"torso","x":-0.6625,"y":0.90872,"z":0.018,"w":0.03167,"h":0.03167,"d":0.24,"c":1,"s":1},{"part":"torso","x":-0.63018,"y":0.90872,"z":0.018,"w":0.03167,"h":0.03167,"d":0.24,"c":1,"s":1},{"part":"torso","x":-0.59787,"y":0.90872,"z":0.018,"w":0.03167,"h":0.03167,"d":0.24,"c":3,"s":3},{"part":"torso","x":-0.50091,"y":0.90872,"z":0.018,"w":0.03167,"h":0.03167,"d":0.24,"c":1,"s":1},{"part":"torso","x":-0.4686,"y":0.90872,"z":0.018,"w":0.03167,"h":0.03167,"d":0.24,"c":3,"s":3},{"part":"rearArm","x":-1.08262,"y":0.8764,"z":0.018,"w":0.03167,"h":0.03167,"d":0.24,"c":8,"s":8},{"part":"rearArm","x":-1.0503,"y":0.8764,"z":0.018,"w":0.03167,"h":0.03167,"d":0.24,"c":3,"s":3},{"part":"rearArm","x":-0.88872,"y":0.8764,"z":-0.012,"w":0.03167,"h":0.03167,"d":0.24,"c":0,"s":0},{"part":"rearArm","x":-0.8564,"y":0.8764,"z":-0.012,"w":0.03167,"h":0.03167,"d":0.24,"c":0,"s":0},{"part":"rearArm","x":-0.82409,"y":0.8764,"z":-0.012,"w":0.03167,"h":0.03167,"d":0.24,"c":0,"s":0},{"part":"rearArm","x":-0.79177,"y":0.8764,"z":0.018,"w":0.03167,"h":0.03167,"d":0.24,"c":3,"s":3},{"part":"rearArm","x":-0.75945,"y":0.8764,"z":0.018,"w":0.03167,"h":0.03167,"d":0.24,"c":3,"s":3},{"part":"rearArm","x":-0.72713,"y":0.8764,"z":0.018,"w":0.03167,"h":0.03167,"d":0.24,"c":1,"s":1},{"part":"rearArm","x":-0.69482,"y":0.8764,"z":0.018,"w":0.03167,"h":0.03167,"d":0.24,"c":1,"s":1},{"part":"torso","x":-0.6625,"y":0.8764,"z":0.018,"w":0.03167,"h":0.03167,"d":0.24,"c":1,"s":1},{"part":"torso","x":-0.63018,"y":0.8764,"z":0.018,"w":0.03167,"h":0.03167,"d":0.24,"c":3,"s":3},{"part":"torso","x":-0.59787,"y":0.8764,"z":0.018,"w":0.03167,"h":0.03167,"d":0.24,"c":3,"s":3},{"part":"torso","x":-0.53323,"y":0.8764,"z":-0.012,"w":0.03167,"h":0.03167,"d":0.24,"c":0,"s":0},{"part":"torso","x":-0.50091,"y":0.8764,"z":0.018,"w":0.03167,"h":0.03167,"d":0.24,"c":3,"s":3},{"part":"rearArm","x":-1.08262,"y":0.84409,"z":-0.012,"w":0.03167,"h":0.03167,"d":0.24,"c":9,"s":9},{"part":"rearArm","x":-0.88872,"y":0.84409,"z":-0.012,"w":0.03167,"h":0.03167,"d":0.24,"c":0,"s":0},{"part":"rearArm","x":-0.8564,"y":0.84409,"z":0.018,"w":0.03167,"h":0.03167,"d":0.24,"c":3,"s":3},{"part":"rearArm","x":-0.82409,"y":0.84409,"z":-0.012,"w":0.03167,"h":0.03167,"d":0.24,"c":0,"s":0},{"part":"rearArm","x":-0.79177,"y":0.84409,"z":-0.012,"w":0.03167,"h":0.03167,"d":0.24,"c":0,"s":0},{"part":"rearArm","x":-0.75945,"y":0.84409,"z":-0.012,"w":0.03167,"h":0.03167,"d":0.24,"c":0,"s":0},{"part":"rearArm","x":-0.72713,"y":0.84409,"z":0.018,"w":0.03167,"h":0.03167,"d":0.24,"c":3,"s":3},{"part":"rearArm","x":-0.69482,"y":0.84409,"z":0.018,"w":0.03167,"h":0.03167,"d":0.24,"c":3,"s":3},{"part":"torso","x":-0.6625,"y":0.84409,"z":-0.012,"w":0.03167,"h":0.03167,"d":0.24,"c":0,"s":0},{"part":"torso","x":-0.63018,"y":0.84409,"z":-0.012,"w":0.03167,"h":0.03167,"d":0.24,"c":0,"s":0},{"part":"torso","x":-0.59787,"y":0.84409,"z":-0.012,"w":0.03167,"h":0.03167,"d":0.24,"c":0,"s":0},{"part":"torso","x":-0.53323,"y":0.84409,"z":0.018,"w":0.03167,"h":0.03167,"d":0.24,"c":8,"s":8},{"part":"torso","x":-0.50091,"y":0.84409,"z":-0.012,"w":0.03167,"h":0.03167,"d":0.24,"c":0,"s":0},{"part":"rearArm","x":-1.11494,"y":0.81177,"z":-0.012,"w":0.03167,"h":0.03167,"d":0.24,"c":10,"s":10},{"part":"rearArm","x":-0.8564,"y":0.81177,"z":-0.012,"w":0.03167,"h":0.03167,"d":0.24,"c":0,"s":0},{"part":"rearArm","x":-0.82409,"y":0.81177,"z":0.018,"w":0.03167,"h":0.03167,"d":0.24,"c":3,"s":3},{"part":"rearArm","x":-0.79177,"y":0.81177,"z":0.018,"w":0.03167,"h":0.03167,"d":0.24,"c":3,"s":3},{"part":"rearArm","x":-0.75945,"y":0.81177,"z":0.018,"w":0.03167,"h":0.03167,"d":0.24,"c":3,"s":3},{"part":"rearArm","x":-0.72713,"y":0.81177,"z":0.018,"w":0.03167,"h":0.03167,"d":0.24,"c":3,"s":3},{"part":"rearArm","x":-0.69482,"y":0.81177,"z":0.018,"w":0.03167,"h":0.03167,"d":0.24,"c":3,"s":3},{"part":"torso","x":-0.6625,"y":0.81177,"z":0.018,"w":0.03167,"h":0.03167,"d":0.24,"c":3,"s":3},{"part":"torso","x":-0.63018,"y":0.81177,"z":-0.012,"w":0.03167,"h":0.03167,"d":0.24,"c":0,"s":0},{"part":"torso","x":-0.59787,"y":0.81177,"z":0.018,"w":0.03167,"h":0.03167,"d":0.24,"c":3,"s":3},{"part":"torso","x":-0.53323,"y":0.81177,"z":-0.012,"w":0.03167,"h":0.03167,"d":0.24,"c":9,"s":9},{"part":"rearArm","x":-0.82409,"y":0.77945,"z":-0.012,"w":0.03167,"h":0.03167,"d":0.24,"c":0,"s":0},{"part":"rearArm","x":-0.79177,"y":0.77945,"z":0.018,"w":0.03167,"h":0.03167,"d":0.24,"c":3,"s":3},{"part":"rearArm","x":-0.75945,"y":0.77945,"z":0.018,"w":0.03167,"h":0.03167,"d":0.24,"c":1,"s":1},{"part":"rearArm","x":-0.72713,"y":0.77945,"z":0.018,"w":0.03167,"h":0.03167,"d":0.24,"c":1,"s":1},{"part":"rearArm","x":-0.69482,"y":0.77945,"z":0.018,"w":0.03167,"h":0.03167,"d":0.24,"c":1,"s":1},{"part":"torso","x":-0.6625,"y":0.77945,"z":0.018,"w":0.03167,"h":0.03167,"d":0.24,"c":1,"s":1},{"part":"torso","x":-0.63018,"y":0.77945,"z":0.018,"w":0.03167,"h":0.03167,"d":0.24,"c":3,"s":3},{"part":"torso","x":-0.59787,"y":0.77945,"z":0.018,"w":0.03167,"h":0.03167,"d":0.24,"c":1,"s":1},{"part":"rearArm","x":-0.79177,"y":0.74713,"z":-0.012,"w":0.03167,"h":0.03167,"d":0.24,"c":0,"s":0},{"part":"rearArm","x":-0.75945,"y":0.74713,"z":0.018,"w":0.03167,"h":0.03167,"d":0.24,"c":3,"s":3},{"part":"rearArm","x":-0.72713,"y":0.74713,"z":0.018,"w":0.03167,"h":0.03167,"d":0.24,"c":1,"s":1},{"part":"rearArm","x":-0.69482,"y":0.74713,"z":0.018,"w":0.03167,"h":0.03167,"d":0.24,"c":2,"s":2},{"part":"torso","x":-0.6625,"y":0.74713,"z":0.018,"w":0.03167,"h":0.03167,"d":0.24,"c":1,"s":1},{"part":"torso","x":-0.63018,"y":0.74713,"z":-0.012,"w":0.03167,"h":0.03167,"d":0.24,"c":0,"s":0},{"part":"torso","x":-0.59787,"y":0.74713,"z":0.018,"w":0.03167,"h":0.03167,"d":0.24,"c":3,"s":3},{"part":"rearArm","x":-0.75945,"y":0.71482,"z":0.018,"w":0.03167,"h":0.03167,"d":0.24,"c":3,"s":3},{"part":"rearArm","x":-0.72713,"y":0.71482,"z":0.018,"w":0.03167,"h":0.03167,"d":0.24,"c":3,"s":3},{"part":"rearArm","x":-0.69482,"y":0.71482,"z":0.018,"w":0.03167,"h":0.03167,"d":0.24,"c":1,"s":1},{"part":"torso","x":-0.6625,"y":0.71482,"z":0.018,"w":0.03167,"h":0.03167,"d":0.24,"c":2,"s":2},{"part":"torso","x":-0.63018,"y":0.71482,"z":-0.012,"w":0.03167,"h":0.03167,"d":0.24,"c":0,"s":0},{"part":"torso","x":0.43628,"y":0.71482,"z":0.018,"w":0.03167,"h":0.03167,"d":0.24,"c":11,"s":11},{"part":"torso","x":0.4686,"y":0.71482,"z":0.018,"w":0.03167,"h":0.03167,"d":0.24,"c":5,"s":5},{"part":"torso","x":0.50091,"y":0.71482,"z":0.018,"w":0.03167,"h":0.03167,"d":0.24,"c":5,"s":5},{"part":"torso","x":0.53323,"y":0.71482,"z":0.018,"w":0.03167,"h":0.03167,"d":0.24,"c":7,"s":7},{"part":"torso","x":0.56555,"y":0.71482,"z":0.018,"w":0.03167,"h":0.03167,"d":0.24,"c":7,"s":7},{"part":"torso","x":0.59787,"y":0.71482,"z":0.018,"w":0.03167,"h":0.03167,"d":0.24,"c":7,"s":7},{"part":"torso","x":0.63018,"y":0.71482,"z":0.018,"w":0.03167,"h":0.03167,"d":0.24,"c":7,"s":7},{"part":"torso","x":0.6625,"y":0.71482,"z":0.018,"w":0.03167,"h":0.03167,"d":0.24,"c":7,"s":7},{"part":"leadArm","x":0.69482,"y":0.71482,"z":0.018,"w":0.03167,"h":0.03167,"d":0.24,"c":7,"s":7},{"part":"leadArm","x":0.72713,"y":0.71482,"z":0.018,"w":0.03167,"h":0.03167,"d":0.24,"c":7,"s":7},{"part":"leadArm","x":0.75945,"y":0.71482,"z":0.018,"w":0.03167,"h":0.03167,"d":0.24,"c":7,"s":7},{"part":"leadArm","x":0.79177,"y":0.71482,"z":0.018,"w":0.03167,"h":0.03167,"d":0.24,"c":7,"s":7},{"part":"leadArm","x":0.82409,"y":0.71482,"z":0.018,"w":0.03167,"h":0.03167,"d":0.24,"c":7,"s":7},{"part":"leadArm","x":0.8564,"y":0.71482,"z":0.018,"w":0.03167,"h":0.03167,"d":0.24,"c":7,"s":7},{"part":"leadArm","x":0.88872,"y":0.71482,"z":0.018,"w":0.03167,"h":0.03167,"d":0.24,"c":7,"s":7},{"part":"leadArm","x":0.92104,"y":0.71482,"z":0.018,"w":0.03167,"h":0.03167,"d":0.24,"c":7,"s":7},{"part":"leadArm","x":0.95335,"y":0.71482,"z":0.018,"w":0.03167,"h":0.03167,"d":0.24,"c":7,"s":7},{"part":"leadArm","x":0.98567,"y":0.71482,"z":0.018,"w":0.03167,"h":0.03167,"d":0.24,"c":7,"s":7},{"part":"leadArm","x":1.01799,"y":0.71482,"z":0.018,"w":0.03167,"h":0.03167,"d":0.24,"c":7,"s":7},{"part":"leadArm","x":1.0503,"y":0.71482,"z":0.018,"w":0.03167,"h":0.03167,"d":0.24,"c":7,"s":7},{"part":"leadArm","x":1.08262,"y":0.71482,"z":0.018,"w":0.03167,"h":0.03167,"d":0.24,"c":5,"s":5},{"part":"leadArm","x":1.11494,"y":0.71482,"z":0.018,"w":0.03167,"h":0.03167,"d":0.24,"c":11,"s":11},{"part":"torso","x":-0.53323,"y":0.6825,"z":0.018,"w":0.03167,"h":0.03167,"d":0.24,"c":5,"s":5},{"part":"torso","x":-0.50091,"y":0.6825,"z":0.018,"w":0.03167,"h":0.03167,"d":0.24,"c":5,"s":5},{"part":"torso","x":-0.4686,"y":0.6825,"z":0.018,"w":0.03167,"h":0.03167,"d":0.24,"c":11,"s":11},{"part":"torso","x":-0.21006,"y":0.6825,"z":0.018,"w":0.03167,"h":0.03167,"d":0.24,"c":11,"s":11},{"part":"torso","x":-0.17774,"y":0.6825,"z":0.018,"w":0.03167,"h":0.03167,"d":0.24,"c":5,"s":5},{"part":"torso","x":-0.14543,"y":0.6825,"z":0.018,"w":0.03167,"h":0.03167,"d":0.24,"c":7,"s":7},{"part":"torso","x":-0.11311,"y":0.6825,"z":0.018,"w":0.03167,"h":0.03167,"d":0.24,"c":7,"s":7},{"part":"torso","x":-0.08079,"y":0.6825,"z":0.018,"w":0.03167,"h":0.03167,"d":0.24,"c":7,"s":7},{"part":"torso","x":-0.04848,"y":0.6825,"z":0.018,"w":0.03167,"h":0.03167,"d":0.24,"c":7,"s":7},{"part":"torso","x":-0.01616,"y":0.6825,"z":0.018,"w":0.03167,"h":0.03167,"d":0.24,"c":7,"s":7},{"part":"torso","x":0.01616,"y":0.6825,"z":0.018,"w":0.03167,"h":0.03167,"d":0.24,"c":7,"s":7},{"part":"torso","x":0.04848,"y":0.6825,"z":0.018,"w":0.03167,"h":0.03167,"d":0.24,"c":7,"s":7},{"part":"torso","x":0.08079,"y":0.6825,"z":0.018,"w":0.03167,"h":0.03167,"d":0.24,"c":7,"s":7},{"part":"torso","x":0.11311,"y":0.6825,"z":0.018,"w":0.03167,"h":0.03167,"d":0.24,"c":7,"s":7},{"part":"torso","x":0.14543,"y":0.6825,"z":0.018,"w":0.03167,"h":0.03167,"d":0.24,"c":7,"s":7},{"part":"torso","x":0.17774,"y":0.6825,"z":0.018,"w":0.03167,"h":0.03167,"d":0.24,"c":7,"s":7},{"part":"torso","x":0.21006,"y":0.6825,"z":0.018,"w":0.03167,"h":0.03167,"d":0.24,"c":7,"s":7},{"part":"torso","x":0.24238,"y":0.6825,"z":0.018,"w":0.03167,"h":0.03167,"d":0.24,"c":7,"s":7},{"part":"torso","x":0.2747,"y":0.6825,"z":0.018,"w":0.03167,"h":0.03167,"d":0.24,"c":7,"s":7},{"part":"torso","x":0.30701,"y":0.6825,"z":0.018,"w":0.03167,"h":0.03167,"d":0.24,"c":7,"s":7},{"part":"torso","x":0.33933,"y":0.6825,"z":0.018,"w":0.03167,"h":0.03167,"d":0.24,"c":7,"s":7},{"part":"torso","x":0.37165,"y":0.6825,"z":0.018,"w":0.03167,"h":0.03167,"d":0.24,"c":7,"s":7},{"part":"torso","x":0.40396,"y":0.6825,"z":0.018,"w":0.03167,"h":0.03167,"d":0.24,"c":7,"s":7},{"part":"torso","x":0.43628,"y":0.6825,"z":0.018,"w":0.03167,"h":0.03167,"d":0.24,"c":7,"s":7},{"part":"torso","x":0.4686,"y":0.6825,"z":0.018,"w":0.03167,"h":0.03167,"d":0.24,"c":7,"s":7},{"part":"torso","x":0.50091,"y":0.6825,"z":0.018,"w":0.03167,"h":0.03167,"d":0.24,"c":7,"s":7},{"part":"torso","x":0.53323,"y":0.6825,"z":0.018,"w":0.03167,"h":0.03167,"d":0.24,"c":7,"s":7},{"part":"torso","x":0.56555,"y":0.6825,"z":0.018,"w":0.03167,"h":0.03167,"d":0.24,"c":7,"s":7},{"part":"torso","x":0.59787,"y":0.6825,"z":0.018,"w":0.03167,"h":0.03167,"d":0.24,"c":7,"s":7},{"part":"torso","x":0.63018,"y":0.6825,"z":0.018,"w":0.03167,"h":0.03167,"d":0.24,"c":7,"s":7},{"part":"torso","x":0.6625,"y":0.6825,"z":0.018,"w":0.03167,"h":0.03167,"d":0.24,"c":7,"s":7},{"part":"leadArm","x":0.69482,"y":0.6825,"z":0.018,"w":0.03167,"h":0.03167,"d":0.24,"c":7,"s":7},{"part":"leadArm","x":0.72713,"y":0.6825,"z":0.018,"w":0.03167,"h":0.03167,"d":0.24,"c":7,"s":7},{"part":"leadArm","x":0.75945,"y":0.6825,"z":0.018,"w":0.03167,"h":0.03167,"d":0.24,"c":7,"s":7},{"part":"leadArm","x":0.79177,"y":0.6825,"z":0.018,"w":0.03167,"h":0.03167,"d":0.24,"c":7,"s":7},{"part":"leadArm","x":0.82409,"y":0.6825,"z":0.018,"w":0.03167,"h":0.03167,"d":0.24,"c":7,"s":7},{"part":"leadArm","x":0.8564,"y":0.6825,"z":0.018,"w":0.03167,"h":0.03167,"d":0.24,"c":7,"s":7},{"part":"leadArm","x":0.88872,"y":0.6825,"z":0.018,"w":0.03167,"h":0.03167,"d":0.24,"c":7,"s":7},{"part":"leadArm","x":0.92104,"y":0.6825,"z":0.018,"w":0.03167,"h":0.03167,"d":0.24,"c":7,"s":7},{"part":"leadArm","x":0.95335,"y":0.6825,"z":0.018,"w":0.03167,"h":0.03167,"d":0.24,"c":7,"s":7},{"part":"leadArm","x":0.98567,"y":0.6825,"z":0.018,"w":0.03167,"h":0.03167,"d":0.24,"c":7,"s":7},{"part":"leadArm","x":1.01799,"y":0.6825,"z":0.018,"w":0.03167,"h":0.03167,"d":0.24,"c":7,"s":7},{"part":"leadArm","x":1.0503,"y":0.6825,"z":0.018,"w":0.03167,"h":0.03167,"d":0.24,"c":7,"s":7},{"part":"leadArm","x":1.08262,"y":0.6825,"z":0.018,"w":0.03167,"h":0.03167,"d":0.24,"c":7,"s":7},{"part":"leadArm","x":1.11494,"y":0.6825,"z":0.018,"w":0.03167,"h":0.03167,"d":0.24,"c":7,"s":7},{"part":"leadArm","x":1.14726,"y":0.6825,"z":0.018,"w":0.03167,"h":0.03167,"d":0.24,"c":7,"s":7},{"part":"leadArm","x":1.17957,"y":0.6825,"z":0.018,"w":0.03167,"h":0.03167,"d":0.24,"c":5,"s":5},{"part":"rearArm","x":-0.8564,"y":0.65018,"z":0.018,"w":0.03167,"h":0.03167,"d":0.24,"c":11,"s":11},{"part":"rearArm","x":-0.82409,"y":0.65018,"z":0.018,"w":0.03167,"h":0.03167,"d":0.24,"c":5,"s":5},{"part":"rearArm","x":-0.79177,"y":0.65018,"z":0.018,"w":0.03167,"h":0.03167,"d":0.24,"c":7,"s":7},{"part":"torso","x":-0.6625,"y":0.65018,"z":0.018,"w":0.03167,"h":0.03167,"d":0.24,"c":7,"s":7},{"part":"torso","x":-0.63018,"y":0.65018,"z":0.018,"w":0.03167,"h":0.03167,"d":0.24,"c":11,"s":11},{"part":"torso","x":-0.56555,"y":0.65018,"z":0.018,"w":0.03167,"h":0.03167,"d":0.24,"c":7,"s":7},{"part":"torso","x":-0.53323,"y":0.65018,"z":0.018,"w":0.03167,"h":0.03167,"d":0.24,"c":7,"s":7},{"part":"torso","x":-0.50091,"y":0.65018,"z":0.018,"w":0.03167,"h":0.03167,"d":0.24,"c":7,"s":7},{"part":"torso","x":-0.4686,"y":0.65018,"z":0.018,"w":0.03167,"h":0.03167,"d":0.24,"c":7,"s":7},{"part":"torso","x":-0.43628,"y":0.65018,"z":0.018,"w":0.03167,"h":0.03167,"d":0.24,"c":7,"s":7},{"part":"torso","x":-0.40396,"y":0.65018,"z":0.018,"w":0.03167,"h":0.03167,"d":0.24,"c":7,"s":7},{"part":"torso","x":-0.37165,"y":0.65018,"z":0.018,"w":0.03167,"h":0.03167,"d":0.24,"c":7,"s":7},{"part":"torso","x":-0.33933,"y":0.65018,"z":0.018,"w":0.03167,"h":0.03167,"d":0.24,"c":7,"s":7},{"part":"torso","x":-0.30701,"y":0.65018,"z":0.018,"w":0.03167,"h":0.03167,"d":0.24,"c":7,"s":7},{"part":"torso","x":-0.2747,"y":0.65018,"z":0.018,"w":0.03167,"h":0.03167,"d":0.24,"c":7,"s":7},{"part":"torso","x":-0.24238,"y":0.65018,"z":0.018,"w":0.03167,"h":0.03167,"d":0.24,"c":7,"s":7},{"part":"torso","x":-0.21006,"y":0.65018,"z":0.018,"w":0.03167,"h":0.03167,"d":0.24,"c":7,"s":7},{"part":"torso","x":-0.17774,"y":0.65018,"z":0.018,"w":0.03167,"h":0.03167,"d":0.24,"c":7,"s":7},{"part":"torso","x":-0.14543,"y":0.65018,"z":0.018,"w":0.03167,"h":0.03167,"d":0.24,"c":7,"s":7},{"part":"torso","x":-0.11311,"y":0.65018,"z":0.018,"w":0.03167,"h":0.03167,"d":0.24,"c":7,"s":7},{"part":"torso","x":-0.08079,"y":0.65018,"z":0.018,"w":0.03167,"h":0.03167,"d":0.24,"c":7,"s":7},{"part":"torso","x":-0.04848,"y":0.65018,"z":0.018,"w":0.03167,"h":0.03167,"d":0.24,"c":7,"s":7},{"part":"torso","x":-0.01616,"y":0.65018,"z":0.018,"w":0.03167,"h":0.03167,"d":0.24,"c":7,"s":7},{"part":"torso","x":0.01616,"y":0.65018,"z":0.018,"w":0.03167,"h":0.03167,"d":0.24,"c":7,"s":7},{"part":"torso","x":0.04848,"y":0.65018,"z":0.018,"w":0.03167,"h":0.03167,"d":0.24,"c":7,"s":7},{"part":"torso","x":0.08079,"y":0.65018,"z":0.018,"w":0.03167,"h":0.03167,"d":0.24,"c":7,"s":7},{"part":"torso","x":0.11311,"y":0.65018,"z":0.018,"w":0.03167,"h":0.03167,"d":0.24,"c":7,"s":7},{"part":"torso","x":0.14543,"y":0.65018,"z":0.018,"w":0.03167,"h":0.03167,"d":0.24,"c":7,"s":7},{"part":"torso","x":0.17774,"y":0.65018,"z":0.018,"w":0.03167,"h":0.03167,"d":0.24,"c":7,"s":7},{"part":"torso","x":0.21006,"y":0.65018,"z":0.018,"w":0.03167,"h":0.03167,"d":0.24,"c":7,"s":7},{"part":"torso","x":0.24238,"y":0.65018,"z":0.018,"w":0.03167,"h":0.03167,"d":0.24,"c":7,"s":7},{"part":"torso","x":0.2747,"y":0.65018,"z":0.018,"w":0.03167,"h":0.03167,"d":0.24,"c":7,"s":7},{"part":"torso","x":0.30701,"y":0.65018,"z":0.018,"w":0.03167,"h":0.03167,"d":0.24,"c":7,"s":7},{"part":"torso","x":0.33933,"y":0.65018,"z":0.018,"w":0.03167,"h":0.03167,"d":0.24,"c":7,"s":7},{"part":"torso","x":0.37165,"y":0.65018,"z":0.018,"w":0.03167,"h":0.03167,"d":0.24,"c":7,"s":7},{"part":"torso","x":0.40396,"y":0.65018,"z":0.018,"w":0.03167,"h":0.03167,"d":0.24,"c":7,"s":7},{"part":"torso","x":0.43628,"y":0.65018,"z":0.018,"w":0.03167,"h":0.03167,"d":0.24,"c":7,"s":7},{"part":"torso","x":0.4686,"y":0.65018,"z":0.018,"w":0.03167,"h":0.03167,"d":0.24,"c":7,"s":7},{"part":"torso","x":0.50091,"y":0.65018,"z":0.018,"w":0.03167,"h":0.03167,"d":0.24,"c":7,"s":7},{"part":"torso","x":0.53323,"y":0.65018,"z":0.018,"w":0.03167,"h":0.03167,"d":0.24,"c":7,"s":7},{"part":"torso","x":0.56555,"y":0.65018,"z":0.018,"w":0.03167,"h":0.03167,"d":0.24,"c":7,"s":7},{"part":"torso","x":0.59787,"y":0.65018,"z":0.018,"w":0.03167,"h":0.03167,"d":0.24,"c":7,"s":7},{"part":"torso","x":0.63018,"y":0.65018,"z":0.018,"w":0.03167,"h":0.03167,"d":0.24,"c":7,"s":7},{"part":"torso","x":0.6625,"y":0.65018,"z":0.018,"w":0.03167,"h":0.03167,"d":0.24,"c":7,"s":7},{"part":"leadArm","x":0.69482,"y":0.65018,"z":0.018,"w":0.03167,"h":0.03167,"d":0.24,"c":7,"s":7},{"part":"leadArm","x":0.72713,"y":0.65018,"z":0.018,"w":0.03167,"h":0.03167,"d":0.24,"c":7,"s":7},{"part":"leadArm","x":0.75945,"y":0.65018,"z":0.018,"w":0.03167,"h":0.03167,"d":0.24,"c":7,"s":7},{"part":"leadArm","x":0.79177,"y":0.65018,"z":0.018,"w":0.03167,"h":0.03167,"d":0.24,"c":7,"s":7},{"part":"leadArm","x":0.82409,"y":0.65018,"z":0.018,"w":0.03167,"h":0.03167,"d":0.24,"c":7,"s":7},{"part":"leadArm","x":0.8564,"y":0.65018,"z":0.018,"w":0.03167,"h":0.03167,"d":0.24,"c":7,"s":7},{"part":"leadArm","x":0.88872,"y":0.65018,"z":0.018,"w":0.03167,"h":0.03167,"d":0.24,"c":7,"s":7},{"part":"leadArm","x":0.92104,"y":0.65018,"z":0.018,"w":0.03167,"h":0.03167,"d":0.24,"c":7,"s":7},{"part":"leadArm","x":0.95335,"y":0.65018,"z":0.018,"w":0.03167,"h":0.03167,"d":0.24,"c":7,"s":7},{"part":"leadArm","x":0.98567,"y":0.65018,"z":0.018,"w":0.03167,"h":0.03167,"d":0.24,"c":7,"s":7},{"part":"leadArm","x":1.01799,"y":0.65018,"z":0.018,"w":0.03167,"h":0.03167,"d":0.24,"c":7,"s":7},{"part":"leadArm","x":1.0503,"y":0.65018,"z":0.018,"w":0.03167,"h":0.03167,"d":0.24,"c":7,"s":7},{"part":"leadArm","x":1.08262,"y":0.65018,"z":0.018,"w":0.03167,"h":0.03167,"d":0.24,"c":7,"s":7},{"part":"leadArm","x":1.11494,"y":0.65018,"z":0.018,"w":0.03167,"h":0.03167,"d":0.24,"c":7,"s":7},{"part":"leadArm","x":1.14726,"y":0.65018,"z":0.018,"w":0.03167,"h":0.03167,"d":0.24,"c":7,"s":7},{"part":"leadArm","x":1.17957,"y":0.65018,"z":0.018,"w":0.03167,"h":0.03167,"d":0.24,"c":7,"s":7},{"part":"leadArm","x":1.21189,"y":0.65018,"z":0.018,"w":0.03167,"h":0.03167,"d":0.24,"c":7,"s":7},{"part":"rearArm","x":-0.88872,"y":0.61787,"z":0.018,"w":0.03167,"h":0.03167,"d":0.24,"c":5,"s":5},{"part":"rearArm","x":-0.8564,"y":0.61787,"z":0.018,"w":0.03167,"h":0.03167,"d":0.24,"c":5,"s":5},{"part":"rearArm","x":-0.82409,"y":0.61787,"z":0.018,"w":0.03167,"h":0.03167,"d":0.24,"c":5,"s":5},{"part":"rearArm","x":-0.79177,"y":0.61787,"z":0.018,"w":0.03167,"h":0.03167,"d":0.24,"c":7,"s":7},{"part":"rearArm","x":-0.75945,"y":0.61787,"z":0.018,"w":0.03167,"h":0.03167,"d":0.24,"c":5,"s":5},{"part":"rearArm","x":-0.72713,"y":0.61787,"z":0.018,"w":0.03167,"h":0.03167,"d":0.24,"c":7,"s":7},{"part":"rearArm","x":-0.69482,"y":0.61787,"z":0.018,"w":0.03167,"h":0.03167,"d":0.24,"c":5,"s":5},{"part":"torso","x":-0.6625,"y":0.61787,"z":-0.012,"w":0.03167,"h":0.03167,"d":0.24,"c":4,"s":4},{"part":"torso","x":-0.63018,"y":0.61787,"z":-0.012,"w":0.03167,"h":0.03167,"d":0.24,"c":4,"s":4},{"part":"torso","x":-0.59787,"y":0.61787,"z":0.018,"w":0.03167,"h":0.03167,"d":0.24,"c":5,"s":5},{"part":"torso","x":-0.56555,"y":0.61787,"z":0.018,"w":0.03167,"h":0.03167,"d":0.24,"c":5,"s":5},{"part":"torso","x":-0.53323,"y":0.61787,"z":0.018,"w":0.03167,"h":0.03167,"d":0.24,"c":5,"s":5},{"part":"torso","x":-0.50091,"y":0.61787,"z":0.018,"w":0.03167,"h":0.03167,"d":0.24,"c":5,"s":5},{"part":"torso","x":-0.4686,"y":0.61787,"z":0.018,"w":0.03167,"h":0.03167,"d":0.24,"c":7,"s":7},{"part":"torso","x":-0.43628,"y":0.61787,"z":0.018,"w":0.03167,"h":0.03167,"d":0.24,"c":7,"s":7},{"part":"torso","x":-0.40396,"y":0.61787,"z":0.018,"w":0.03167,"h":0.03167,"d":0.24,"c":7,"s":7},{"part":"torso","x":-0.37165,"y":0.61787,"z":0.018,"w":0.03167,"h":0.03167,"d":0.24,"c":7,"s":7},{"part":"torso","x":-0.33933,"y":0.61787,"z":0.018,"w":0.03167,"h":0.03167,"d":0.24,"c":7,"s":7},{"part":"torso","x":-0.30701,"y":0.61787,"z":0.018,"w":0.03167,"h":0.03167,"d":0.24,"c":7,"s":7},{"part":"torso","x":-0.2747,"y":0.61787,"z":0.018,"w":0.03167,"h":0.03167,"d":0.24,"c":7,"s":7},{"part":"torso","x":-0.24238,"y":0.61787,"z":0.018,"w":0.03167,"h":0.03167,"d":0.24,"c":7,"s":7},{"part":"torso","x":-0.21006,"y":0.61787,"z":0.018,"w":0.03167,"h":0.03167,"d":0.24,"c":7,"s":7},{"part":"torso","x":-0.17774,"y":0.61787,"z":0.018,"w":0.03167,"h":0.03167,"d":0.24,"c":7,"s":7},{"part":"torso","x":-0.14543,"y":0.61787,"z":0.018,"w":0.03167,"h":0.03167,"d":0.24,"c":7,"s":7},{"part":"torso","x":-0.11311,"y":0.61787,"z":0.018,"w":0.03167,"h":0.03167,"d":0.24,"c":7,"s":7},{"part":"torso","x":-0.08079,"y":0.61787,"z":0.018,"w":0.03167,"h":0.03167,"d":0.24,"c":7,"s":7},{"part":"torso","x":-0.04848,"y":0.61787,"z":0.018,"w":0.03167,"h":0.03167,"d":0.24,"c":7,"s":7},{"part":"torso","x":-0.01616,"y":0.61787,"z":0.018,"w":0.03167,"h":0.03167,"d":0.24,"c":7,"s":7},{"part":"torso","x":0.01616,"y":0.61787,"z":0.018,"w":0.03167,"h":0.03167,"d":0.24,"c":7,"s":7},{"part":"torso","x":0.04848,"y":0.61787,"z":0.018,"w":0.03167,"h":0.03167,"d":0.24,"c":7,"s":7},{"part":"torso","x":0.08079,"y":0.61787,"z":0.018,"w":0.03167,"h":0.03167,"d":0.24,"c":7,"s":7},{"part":"torso","x":0.11311,"y":0.61787,"z":0.018,"w":0.03167,"h":0.03167,"d":0.24,"c":7,"s":7},{"part":"torso","x":0.14543,"y":0.61787,"z":0.018,"w":0.03167,"h":0.03167,"d":0.24,"c":7,"s":7},{"part":"torso","x":0.17774,"y":0.61787,"z":0.018,"w":0.03167,"h":0.03167,"d":0.24,"c":7,"s":7},{"part":"torso","x":0.21006,"y":0.61787,"z":0.018,"w":0.03167,"h":0.03167,"d":0.24,"c":7,"s":7},{"part":"torso","x":0.24238,"y":0.61787,"z":0.018,"w":0.03167,"h":0.03167,"d":0.24,"c":7,"s":7},{"part":"torso","x":0.2747,"y":0.61787,"z":0.018,"w":0.03167,"h":0.03167,"d":0.24,"c":7,"s":7},{"part":"torso","x":0.30701,"y":0.61787,"z":0.018,"w":0.03167,"h":0.03167,"d":0.24,"c":7,"s":7},{"part":"torso","x":0.33933,"y":0.61787,"z":0.018,"w":0.03167,"h":0.03167,"d":0.24,"c":7,"s":7},{"part":"torso","x":0.37165,"y":0.61787,"z":0.018,"w":0.03167,"h":0.03167,"d":0.24,"c":7,"s":7},{"part":"torso","x":0.40396,"y":0.61787,"z":0.018,"w":0.03167,"h":0.03167,"d":0.24,"c":7,"s":7},{"part":"torso","x":0.43628,"y":0.61787,"z":0.018,"w":0.03167,"h":0.03167,"d":0.24,"c":7,"s":7},{"part":"torso","x":0.4686,"y":0.61787,"z":0.018,"w":0.03167,"h":0.03167,"d":0.24,"c":7,"s":7},{"part":"torso","x":0.50091,"y":0.61787,"z":0.018,"w":0.03167,"h":0.03167,"d":0.24,"c":7,"s":7},{"part":"torso","x":0.53323,"y":0.61787,"z":0.018,"w":0.03167,"h":0.03167,"d":0.24,"c":7,"s":7},{"part":"torso","x":0.56555,"y":0.61787,"z":0.018,"w":0.03167,"h":0.03167,"d":0.24,"c":7,"s":7},{"part":"torso","x":0.59787,"y":0.61787,"z":0.018,"w":0.03167,"h":0.03167,"d":0.24,"c":7,"s":7},{"part":"torso","x":0.63018,"y":0.61787,"z":0.018,"w":0.03167,"h":0.03167,"d":0.24,"c":7,"s":7},{"part":"torso","x":0.6625,"y":0.61787,"z":0.018,"w":0.03167,"h":0.03167,"d":0.24,"c":7,"s":7},{"part":"leadArm","x":0.69482,"y":0.61787,"z":0.018,"w":0.03167,"h":0.03167,"d":0.24,"c":7,"s":7},{"part":"leadArm","x":0.72713,"y":0.61787,"z":0.018,"w":0.03167,"h":0.03167,"d":0.24,"c":7,"s":7},{"part":"leadArm","x":0.75945,"y":0.61787,"z":0.018,"w":0.03167,"h":0.03167,"d":0.24,"c":7,"s":7},{"part":"leadArm","x":0.79177,"y":0.61787,"z":0.018,"w":0.03167,"h":0.03167,"d":0.24,"c":7,"s":7},{"part":"leadArm","x":0.82409,"y":0.61787,"z":0.018,"w":0.03167,"h":0.03167,"d":0.24,"c":7,"s":7},{"part":"leadArm","x":0.8564,"y":0.61787,"z":0.018,"w":0.03167,"h":0.03167,"d":0.24,"c":7,"s":7},{"part":"leadArm","x":0.88872,"y":0.61787,"z":0.018,"w":0.03167,"h":0.03167,"d":0.24,"c":7,"s":7},{"part":"leadArm","x":0.92104,"y":0.61787,"z":0.018,"w":0.03167,"h":0.03167,"d":0.24,"c":7,"s":7},{"part":"leadArm","x":0.95335,"y":0.61787,"z":0.018,"w":0.03167,"h":0.03167,"d":0.24,"c":7,"s":7},{"part":"leadArm","x":0.98567,"y":0.61787,"z":0.018,"w":0.03167,"h":0.03167,"d":0.24,"c":7,"s":7},{"part":"leadArm","x":1.01799,"y":0.61787,"z":0.018,"w":0.03167,"h":0.03167,"d":0.24,"c":7,"s":7},{"part":"leadArm","x":1.0503,"y":0.61787,"z":0.018,"w":0.03167,"h":0.03167,"d":0.24,"c":7,"s":7},{"part":"leadArm","x":1.08262,"y":0.61787,"z":0.018,"w":0.03167,"h":0.03167,"d":0.24,"c":7,"s":7},{"part":"leadArm","x":1.11494,"y":0.61787,"z":0.018,"w":0.03167,"h":0.03167,"d":0.24,"c":7,"s":7},{"part":"leadArm","x":1.14726,"y":0.61787,"z":0.018,"w":0.03167,"h":0.03167,"d":0.24,"c":7,"s":7},{"part":"leadArm","x":1.17957,"y":0.61787,"z":0.018,"w":0.03167,"h":0.03167,"d":0.24,"c":7,"s":7},{"part":"leadArm","x":1.21189,"y":0.61787,"z":0.018,"w":0.03167,"h":0.03167,"d":0.24,"c":7,"s":7},{"part":"leadArm","x":1.27652,"y":0.61787,"z":-0.012,"w":0.03167,"h":0.03167,"d":0.24,"c":9,"s":9},{"part":"leadArm","x":1.30884,"y":0.61787,"z":0.018,"w":0.03167,"h":0.03167,"d":0.24,"c":8,"s":8},{"part":"rearLeg","x":-0.92104,"y":0.58555,"z":0.018,"w":0.03167,"h":0.03167,"d":0.24,"c":5,"s":5},{"part":"rearLeg","x":-0.88872,"y":0.58555,"z":0.018,"w":0.03167,"h":0.03167,"d":0.24,"c":7,"s":7},{"part":"rearLeg","x":-0.8564,"y":0.58555,"z":0.018,"w":0.03167,"h":0.03167,"d":0.24,"c":7,"s":7},{"part":"rearLeg","x":-0.82409,"y":0.58555,"z":0.018,"w":0.03167,"h":0.03167,"d":0.24,"c":7,"s":7},{"part":"rearLeg","x":-0.79177,"y":0.58555,"z":0.018,"w":0.03167,"h":0.03167,"d":0.24,"c":5,"s":5},{"part":"rearLeg","x":-0.75945,"y":0.58555,"z":0.018,"w":0.03167,"h":0.03167,"d":0.24,"c":5,"s":5},{"part":"rearLeg","x":-0.72713,"y":0.58555,"z":0.018,"w":0.03167,"h":0.03167,"d":0.24,"c":11,"s":11},{"part":"rearLeg","x":-0.69482,"y":0.58555,"z":0.018,"w":0.03167,"h":0.03167,"d":0.24,"c":11,"s":11},{"part":"rearLeg","x":-0.6625,"y":0.58555,"z":0.018,"w":0.03167,"h":0.03167,"d":0.24,"c":5,"s":5},{"part":"rearLeg","x":-0.63018,"y":0.58555,"z":0.018,"w":0.03167,"h":0.03167,"d":0.24,"c":11,"s":11},{"part":"rearLeg","x":-0.59787,"y":0.58555,"z":0.018,"w":0.03167,"h":0.03167,"d":0.24,"c":5,"s":5},{"part":"rearLeg","x":-0.56555,"y":0.58555,"z":0.018,"w":0.03167,"h":0.03167,"d":0.24,"c":7,"s":7},{"part":"rearLeg","x":-0.53323,"y":0.58555,"z":0.018,"w":0.03167,"h":0.03167,"d":0.24,"c":7,"s":7},{"part":"rearLeg","x":-0.50091,"y":0.58555,"z":0.018,"w":0.03167,"h":0.03167,"d":0.24,"c":7,"s":7},{"part":"rearLeg","x":-0.4686,"y":0.58555,"z":0.018,"w":0.03167,"h":0.03167,"d":0.24,"c":7,"s":7},{"part":"rearLeg","x":-0.43628,"y":0.58555,"z":0.018,"w":0.03167,"h":0.03167,"d":0.24,"c":7,"s":7},{"part":"rearLeg","x":-0.40396,"y":0.58555,"z":0.018,"w":0.03167,"h":0.03167,"d":0.24,"c":7,"s":7},{"part":"rearLeg","x":-0.37165,"y":0.58555,"z":0.018,"w":0.03167,"h":0.03167,"d":0.24,"c":7,"s":7},{"part":"rearLeg","x":-0.33933,"y":0.58555,"z":0.018,"w":0.03167,"h":0.03167,"d":0.24,"c":7,"s":7},{"part":"rearLeg","x":-0.30701,"y":0.58555,"z":0.018,"w":0.03167,"h":0.03167,"d":0.24,"c":7,"s":7},{"part":"rearLeg","x":-0.2747,"y":0.58555,"z":0.018,"w":0.03167,"h":0.03167,"d":0.24,"c":7,"s":7},{"part":"rearLeg","x":-0.24238,"y":0.58555,"z":0.018,"w":0.03167,"h":0.03167,"d":0.24,"c":7,"s":7},{"part":"rearLeg","x":-0.21006,"y":0.58555,"z":0.018,"w":0.03167,"h":0.03167,"d":0.24,"c":7,"s":7},{"part":"rearLeg","x":-0.17774,"y":0.58555,"z":0.018,"w":0.03167,"h":0.03167,"d":0.24,"c":7,"s":7},{"part":"rearLeg","x":-0.14543,"y":0.58555,"z":0.018,"w":0.03167,"h":0.03167,"d":0.24,"c":7,"s":7},{"part":"rearLeg","x":-0.11311,"y":0.58555,"z":0.018,"w":0.03167,"h":0.03167,"d":0.24,"c":7,"s":7},{"part":"rearLeg","x":-0.08079,"y":0.58555,"z":0.018,"w":0.03167,"h":0.03167,"d":0.24,"c":7,"s":7},{"part":"rearLeg","x":-0.04848,"y":0.58555,"z":0.018,"w":0.03167,"h":0.03167,"d":0.24,"c":7,"s":7},{"part":"rearLeg","x":-0.01616,"y":0.58555,"z":0.018,"w":0.03167,"h":0.03167,"d":0.24,"c":7,"s":7},{"part":"leadLeg","x":0.01616,"y":0.58555,"z":0.018,"w":0.03167,"h":0.03167,"d":0.24,"c":7,"s":7},{"part":"leadLeg","x":0.04848,"y":0.58555,"z":0.018,"w":0.03167,"h":0.03167,"d":0.24,"c":7,"s":7},{"part":"leadLeg","x":0.08079,"y":0.58555,"z":0.018,"w":0.03167,"h":0.03167,"d":0.24,"c":7,"s":7},{"part":"leadLeg","x":0.11311,"y":0.58555,"z":0.018,"w":0.03167,"h":0.03167,"d":0.24,"c":7,"s":7},{"part":"leadLeg","x":0.14543,"y":0.58555,"z":0.018,"w":0.03167,"h":0.03167,"d":0.24,"c":7,"s":7},{"part":"leadLeg","x":0.17774,"y":0.58555,"z":0.018,"w":0.03167,"h":0.03167,"d":0.24,"c":7,"s":7},{"part":"leadLeg","x":0.21006,"y":0.58555,"z":0.018,"w":0.03167,"h":0.03167,"d":0.24,"c":7,"s":7},{"part":"leadLeg","x":0.24238,"y":0.58555,"z":0.018,"w":0.03167,"h":0.03167,"d":0.24,"c":7,"s":7},{"part":"leadLeg","x":0.2747,"y":0.58555,"z":0.018,"w":0.03167,"h":0.03167,"d":0.24,"c":7,"s":7},{"part":"leadLeg","x":0.30701,"y":0.58555,"z":0.018,"w":0.03167,"h":0.03167,"d":0.24,"c":7,"s":7},{"part":"leadLeg","x":0.33933,"y":0.58555,"z":0.018,"w":0.03167,"h":0.03167,"d":0.24,"c":7,"s":7},{"part":"leadLeg","x":0.37165,"y":0.58555,"z":0.018,"w":0.03167,"h":0.03167,"d":0.24,"c":7,"s":7},{"part":"leadLeg","x":0.40396,"y":0.58555,"z":0.018,"w":0.03167,"h":0.03167,"d":0.24,"c":7,"s":7},{"part":"leadLeg","x":0.43628,"y":0.58555,"z":0.018,"w":0.03167,"h":0.03167,"d":0.24,"c":5,"s":5},{"part":"leadLeg","x":0.4686,"y":0.58555,"z":0.018,"w":0.03167,"h":0.03167,"d":0.24,"c":5,"s":5},{"part":"leadLeg","x":0.50091,"y":0.58555,"z":0.018,"w":0.03167,"h":0.03167,"d":0.24,"c":5,"s":5},{"part":"leadLeg","x":0.53323,"y":0.58555,"z":0.018,"w":0.03167,"h":0.03167,"d":0.24,"c":5,"s":5},{"part":"leadLeg","x":0.56555,"y":0.58555,"z":0.018,"w":0.03167,"h":0.03167,"d":0.24,"c":5,"s":5},{"part":"leadLeg","x":0.59787,"y":0.58555,"z":0.018,"w":0.03167,"h":0.03167,"d":0.24,"c":5,"s":5},{"part":"leadLeg","x":0.63018,"y":0.58555,"z":0.018,"w":0.03167,"h":0.03167,"d":0.24,"c":7,"s":7},{"part":"leadLeg","x":0.6625,"y":0.58555,"z":0.018,"w":0.03167,"h":0.03167,"d":0.24,"c":7,"s":7},{"part":"leadLeg","x":0.69482,"y":0.58555,"z":0.018,"w":0.03167,"h":0.03167,"d":0.24,"c":7,"s":7},{"part":"leadLeg","x":0.72713,"y":0.58555,"z":0.018,"w":0.03167,"h":0.03167,"d":0.24,"c":7,"s":7},{"part":"leadLeg","x":0.75945,"y":0.58555,"z":0.018,"w":0.03167,"h":0.03167,"d":0.24,"c":7,"s":7},{"part":"leadLeg","x":0.79177,"y":0.58555,"z":0.018,"w":0.03167,"h":0.03167,"d":0.24,"c":7,"s":7},{"part":"leadLeg","x":0.82409,"y":0.58555,"z":0.018,"w":0.03167,"h":0.03167,"d":0.24,"c":7,"s":7},{"part":"leadLeg","x":0.8564,"y":0.58555,"z":0.018,"w":0.03167,"h":0.03167,"d":0.24,"c":7,"s":7},{"part":"leadLeg","x":0.88872,"y":0.58555,"z":0.018,"w":0.03167,"h":0.03167,"d":0.24,"c":7,"s":7},{"part":"leadLeg","x":0.92104,"y":0.58555,"z":0.018,"w":0.03167,"h":0.03167,"d":0.24,"c":7,"s":7},{"part":"leadLeg","x":0.95335,"y":0.58555,"z":0.018,"w":0.03167,"h":0.03167,"d":0.24,"c":7,"s":7},{"part":"leadLeg","x":0.98567,"y":0.58555,"z":0.018,"w":0.03167,"h":0.03167,"d":0.24,"c":5,"s":5},{"part":"leadLeg","x":1.01799,"y":0.58555,"z":0.018,"w":0.03167,"h":0.03167,"d":0.24,"c":5,"s":5},{"part":"leadLeg","x":1.0503,"y":0.58555,"z":0.018,"w":0.03167,"h":0.03167,"d":0.24,"c":5,"s":5},{"part":"leadLeg","x":1.08262,"y":0.58555,"z":0.018,"w":0.03167,"h":0.03167,"d":0.24,"c":5,"s":5},{"part":"leadLeg","x":1.11494,"y":0.58555,"z":0.018,"w":0.03167,"h":0.03167,"d":0.24,"c":5,"s":5},{"part":"leadLeg","x":1.14726,"y":0.58555,"z":0.018,"w":0.03167,"h":0.03167,"d":0.24,"c":5,"s":5},{"part":"leadLeg","x":1.17957,"y":0.58555,"z":0.018,"w":0.03167,"h":0.03167,"d":0.24,"c":5,"s":5},{"part":"leadLeg","x":1.21189,"y":0.58555,"z":0.018,"w":0.03167,"h":0.03167,"d":0.24,"c":5,"s":5},{"part":"leadLeg","x":1.27652,"y":0.58555,"z":-0.012,"w":0.03167,"h":0.03167,"d":0.24,"c":10,"s":10},{"part":"leadLeg","x":1.30884,"y":0.58555,"z":0.018,"w":0.03167,"h":0.03167,"d":0.24,"c":8,"s":8},{"part":"rearLeg","x":-0.98567,"y":0.55323,"z":0.018,"w":0.03167,"h":0.03167,"d":0.24,"c":11,"s":11},{"part":"rearLeg","x":-0.95335,"y":0.55323,"z":0.018,"w":0.03167,"h":0.03167,"d":0.24,"c":11,"s":11},{"part":"rearLeg","x":-0.92104,"y":0.55323,"z":0.018,"w":0.03167,"h":0.03167,"d":0.24,"c":5,"s":5},{"part":"rearLeg","x":-0.88872,"y":0.55323,"z":0.018,"w":0.03167,"h":0.03167,"d":0.24,"c":5,"s":5},{"part":"rearLeg","x":-0.8564,"y":0.55323,"z":0.018,"w":0.03167,"h":0.03167,"d":0.24,"c":5,"s":5},{"part":"rearLeg","x":-0.82409,"y":0.55323,"z":0.018,"w":0.03167,"h":0.03167,"d":0.24,"c":7,"s":7},{"part":"rearLeg","x":-0.79177,"y":0.55323,"z":0.018,"w":0.03167,"h":0.03167,"d":0.24,"c":7,"s":7},{"part":"rearLeg","x":-0.75945,"y":0.55323,"z":0.018,"w":0.03167,"h":0.03167,"d":0.24,"c":7,"s":7},{"part":"rearLeg","x":-0.72713,"y":0.55323,"z":0.018,"w":0.03167,"h":0.03167,"d":0.24,"c":5,"s":5},{"part":"rearLeg","x":-0.69482,"y":0.55323,"z":0.018,"w":0.03167,"h":0.03167,"d":0.24,"c":5,"s":5},{"part":"rearLeg","x":-0.6625,"y":0.55323,"z":0.018,"w":0.03167,"h":0.03167,"d":0.24,"c":11,"s":11},{"part":"rearLeg","x":-0.63018,"y":0.55323,"z":0.018,"w":0.03167,"h":0.03167,"d":0.24,"c":11,"s":11},{"part":"rearLeg","x":-0.59787,"y":0.55323,"z":0.018,"w":0.03167,"h":0.03167,"d":0.24,"c":11,"s":11},{"part":"rearLeg","x":-0.56555,"y":0.55323,"z":0.018,"w":0.03167,"h":0.03167,"d":0.24,"c":5,"s":5},{"part":"rearLeg","x":-0.53323,"y":0.55323,"z":0.018,"w":0.03167,"h":0.03167,"d":0.24,"c":7,"s":7},{"part":"rearLeg","x":-0.50091,"y":0.55323,"z":0.018,"w":0.03167,"h":0.03167,"d":0.24,"c":7,"s":7},{"part":"rearLeg","x":-0.4686,"y":0.55323,"z":0.018,"w":0.03167,"h":0.03167,"d":0.24,"c":5,"s":5},{"part":"rearLeg","x":-0.43628,"y":0.55323,"z":0.018,"w":0.03167,"h":0.03167,"d":0.24,"c":5,"s":5},{"part":"rearLeg","x":-0.40396,"y":0.55323,"z":0.018,"w":0.03167,"h":0.03167,"d":0.24,"c":5,"s":5},{"part":"rearLeg","x":-0.37165,"y":0.55323,"z":0.018,"w":0.03167,"h":0.03167,"d":0.24,"c":7,"s":7},{"part":"rearLeg","x":-0.33933,"y":0.55323,"z":0.018,"w":0.03167,"h":0.03167,"d":0.24,"c":7,"s":7},{"part":"rearLeg","x":-0.30701,"y":0.55323,"z":0.018,"w":0.03167,"h":0.03167,"d":0.24,"c":7,"s":7},{"part":"rearLeg","x":-0.2747,"y":0.55323,"z":0.018,"w":0.03167,"h":0.03167,"d":0.24,"c":7,"s":7},{"part":"rearLeg","x":-0.24238,"y":0.55323,"z":0.018,"w":0.03167,"h":0.03167,"d":0.24,"c":7,"s":7},{"part":"rearLeg","x":-0.21006,"y":0.55323,"z":0.018,"w":0.03167,"h":0.03167,"d":0.24,"c":7,"s":7},{"part":"rearLeg","x":-0.17774,"y":0.55323,"z":0.018,"w":0.03167,"h":0.03167,"d":0.24,"c":5,"s":5},{"part":"rearLeg","x":-0.14543,"y":0.55323,"z":0.018,"w":0.03167,"h":0.03167,"d":0.24,"c":5,"s":5},{"part":"rearLeg","x":-0.11311,"y":0.55323,"z":0.018,"w":0.03167,"h":0.03167,"d":0.24,"c":5,"s":5},{"part":"rearLeg","x":-0.08079,"y":0.55323,"z":0.018,"w":0.03167,"h":0.03167,"d":0.24,"c":5,"s":5},{"part":"rearLeg","x":-0.04848,"y":0.55323,"z":0.018,"w":0.03167,"h":0.03167,"d":0.24,"c":5,"s":5},{"part":"rearLeg","x":-0.01616,"y":0.55323,"z":0.018,"w":0.03167,"h":0.03167,"d":0.24,"c":7,"s":7},{"part":"leadLeg","x":0.01616,"y":0.55323,"z":0.018,"w":0.03167,"h":0.03167,"d":0.24,"c":7,"s":7},{"part":"leadLeg","x":0.04848,"y":0.55323,"z":0.018,"w":0.03167,"h":0.03167,"d":0.24,"c":7,"s":7},{"part":"leadLeg","x":0.08079,"y":0.55323,"z":0.018,"w":0.03167,"h":0.03167,"d":0.24,"c":7,"s":7},{"part":"leadLeg","x":0.11311,"y":0.55323,"z":0.018,"w":0.03167,"h":0.03167,"d":0.24,"c":7,"s":7},{"part":"leadLeg","x":0.14543,"y":0.55323,"z":0.018,"w":0.03167,"h":0.03167,"d":0.24,"c":7,"s":7},{"part":"leadLeg","x":0.17774,"y":0.55323,"z":0.018,"w":0.03167,"h":0.03167,"d":0.24,"c":7,"s":7},{"part":"leadLeg","x":0.21006,"y":0.55323,"z":0.018,"w":0.03167,"h":0.03167,"d":0.24,"c":7,"s":7},{"part":"leadLeg","x":0.24238,"y":0.55323,"z":0.018,"w":0.03167,"h":0.03167,"d":0.24,"c":7,"s":7},{"part":"leadLeg","x":0.2747,"y":0.55323,"z":0.018,"w":0.03167,"h":0.03167,"d":0.24,"c":7,"s":7},{"part":"leadLeg","x":0.30701,"y":0.55323,"z":0.018,"w":0.03167,"h":0.03167,"d":0.24,"c":7,"s":7},{"part":"leadLeg","x":0.33933,"y":0.55323,"z":0.018,"w":0.03167,"h":0.03167,"d":0.24,"c":7,"s":7},{"part":"leadLeg","x":0.37165,"y":0.55323,"z":0.018,"w":0.03167,"h":0.03167,"d":0.24,"c":5,"s":5},{"part":"leadLeg","x":0.40396,"y":0.55323,"z":0.018,"w":0.03167,"h":0.03167,"d":0.24,"c":5,"s":5},{"part":"leadLeg","x":0.43628,"y":0.55323,"z":0.018,"w":0.03167,"h":0.03167,"d":0.24,"c":5,"s":5},{"part":"leadLeg","x":0.4686,"y":0.55323,"z":0.018,"w":0.03167,"h":0.03167,"d":0.24,"c":5,"s":5},{"part":"leadLeg","x":0.50091,"y":0.55323,"z":0.018,"w":0.03167,"h":0.03167,"d":0.24,"c":7,"s":7},{"part":"leadLeg","x":0.53323,"y":0.55323,"z":0.018,"w":0.03167,"h":0.03167,"d":0.24,"c":7,"s":7},{"part":"leadLeg","x":0.56555,"y":0.55323,"z":0.018,"w":0.03167,"h":0.03167,"d":0.24,"c":7,"s":7},{"part":"leadLeg","x":0.59787,"y":0.55323,"z":0.018,"w":0.03167,"h":0.03167,"d":0.24,"c":7,"s":7},{"part":"leadLeg","x":0.63018,"y":0.55323,"z":0.018,"w":0.03167,"h":0.03167,"d":0.24,"c":7,"s":7},{"part":"leadLeg","x":0.6625,"y":0.55323,"z":0.018,"w":0.03167,"h":0.03167,"d":0.24,"c":7,"s":7},{"part":"leadLeg","x":0.69482,"y":0.55323,"z":0.018,"w":0.03167,"h":0.03167,"d":0.24,"c":7,"s":7},{"part":"leadLeg","x":0.72713,"y":0.55323,"z":0.018,"w":0.03167,"h":0.03167,"d":0.24,"c":7,"s":7},{"part":"leadLeg","x":0.75945,"y":0.55323,"z":0.018,"w":0.03167,"h":0.03167,"d":0.24,"c":7,"s":7},{"part":"leadLeg","x":0.79177,"y":0.55323,"z":0.018,"w":0.03167,"h":0.03167,"d":0.24,"c":7,"s":7},{"part":"leadLeg","x":0.82409,"y":0.55323,"z":0.018,"w":0.03167,"h":0.03167,"d":0.24,"c":7,"s":7},{"part":"leadLeg","x":0.8564,"y":0.55323,"z":0.018,"w":0.03167,"h":0.03167,"d":0.24,"c":7,"s":7},{"part":"leadLeg","x":0.88872,"y":0.55323,"z":0.018,"w":0.03167,"h":0.03167,"d":0.24,"c":7,"s":7},{"part":"leadLeg","x":0.92104,"y":0.55323,"z":0.018,"w":0.03167,"h":0.03167,"d":0.24,"c":7,"s":7},{"part":"leadLeg","x":0.95335,"y":0.55323,"z":0.018,"w":0.03167,"h":0.03167,"d":0.24,"c":7,"s":7},{"part":"leadLeg","x":0.98567,"y":0.55323,"z":0.018,"w":0.03167,"h":0.03167,"d":0.24,"c":7,"s":7},{"part":"leadLeg","x":1.01799,"y":0.55323,"z":0.018,"w":0.03167,"h":0.03167,"d":0.24,"c":7,"s":7},{"part":"leadLeg","x":1.0503,"y":0.55323,"z":0.018,"w":0.03167,"h":0.03167,"d":0.24,"c":7,"s":7},{"part":"leadLeg","x":1.08262,"y":0.55323,"z":0.018,"w":0.03167,"h":0.03167,"d":0.24,"c":5,"s":5},{"part":"leadLeg","x":1.11494,"y":0.55323,"z":0.018,"w":0.03167,"h":0.03167,"d":0.24,"c":5,"s":5},{"part":"leadLeg","x":1.14726,"y":0.55323,"z":0.018,"w":0.03167,"h":0.03167,"d":0.24,"c":11,"s":11},{"part":"leadLeg","x":1.17957,"y":0.55323,"z":0.018,"w":0.03167,"h":0.03167,"d":0.24,"c":11,"s":11},{"part":"leadLeg","x":1.21189,"y":0.55323,"z":0.018,"w":0.03167,"h":0.03167,"d":0.24,"c":11,"s":11},{"part":"leadLeg","x":1.27652,"y":0.55323,"z":-0.012,"w":0.03167,"h":0.03167,"d":0.24,"c":10,"s":10},{"part":"leadLeg","x":1.30884,"y":0.55323,"z":-0.012,"w":0.03167,"h":0.03167,"d":0.24,"c":9,"s":9},{"part":"rearLeg","x":-1.0503,"y":0.52091,"z":0.018,"w":0.03167,"h":0.03167,"d":0.24,"c":11,"s":11},{"part":"rearLeg","x":-1.01799,"y":0.52091,"z":0.018,"w":0.03167,"h":0.03167,"d":0.24,"c":5,"s":5},{"part":"rearLeg","x":-0.98567,"y":0.52091,"z":0.018,"w":0.03167,"h":0.03167,"d":0.24,"c":7,"s":7},{"part":"rearLeg","x":-0.95335,"y":0.52091,"z":0.018,"w":0.03167,"h":0.03167,"d":0.24,"c":7,"s":7},{"part":"rearLeg","x":-0.92104,"y":0.52091,"z":0.018,"w":0.03167,"h":0.03167,"d":0.24,"c":7,"s":7},{"part":"rearLeg","x":-0.88872,"y":0.52091,"z":0.018,"w":0.03167,"h":0.03167,"d":0.24,"c":7,"s":7},{"part":"rearLeg","x":-0.8564,"y":0.52091,"z":0.018,"w":0.03167,"h":0.03167,"d":0.24,"c":7,"s":7},{"part":"rearLeg","x":-0.82409,"y":0.52091,"z":0.018,"w":0.03167,"h":0.03167,"d":0.24,"c":7,"s":7},{"part":"rearLeg","x":-0.79177,"y":0.52091,"z":0.018,"w":0.03167,"h":0.03167,"d":0.24,"c":7,"s":7},{"part":"rearLeg","x":-0.75945,"y":0.52091,"z":0.018,"w":0.03167,"h":0.03167,"d":0.24,"c":7,"s":7},{"part":"rearLeg","x":-0.72713,"y":0.52091,"z":0.018,"w":0.03167,"h":0.03167,"d":0.24,"c":7,"s":7},{"part":"rearLeg","x":-0.69482,"y":0.52091,"z":0.018,"w":0.03167,"h":0.03167,"d":0.24,"c":7,"s":7},{"part":"rearLeg","x":-0.6625,"y":0.52091,"z":0.018,"w":0.03167,"h":0.03167,"d":0.24,"c":5,"s":5},{"part":"rearLeg","x":-0.63018,"y":0.52091,"z":0.018,"w":0.03167,"h":0.03167,"d":0.24,"c":5,"s":5},{"part":"rearLeg","x":-0.59787,"y":0.52091,"z":0.018,"w":0.03167,"h":0.03167,"d":0.24,"c":11,"s":11},{"part":"rearLeg","x":-0.56555,"y":0.52091,"z":0.018,"w":0.03167,"h":0.03167,"d":0.24,"c":5,"s":5},{"part":"rearLeg","x":-0.53323,"y":0.52091,"z":0.018,"w":0.03167,"h":0.03167,"d":0.24,"c":5,"s":5},{"part":"rearLeg","x":-0.50091,"y":0.52091,"z":0.018,"w":0.03167,"h":0.03167,"d":0.24,"c":5,"s":5},{"part":"rearLeg","x":-0.4686,"y":0.52091,"z":0.018,"w":0.03167,"h":0.03167,"d":0.24,"c":5,"s":5},{"part":"rearLeg","x":-0.43628,"y":0.52091,"z":0.018,"w":0.03167,"h":0.03167,"d":0.24,"c":5,"s":5},{"part":"rearLeg","x":-0.40396,"y":0.52091,"z":0.018,"w":0.03167,"h":0.03167,"d":0.24,"c":11,"s":11},{"part":"rearLeg","x":-0.37165,"y":0.52091,"z":0.018,"w":0.03167,"h":0.03167,"d":0.24,"c":5,"s":5},{"part":"rearLeg","x":-0.33933,"y":0.52091,"z":0.018,"w":0.03167,"h":0.03167,"d":0.24,"c":7,"s":7},{"part":"rearLeg","x":-0.30701,"y":0.52091,"z":0.018,"w":0.03167,"h":0.03167,"d":0.24,"c":7,"s":7},{"part":"rearLeg","x":-0.2747,"y":0.52091,"z":0.018,"w":0.03167,"h":0.03167,"d":0.24,"c":7,"s":7},{"part":"rearLeg","x":-0.24238,"y":0.52091,"z":0.018,"w":0.03167,"h":0.03167,"d":0.24,"c":7,"s":7},{"part":"rearLeg","x":-0.21006,"y":0.52091,"z":0.018,"w":0.03167,"h":0.03167,"d":0.24,"c":7,"s":7},{"part":"rearLeg","x":-0.17774,"y":0.52091,"z":0.018,"w":0.03167,"h":0.03167,"d":0.24,"c":7,"s":7},{"part":"rearLeg","x":-0.14543,"y":0.52091,"z":0.018,"w":0.03167,"h":0.03167,"d":0.24,"c":7,"s":7},{"part":"rearLeg","x":-0.11311,"y":0.52091,"z":0.018,"w":0.03167,"h":0.03167,"d":0.24,"c":7,"s":7},{"part":"rearLeg","x":-0.08079,"y":0.52091,"z":0.018,"w":0.03167,"h":0.03167,"d":0.24,"c":7,"s":7},{"part":"rearLeg","x":-0.04848,"y":0.52091,"z":0.018,"w":0.03167,"h":0.03167,"d":0.24,"c":5,"s":5},{"part":"rearLeg","x":-0.01616,"y":0.52091,"z":0.018,"w":0.03167,"h":0.03167,"d":0.24,"c":5,"s":5},{"part":"leadLeg","x":0.01616,"y":0.52091,"z":0.018,"w":0.03167,"h":0.03167,"d":0.24,"c":5,"s":5},{"part":"leadLeg","x":0.04848,"y":0.52091,"z":0.018,"w":0.03167,"h":0.03167,"d":0.24,"c":5,"s":5},{"part":"leadLeg","x":0.08079,"y":0.52091,"z":0.018,"w":0.03167,"h":0.03167,"d":0.24,"c":5,"s":5},{"part":"leadLeg","x":0.11311,"y":0.52091,"z":0.018,"w":0.03167,"h":0.03167,"d":0.24,"c":5,"s":5},{"part":"leadLeg","x":0.14543,"y":0.52091,"z":0.018,"w":0.03167,"h":0.03167,"d":0.24,"c":7,"s":7},{"part":"leadLeg","x":0.17774,"y":0.52091,"z":0.018,"w":0.03167,"h":0.03167,"d":0.24,"c":7,"s":7},{"part":"leadLeg","x":0.21006,"y":0.52091,"z":0.018,"w":0.03167,"h":0.03167,"d":0.24,"c":7,"s":7},{"part":"leadLeg","x":0.24238,"y":0.52091,"z":0.018,"w":0.03167,"h":0.03167,"d":0.24,"c":7,"s":7},{"part":"leadLeg","x":0.2747,"y":0.52091,"z":0.018,"w":0.03167,"h":0.03167,"d":0.24,"c":5,"s":5},{"part":"leadLeg","x":0.30701,"y":0.52091,"z":0.018,"w":0.03167,"h":0.03167,"d":0.24,"c":5,"s":5},{"part":"leadLeg","x":0.33933,"y":0.52091,"z":0.018,"w":0.03167,"h":0.03167,"d":0.24,"c":5,"s":5},{"part":"leadLeg","x":0.37165,"y":0.52091,"z":0.018,"w":0.03167,"h":0.03167,"d":0.24,"c":5,"s":5},{"part":"leadLeg","x":0.40396,"y":0.52091,"z":0.018,"w":0.03167,"h":0.03167,"d":0.24,"c":5,"s":5},{"part":"leadLeg","x":0.43628,"y":0.52091,"z":0.018,"w":0.03167,"h":0.03167,"d":0.24,"c":7,"s":7},{"part":"leadLeg","x":0.4686,"y":0.52091,"z":0.018,"w":0.03167,"h":0.03167,"d":0.24,"c":7,"s":7},{"part":"leadLeg","x":0.50091,"y":0.52091,"z":0.018,"w":0.03167,"h":0.03167,"d":0.24,"c":7,"s":7},{"part":"leadLeg","x":0.53323,"y":0.52091,"z":0.018,"w":0.03167,"h":0.03167,"d":0.24,"c":7,"s":7},{"part":"leadLeg","x":0.56555,"y":0.52091,"z":0.018,"w":0.03167,"h":0.03167,"d":0.24,"c":7,"s":7},{"part":"leadLeg","x":0.59787,"y":0.52091,"z":0.018,"w":0.03167,"h":0.03167,"d":0.24,"c":7,"s":7},{"part":"leadLeg","x":0.63018,"y":0.52091,"z":0.018,"w":0.03167,"h":0.03167,"d":0.24,"c":7,"s":7},{"part":"leadLeg","x":0.6625,"y":0.52091,"z":0.018,"w":0.03167,"h":0.03167,"d":0.24,"c":7,"s":7},{"part":"leadLeg","x":0.69482,"y":0.52091,"z":0.018,"w":0.03167,"h":0.03167,"d":0.24,"c":7,"s":7},{"part":"leadLeg","x":0.72713,"y":0.52091,"z":0.018,"w":0.03167,"h":0.03167,"d":0.24,"c":7,"s":7},{"part":"leadLeg","x":0.75945,"y":0.52091,"z":0.018,"w":0.03167,"h":0.03167,"d":0.24,"c":7,"s":7},{"part":"leadLeg","x":0.79177,"y":0.52091,"z":0.018,"w":0.03167,"h":0.03167,"d":0.24,"c":7,"s":7},{"part":"leadLeg","x":0.82409,"y":0.52091,"z":0.018,"w":0.03167,"h":0.03167,"d":0.24,"c":7,"s":7},{"part":"leadLeg","x":0.8564,"y":0.52091,"z":0.018,"w":0.03167,"h":0.03167,"d":0.24,"c":7,"s":7},{"part":"leadLeg","x":0.88872,"y":0.52091,"z":0.018,"w":0.03167,"h":0.03167,"d":0.24,"c":7,"s":7},{"part":"leadLeg","x":0.92104,"y":0.52091,"z":0.018,"w":0.03167,"h":0.03167,"d":0.24,"c":7,"s":7},{"part":"leadLeg","x":0.95335,"y":0.52091,"z":0.018,"w":0.03167,"h":0.03167,"d":0.24,"c":7,"s":7},{"part":"leadLeg","x":0.98567,"y":0.52091,"z":0.018,"w":0.03167,"h":0.03167,"d":0.24,"c":7,"s":7},{"part":"leadLeg","x":1.01799,"y":0.52091,"z":0.018,"w":0.03167,"h":0.03167,"d":0.24,"c":7,"s":7},{"part":"leadLeg","x":1.0503,"y":0.52091,"z":0.018,"w":0.03167,"h":0.03167,"d":0.24,"c":7,"s":7},{"part":"leadLeg","x":1.08262,"y":0.52091,"z":0.018,"w":0.03167,"h":0.03167,"d":0.24,"c":7,"s":7},{"part":"leadLeg","x":1.11494,"y":0.52091,"z":0.018,"w":0.03167,"h":0.03167,"d":0.24,"c":5,"s":5},{"part":"leadLeg","x":1.14726,"y":0.52091,"z":0.018,"w":0.03167,"h":0.03167,"d":0.24,"c":5,"s":5},{"part":"leadLeg","x":1.17957,"y":0.52091,"z":0.018,"w":0.03167,"h":0.03167,"d":0.24,"c":5,"s":5},{"part":"leadLeg","x":1.24421,"y":0.52091,"z":-0.012,"w":0.03167,"h":0.03167,"d":0.24,"c":10,"s":10},{"part":"leadLeg","x":1.27652,"y":0.52091,"z":-0.012,"w":0.03167,"h":0.03167,"d":0.24,"c":9,"s":9},{"part":"rearLeg","x":-1.08262,"y":0.4886,"z":0.018,"w":0.03167,"h":0.03167,"d":0.24,"c":11,"s":11},{"part":"rearLeg","x":-1.0503,"y":0.4886,"z":0.018,"w":0.03167,"h":0.03167,"d":0.24,"c":5,"s":5},{"part":"rearLeg","x":-1.01799,"y":0.4886,"z":0.018,"w":0.03167,"h":0.03167,"d":0.24,"c":7,"s":7},{"part":"rearLeg","x":-0.98567,"y":0.4886,"z":0.018,"w":0.03167,"h":0.03167,"d":0.24,"c":7,"s":7},{"part":"rearLeg","x":-0.95335,"y":0.4886,"z":0.018,"w":0.03167,"h":0.03167,"d":0.24,"c":7,"s":7},{"part":"rearLeg","x":-0.92104,"y":0.4886,"z":0.018,"w":0.03167,"h":0.03167,"d":0.24,"c":7,"s":7},{"part":"rearLeg","x":-0.88872,"y":0.4886,"z":0.018,"w":0.03167,"h":0.03167,"d":0.24,"c":7,"s":7},{"part":"rearLeg","x":-0.8564,"y":0.4886,"z":0.018,"w":0.03167,"h":0.03167,"d":0.24,"c":7,"s":7},{"part":"rearLeg","x":-0.82409,"y":0.4886,"z":0.018,"w":0.03167,"h":0.03167,"d":0.24,"c":7,"s":7},{"part":"rearLeg","x":-0.79177,"y":0.4886,"z":0.018,"w":0.03167,"h":0.03167,"d":0.24,"c":5,"s":5},{"part":"rearLeg","x":-0.75945,"y":0.4886,"z":0.018,"w":0.03167,"h":0.03167,"d":0.24,"c":5,"s":5},{"part":"rearLeg","x":-0.72713,"y":0.4886,"z":0.018,"w":0.03167,"h":0.03167,"d":0.24,"c":5,"s":5},{"part":"rearLeg","x":-0.69482,"y":0.4886,"z":0.018,"w":0.03167,"h":0.03167,"d":0.24,"c":5,"s":5},{"part":"rearLeg","x":-0.6625,"y":0.4886,"z":0.018,"w":0.03167,"h":0.03167,"d":0.24,"c":11,"s":11},{"part":"rearLeg","x":-0.63018,"y":0.4886,"z":0.018,"w":0.03167,"h":0.03167,"d":0.24,"c":11,"s":11},{"part":"rearLeg","x":-0.59787,"y":0.4886,"z":-0.012,"w":0.03167,"h":0.03167,"d":0.24,"c":12,"s":12},{"part":"rearLeg","x":-0.56555,"y":0.4886,"z":0.018,"w":0.03167,"h":0.03167,"d":0.24,"c":11,"s":11},{"part":"rearLeg","x":-0.53323,"y":0.4886,"z":0.018,"w":0.03167,"h":0.03167,"d":0.24,"c":11,"s":11},{"part":"rearLeg","x":-0.50091,"y":0.4886,"z":0.018,"w":0.03167,"h":0.03167,"d":0.24,"c":11,"s":11},{"part":"rearLeg","x":-0.4686,"y":0.4886,"z":0.018,"w":0.03167,"h":0.03167,"d":0.24,"c":5,"s":5},{"part":"rearLeg","x":-0.43628,"y":0.4886,"z":0.018,"w":0.03167,"h":0.03167,"d":0.24,"c":5,"s":5},{"part":"rearLeg","x":-0.40396,"y":0.4886,"z":0.018,"w":0.03167,"h":0.03167,"d":0.24,"c":5,"s":5},{"part":"rearLeg","x":-0.37165,"y":0.4886,"z":0.018,"w":0.03167,"h":0.03167,"d":0.24,"c":11,"s":11},{"part":"rearLeg","x":-0.33933,"y":0.4886,"z":0.018,"w":0.03167,"h":0.03167,"d":0.24,"c":11,"s":11},{"part":"rearLeg","x":-0.30701,"y":0.4886,"z":0.018,"w":0.03167,"h":0.03167,"d":0.24,"c":11,"s":11},{"part":"rearLeg","x":-0.2747,"y":0.4886,"z":0.018,"w":0.03167,"h":0.03167,"d":0.24,"c":11,"s":11},{"part":"rearLeg","x":-0.24238,"y":0.4886,"z":0.018,"w":0.03167,"h":0.03167,"d":0.24,"c":11,"s":11},{"part":"rearLeg","x":-0.21006,"y":0.4886,"z":0.018,"w":0.03167,"h":0.03167,"d":0.24,"c":5,"s":5},{"part":"rearLeg","x":-0.17774,"y":0.4886,"z":0.018,"w":0.03167,"h":0.03167,"d":0.24,"c":5,"s":5},{"part":"rearLeg","x":-0.14543,"y":0.4886,"z":0.018,"w":0.03167,"h":0.03167,"d":0.24,"c":5,"s":5},{"part":"rearLeg","x":-0.11311,"y":0.4886,"z":0.018,"w":0.03167,"h":0.03167,"d":0.24,"c":5,"s":5},{"part":"rearLeg","x":-0.08079,"y":0.4886,"z":0.018,"w":0.03167,"h":0.03167,"d":0.24,"c":5,"s":5},{"part":"rearLeg","x":-0.04848,"y":0.4886,"z":0.018,"w":0.03167,"h":0.03167,"d":0.24,"c":5,"s":5},{"part":"rearLeg","x":-0.01616,"y":0.4886,"z":0.018,"w":0.03167,"h":0.03167,"d":0.24,"c":11,"s":11},{"part":"leadLeg","x":0.01616,"y":0.4886,"z":0.018,"w":0.03167,"h":0.03167,"d":0.24,"c":11,"s":11},{"part":"leadLeg","x":0.04848,"y":0.4886,"z":0.018,"w":0.03167,"h":0.03167,"d":0.24,"c":11,"s":11},{"part":"leadLeg","x":0.08079,"y":0.4886,"z":0.018,"w":0.03167,"h":0.03167,"d":0.24,"c":11,"s":11},{"part":"leadLeg","x":0.11311,"y":0.4886,"z":0.018,"w":0.03167,"h":0.03167,"d":0.24,"c":5,"s":5},{"part":"leadLeg","x":0.14543,"y":0.4886,"z":0.018,"w":0.03167,"h":0.03167,"d":0.24,"c":5,"s":5},{"part":"leadLeg","x":0.17774,"y":0.4886,"z":0.018,"w":0.03167,"h":0.03167,"d":0.24,"c":5,"s":5},{"part":"leadLeg","x":0.21006,"y":0.4886,"z":0.018,"w":0.03167,"h":0.03167,"d":0.24,"c":5,"s":5},{"part":"leadLeg","x":0.24238,"y":0.4886,"z":0.018,"w":0.03167,"h":0.03167,"d":0.24,"c":5,"s":5},{"part":"leadLeg","x":0.2747,"y":0.4886,"z":0.018,"w":0.03167,"h":0.03167,"d":0.24,"c":5,"s":5},{"part":"leadLeg","x":0.30701,"y":0.4886,"z":0.018,"w":0.03167,"h":0.03167,"d":0.24,"c":11,"s":11},{"part":"leadLeg","x":0.33933,"y":0.4886,"z":0.018,"w":0.03167,"h":0.03167,"d":0.24,"c":11,"s":11},{"part":"leadLeg","x":0.37165,"y":0.4886,"z":0.018,"w":0.03167,"h":0.03167,"d":0.24,"c":5,"s":5},{"part":"leadLeg","x":0.40396,"y":0.4886,"z":0.018,"w":0.03167,"h":0.03167,"d":0.24,"c":5,"s":5},{"part":"leadLeg","x":0.43628,"y":0.4886,"z":0.018,"w":0.03167,"h":0.03167,"d":0.24,"c":5,"s":5},{"part":"leadLeg","x":0.4686,"y":0.4886,"z":0.018,"w":0.03167,"h":0.03167,"d":0.24,"c":5,"s":5},{"part":"leadLeg","x":0.50091,"y":0.4886,"z":0.018,"w":0.03167,"h":0.03167,"d":0.24,"c":5,"s":5},{"part":"leadLeg","x":0.53323,"y":0.4886,"z":0.018,"w":0.03167,"h":0.03167,"d":0.24,"c":5,"s":5},{"part":"leadLeg","x":0.56555,"y":0.4886,"z":0.018,"w":0.03167,"h":0.03167,"d":0.24,"c":7,"s":7},{"part":"leadLeg","x":0.59787,"y":0.4886,"z":0.018,"w":0.03167,"h":0.03167,"d":0.24,"c":7,"s":7},{"part":"leadLeg","x":0.63018,"y":0.4886,"z":0.018,"w":0.03167,"h":0.03167,"d":0.24,"c":7,"s":7},{"part":"leadLeg","x":0.6625,"y":0.4886,"z":0.018,"w":0.03167,"h":0.03167,"d":0.24,"c":7,"s":7},{"part":"leadLeg","x":0.69482,"y":0.4886,"z":0.018,"w":0.03167,"h":0.03167,"d":0.24,"c":7,"s":7},{"part":"leadLeg","x":0.72713,"y":0.4886,"z":0.018,"w":0.03167,"h":0.03167,"d":0.24,"c":7,"s":7},{"part":"leadLeg","x":0.75945,"y":0.4886,"z":0.018,"w":0.03167,"h":0.03167,"d":0.24,"c":7,"s":7},{"part":"leadLeg","x":0.79177,"y":0.4886,"z":0.018,"w":0.03167,"h":0.03167,"d":0.24,"c":7,"s":7},{"part":"leadLeg","x":0.82409,"y":0.4886,"z":0.018,"w":0.03167,"h":0.03167,"d":0.24,"c":7,"s":7},{"part":"leadLeg","x":0.8564,"y":0.4886,"z":0.018,"w":0.03167,"h":0.03167,"d":0.24,"c":7,"s":7},{"part":"leadLeg","x":0.88872,"y":0.4886,"z":0.018,"w":0.03167,"h":0.03167,"d":0.24,"c":7,"s":7},{"part":"leadLeg","x":0.92104,"y":0.4886,"z":0.018,"w":0.03167,"h":0.03167,"d":0.24,"c":7,"s":7},{"part":"leadLeg","x":0.95335,"y":0.4886,"z":0.018,"w":0.03167,"h":0.03167,"d":0.24,"c":7,"s":7},{"part":"leadLeg","x":0.98567,"y":0.4886,"z":0.018,"w":0.03167,"h":0.03167,"d":0.24,"c":7,"s":7},{"part":"leadLeg","x":1.01799,"y":0.4886,"z":0.018,"w":0.03167,"h":0.03167,"d":0.24,"c":5,"s":5},{"part":"leadLeg","x":1.0503,"y":0.4886,"z":0.018,"w":0.03167,"h":0.03167,"d":0.24,"c":5,"s":5},{"part":"leadLeg","x":1.08262,"y":0.4886,"z":0.018,"w":0.03167,"h":0.03167,"d":0.24,"c":5,"s":5},{"part":"leadLeg","x":1.11494,"y":0.4886,"z":0.018,"w":0.03167,"h":0.03167,"d":0.24,"c":5,"s":5},{"part":"leadLeg","x":1.14726,"y":0.4886,"z":0.018,"w":0.03167,"h":0.03167,"d":0.24,"c":5,"s":5},{"part":"leadLeg","x":1.17957,"y":0.4886,"z":0.018,"w":0.03167,"h":0.03167,"d":0.24,"c":11,"s":11},{"part":"leadLeg","x":1.24421,"y":0.4886,"z":-0.012,"w":0.03167,"h":0.03167,"d":0.24,"c":10,"s":10},{"part":"leadLeg","x":1.27652,"y":0.4886,"z":-0.012,"w":0.03167,"h":0.03167,"d":0.24,"c":10,"s":10},{"part":"rearLeg","x":-1.08262,"y":0.45628,"z":0.018,"w":0.03167,"h":0.03167,"d":0.24,"c":5,"s":5},{"part":"rearLeg","x":-1.0503,"y":0.45628,"z":0.018,"w":0.03167,"h":0.03167,"d":0.24,"c":7,"s":7},{"part":"rearLeg","x":-1.01799,"y":0.45628,"z":0.018,"w":0.03167,"h":0.03167,"d":0.24,"c":7,"s":7},{"part":"rearLeg","x":-0.98567,"y":0.45628,"z":0.018,"w":0.03167,"h":0.03167,"d":0.24,"c":7,"s":7},{"part":"rearLeg","x":-0.95335,"y":0.45628,"z":0.018,"w":0.03167,"h":0.03167,"d":0.24,"c":7,"s":7},{"part":"rearLeg","x":-0.92104,"y":0.45628,"z":0.018,"w":0.03167,"h":0.03167,"d":0.24,"c":7,"s":7},{"part":"rearLeg","x":-0.88872,"y":0.45628,"z":0.018,"w":0.03167,"h":0.03167,"d":0.24,"c":7,"s":7},{"part":"rearLeg","x":-0.8564,"y":0.45628,"z":0.018,"w":0.03167,"h":0.03167,"d":0.24,"c":7,"s":7},{"part":"rearLeg","x":-0.82409,"y":0.45628,"z":0.018,"w":0.03167,"h":0.03167,"d":0.24,"c":7,"s":7},{"part":"rearLeg","x":-0.79177,"y":0.45628,"z":0.018,"w":0.03167,"h":0.03167,"d":0.24,"c":7,"s":7},{"part":"rearLeg","x":-0.75945,"y":0.45628,"z":0.018,"w":0.03167,"h":0.03167,"d":0.24,"c":7,"s":7},{"part":"rearLeg","x":-0.72713,"y":0.45628,"z":0.018,"w":0.03167,"h":0.03167,"d":0.24,"c":7,"s":7},{"part":"rearLeg","x":-0.69482,"y":0.45628,"z":0.018,"w":0.03167,"h":0.03167,"d":0.24,"c":5,"s":5},{"part":"rearLeg","x":-0.6625,"y":0.45628,"z":0.018,"w":0.03167,"h":0.03167,"d":0.24,"c":5,"s":5},{"part":"rearLeg","x":-0.63018,"y":0.45628,"z":0.018,"w":0.03167,"h":0.03167,"d":0.24,"c":11,"s":11},{"part":"rearLeg","x":-0.59787,"y":0.45628,"z":0.018,"w":0.03167,"h":0.03167,"d":0.24,"c":11,"s":11},{"part":"rearLeg","x":-0.21006,"y":0.45628,"z":0.018,"w":0.03167,"h":0.03167,"d":0.24,"c":11,"s":11},{"part":"rearLeg","x":-0.17774,"y":0.45628,"z":0.018,"w":0.03167,"h":0.03167,"d":0.24,"c":11,"s":11},{"part":"rearLeg","x":-0.14543,"y":0.45628,"z":0.018,"w":0.03167,"h":0.03167,"d":0.24,"c":11,"s":11},{"part":"rearLeg","x":-0.11311,"y":0.45628,"z":0.018,"w":0.03167,"h":0.03167,"d":0.24,"c":11,"s":11},{"part":"rearLeg","x":-0.08079,"y":0.45628,"z":0.018,"w":0.03167,"h":0.03167,"d":0.24,"c":5,"s":5},{"part":"rearLeg","x":-0.04848,"y":0.45628,"z":0.018,"w":0.03167,"h":0.03167,"d":0.24,"c":5,"s":5},{"part":"rearLeg","x":-0.01616,"y":0.45628,"z":0.018,"w":0.03167,"h":0.03167,"d":0.24,"c":5,"s":5},{"part":"leadLeg","x":0.01616,"y":0.45628,"z":0.018,"w":0.03167,"h":0.03167,"d":0.24,"c":5,"s":5},{"part":"leadLeg","x":0.04848,"y":0.45628,"z":0.018,"w":0.03167,"h":0.03167,"d":0.24,"c":11,"s":11},{"part":"leadLeg","x":0.08079,"y":0.45628,"z":0.018,"w":0.03167,"h":0.03167,"d":0.24,"c":11,"s":11},{"part":"leadLeg","x":0.11311,"y":0.45628,"z":0.018,"w":0.03167,"h":0.03167,"d":0.24,"c":11,"s":11},{"part":"leadLeg","x":0.14543,"y":0.45628,"z":0.018,"w":0.03167,"h":0.03167,"d":0.24,"c":11,"s":11},{"part":"leadLeg","x":0.17774,"y":0.45628,"z":0.018,"w":0.03167,"h":0.03167,"d":0.24,"c":11,"s":11},{"part":"leadLeg","x":0.21006,"y":0.45628,"z":0.018,"w":0.03167,"h":0.03167,"d":0.24,"c":11,"s":11},{"part":"leadLeg","x":0.24238,"y":0.45628,"z":0.018,"w":0.03167,"h":0.03167,"d":0.24,"c":11,"s":11},{"part":"leadLeg","x":0.2747,"y":0.45628,"z":0.018,"w":0.03167,"h":0.03167,"d":0.24,"c":11,"s":11},{"part":"leadLeg","x":0.30701,"y":0.45628,"z":0.018,"w":0.03167,"h":0.03167,"d":0.24,"c":11,"s":11},{"part":"leadLeg","x":0.33933,"y":0.45628,"z":0.018,"w":0.03167,"h":0.03167,"d":0.24,"c":11,"s":11},{"part":"leadLeg","x":0.37165,"y":0.45628,"z":0.018,"w":0.03167,"h":0.03167,"d":0.24,"c":5,"s":5},{"part":"leadLeg","x":0.40396,"y":0.45628,"z":0.018,"w":0.03167,"h":0.03167,"d":0.24,"c":5,"s":5},{"part":"leadLeg","x":0.43628,"y":0.45628,"z":0.018,"w":0.03167,"h":0.03167,"d":0.24,"c":5,"s":5},{"part":"leadLeg","x":0.4686,"y":0.45628,"z":0.018,"w":0.03167,"h":0.03167,"d":0.24,"c":5,"s":5},{"part":"leadLeg","x":0.50091,"y":0.45628,"z":0.018,"w":0.03167,"h":0.03167,"d":0.24,"c":5,"s":5},{"part":"leadLeg","x":0.53323,"y":0.45628,"z":0.018,"w":0.03167,"h":0.03167,"d":0.24,"c":5,"s":5},{"part":"leadLeg","x":0.56555,"y":0.45628,"z":0.018,"w":0.03167,"h":0.03167,"d":0.24,"c":5,"s":5},{"part":"leadLeg","x":0.59787,"y":0.45628,"z":0.018,"w":0.03167,"h":0.03167,"d":0.24,"c":5,"s":5},{"part":"leadLeg","x":0.63018,"y":0.45628,"z":0.018,"w":0.03167,"h":0.03167,"d":0.24,"c":5,"s":5},{"part":"leadLeg","x":0.6625,"y":0.45628,"z":0.018,"w":0.03167,"h":0.03167,"d":0.24,"c":5,"s":5},{"part":"leadLeg","x":0.69482,"y":0.45628,"z":0.018,"w":0.03167,"h":0.03167,"d":0.24,"c":5,"s":5},{"part":"leadLeg","x":0.72713,"y":0.45628,"z":0.018,"w":0.03167,"h":0.03167,"d":0.24,"c":5,"s":5},{"part":"leadLeg","x":0.75945,"y":0.45628,"z":0.018,"w":0.03167,"h":0.03167,"d":0.24,"c":5,"s":5},{"part":"leadLeg","x":0.79177,"y":0.45628,"z":0.018,"w":0.03167,"h":0.03167,"d":0.24,"c":5,"s":5},{"part":"leadLeg","x":0.82409,"y":0.45628,"z":0.018,"w":0.03167,"h":0.03167,"d":0.24,"c":5,"s":5},{"part":"leadLeg","x":0.8564,"y":0.45628,"z":0.018,"w":0.03167,"h":0.03167,"d":0.24,"c":5,"s":5},{"part":"leadLeg","x":0.88872,"y":0.45628,"z":0.018,"w":0.03167,"h":0.03167,"d":0.24,"c":5,"s":5},{"part":"leadLeg","x":0.92104,"y":0.45628,"z":0.018,"w":0.03167,"h":0.03167,"d":0.24,"c":5,"s":5},{"part":"leadLeg","x":0.95335,"y":0.45628,"z":0.018,"w":0.03167,"h":0.03167,"d":0.24,"c":5,"s":5},{"part":"leadLeg","x":0.98567,"y":0.45628,"z":0.018,"w":0.03167,"h":0.03167,"d":0.24,"c":5,"s":5},{"part":"leadLeg","x":1.01799,"y":0.45628,"z":0.018,"w":0.03167,"h":0.03167,"d":0.24,"c":5,"s":5},{"part":"leadLeg","x":1.0503,"y":0.45628,"z":0.018,"w":0.03167,"h":0.03167,"d":0.24,"c":5,"s":5},{"part":"leadLeg","x":1.08262,"y":0.45628,"z":0.018,"w":0.03167,"h":0.03167,"d":0.24,"c":5,"s":5},{"part":"leadLeg","x":1.11494,"y":0.45628,"z":0.018,"w":0.03167,"h":0.03167,"d":0.24,"c":5,"s":5},{"part":"leadLeg","x":1.14726,"y":0.45628,"z":0.018,"w":0.03167,"h":0.03167,"d":0.24,"c":11,"s":11},{"part":"rearLeg","x":-1.11494,"y":0.42396,"z":0.018,"w":0.03167,"h":0.03167,"d":0.24,"c":11,"s":11},{"part":"rearLeg","x":-1.08262,"y":0.42396,"z":0.018,"w":0.03167,"h":0.03167,"d":0.24,"c":5,"s":5},{"part":"rearLeg","x":-1.0503,"y":0.42396,"z":0.018,"w":0.03167,"h":0.03167,"d":0.24,"c":7,"s":7},{"part":"rearLeg","x":-1.01799,"y":0.42396,"z":0.018,"w":0.03167,"h":0.03167,"d":0.24,"c":7,"s":7},{"part":"rearLeg","x":-0.98567,"y":0.42396,"z":0.018,"w":0.03167,"h":0.03167,"d":0.24,"c":7,"s":7},{"part":"rearLeg","x":-0.95335,"y":0.42396,"z":0.018,"w":0.03167,"h":0.03167,"d":0.24,"c":7,"s":7},{"part":"rearLeg","x":-0.92104,"y":0.42396,"z":0.018,"w":0.03167,"h":0.03167,"d":0.24,"c":7,"s":7},{"part":"rearLeg","x":-0.88872,"y":0.42396,"z":0.018,"w":0.03167,"h":0.03167,"d":0.24,"c":7,"s":7},{"part":"rearLeg","x":-0.8564,"y":0.42396,"z":0.018,"w":0.03167,"h":0.03167,"d":0.24,"c":7,"s":7},{"part":"rearLeg","x":-0.82409,"y":0.42396,"z":0.018,"w":0.03167,"h":0.03167,"d":0.24,"c":5,"s":5},{"part":"rearLeg","x":-0.79177,"y":0.42396,"z":0.018,"w":0.03167,"h":0.03167,"d":0.24,"c":5,"s":5},{"part":"rearLeg","x":-0.75945,"y":0.42396,"z":0.018,"w":0.03167,"h":0.03167,"d":0.24,"c":5,"s":5},{"part":"rearLeg","x":-0.72713,"y":0.42396,"z":0.018,"w":0.03167,"h":0.03167,"d":0.24,"c":11,"s":11},{"part":"rearLeg","x":-0.69482,"y":0.42396,"z":0.018,"w":0.03167,"h":0.03167,"d":0.24,"c":11,"s":11},{"part":"rearLeg","x":-0.6625,"y":0.42396,"z":0.018,"w":0.03167,"h":0.03167,"d":0.24,"c":11,"s":11},{"part":"rearLeg","x":-0.63018,"y":0.42396,"z":0.018,"w":0.03167,"h":0.03167,"d":0.24,"c":11,"s":11},{"part":"leadLeg","x":0.30701,"y":0.42396,"z":0.018,"w":0.03167,"h":0.03167,"d":0.24,"c":11,"s":11},{"part":"leadLeg","x":0.33933,"y":0.42396,"z":0.018,"w":0.03167,"h":0.03167,"d":0.24,"c":11,"s":11},{"part":"leadLeg","x":0.37165,"y":0.42396,"z":0.018,"w":0.03167,"h":0.03167,"d":0.24,"c":11,"s":11},{"part":"leadLeg","x":0.40396,"y":0.42396,"z":0.018,"w":0.03167,"h":0.03167,"d":0.24,"c":11,"s":11},{"part":"leadLeg","x":0.43628,"y":0.42396,"z":0.018,"w":0.03167,"h":0.03167,"d":0.24,"c":5,"s":5},{"part":"leadLeg","x":0.4686,"y":0.42396,"z":0.018,"w":0.03167,"h":0.03167,"d":0.24,"c":5,"s":5},{"part":"leadLeg","x":0.50091,"y":0.42396,"z":0.018,"w":0.03167,"h":0.03167,"d":0.24,"c":5,"s":5},{"part":"leadLeg","x":0.53323,"y":0.42396,"z":0.018,"w":0.03167,"h":0.03167,"d":0.24,"c":11,"s":11},{"part":"leadLeg","x":0.56555,"y":0.42396,"z":0.018,"w":0.03167,"h":0.03167,"d":0.24,"c":11,"s":11},{"part":"leadLeg","x":0.59787,"y":0.42396,"z":0.018,"w":0.03167,"h":0.03167,"d":0.24,"c":11,"s":11},{"part":"leadLeg","x":0.63018,"y":0.42396,"z":0.018,"w":0.03167,"h":0.03167,"d":0.24,"c":11,"s":11},{"part":"leadLeg","x":0.6625,"y":0.42396,"z":0.018,"w":0.03167,"h":0.03167,"d":0.24,"c":5,"s":5},{"part":"leadLeg","x":0.69482,"y":0.42396,"z":0.018,"w":0.03167,"h":0.03167,"d":0.24,"c":5,"s":5},{"part":"leadLeg","x":0.72713,"y":0.42396,"z":0.018,"w":0.03167,"h":0.03167,"d":0.24,"c":5,"s":5},{"part":"leadLeg","x":0.75945,"y":0.42396,"z":0.018,"w":0.03167,"h":0.03167,"d":0.24,"c":5,"s":5},{"part":"leadLeg","x":0.79177,"y":0.42396,"z":0.018,"w":0.03167,"h":0.03167,"d":0.24,"c":5,"s":5},{"part":"leadLeg","x":0.82409,"y":0.42396,"z":0.018,"w":0.03167,"h":0.03167,"d":0.24,"c":5,"s":5},{"part":"leadLeg","x":0.8564,"y":0.42396,"z":0.018,"w":0.03167,"h":0.03167,"d":0.24,"c":5,"s":5},{"part":"leadLeg","x":0.88872,"y":0.42396,"z":0.018,"w":0.03167,"h":0.03167,"d":0.24,"c":11,"s":11},{"part":"leadLeg","x":0.92104,"y":0.42396,"z":0.018,"w":0.03167,"h":0.03167,"d":0.24,"c":11,"s":11},{"part":"leadLeg","x":0.95335,"y":0.42396,"z":0.018,"w":0.03167,"h":0.03167,"d":0.24,"c":11,"s":11},{"part":"leadLeg","x":0.98567,"y":0.42396,"z":0.018,"w":0.03167,"h":0.03167,"d":0.24,"c":5,"s":5},{"part":"leadLeg","x":1.01799,"y":0.42396,"z":0.018,"w":0.03167,"h":0.03167,"d":0.24,"c":5,"s":5},{"part":"leadLeg","x":1.0503,"y":0.42396,"z":0.018,"w":0.03167,"h":0.03167,"d":0.24,"c":5,"s":5},{"part":"leadLeg","x":1.08262,"y":0.42396,"z":0.018,"w":0.03167,"h":0.03167,"d":0.24,"c":11,"s":11},{"part":"leadLeg","x":1.11494,"y":0.42396,"z":0.018,"w":0.03167,"h":0.03167,"d":0.24,"c":11,"s":11},{"part":"rearLeg","x":-1.11494,"y":0.39165,"z":0.018,"w":0.03167,"h":0.03167,"d":0.24,"c":11,"s":11},{"part":"rearLeg","x":-1.08262,"y":0.39165,"z":0.018,"w":0.03167,"h":0.03167,"d":0.24,"c":5,"s":5},{"part":"rearLeg","x":-1.0503,"y":0.39165,"z":0.018,"w":0.03167,"h":0.03167,"d":0.24,"c":7,"s":7},{"part":"rearLeg","x":-1.01799,"y":0.39165,"z":0.018,"w":0.03167,"h":0.03167,"d":0.24,"c":7,"s":7},{"part":"rearLeg","x":-0.98567,"y":0.39165,"z":0.018,"w":0.03167,"h":0.03167,"d":0.24,"c":7,"s":7},{"part":"rearLeg","x":-0.95335,"y":0.39165,"z":0.018,"w":0.03167,"h":0.03167,"d":0.24,"c":5,"s":5},{"part":"rearLeg","x":-0.92104,"y":0.39165,"z":0.018,"w":0.03167,"h":0.03167,"d":0.24,"c":5,"s":5},{"part":"rearLeg","x":-0.88872,"y":0.39165,"z":0.018,"w":0.03167,"h":0.03167,"d":0.24,"c":11,"s":11},{"part":"rearLeg","x":-0.8564,"y":0.39165,"z":0.018,"w":0.03167,"h":0.03167,"d":0.24,"c":11,"s":11},{"part":"rearLeg","x":-0.82409,"y":0.39165,"z":0.018,"w":0.03167,"h":0.03167,"d":0.24,"c":11,"s":11},{"part":"leadLeg","x":0.43628,"y":0.39165,"z":0.018,"w":0.03167,"h":0.03167,"d":0.24,"c":11,"s":11},{"part":"leadLeg","x":0.4686,"y":0.39165,"z":0.018,"w":0.03167,"h":0.03167,"d":0.24,"c":11,"s":11},{"part":"leadLeg","x":0.50091,"y":0.39165,"z":0.018,"w":0.03167,"h":0.03167,"d":0.24,"c":11,"s":11},{"part":"leadLeg","x":0.53323,"y":0.39165,"z":0.018,"w":0.03167,"h":0.03167,"d":0.24,"c":11,"s":11},{"part":"leadLeg","x":0.56555,"y":0.39165,"z":0.018,"w":0.03167,"h":0.03167,"d":0.24,"c":5,"s":5},{"part":"leadLeg","x":0.59787,"y":0.39165,"z":0.018,"w":0.03167,"h":0.03167,"d":0.24,"c":5,"s":5},{"part":"leadLeg","x":0.63018,"y":0.39165,"z":0.018,"w":0.03167,"h":0.03167,"d":0.24,"c":5,"s":5},{"part":"leadLeg","x":0.6625,"y":0.39165,"z":0.018,"w":0.03167,"h":0.03167,"d":0.24,"c":5,"s":5},{"part":"leadLeg","x":0.69482,"y":0.39165,"z":0.018,"w":0.03167,"h":0.03167,"d":0.24,"c":5,"s":5},{"part":"leadLeg","x":0.72713,"y":0.39165,"z":0.018,"w":0.03167,"h":0.03167,"d":0.24,"c":5,"s":5},{"part":"leadLeg","x":0.75945,"y":0.39165,"z":0.018,"w":0.03167,"h":0.03167,"d":0.24,"c":5,"s":5},{"part":"leadLeg","x":0.79177,"y":0.39165,"z":0.018,"w":0.03167,"h":0.03167,"d":0.24,"c":5,"s":5},{"part":"leadLeg","x":0.82409,"y":0.39165,"z":0.018,"w":0.03167,"h":0.03167,"d":0.24,"c":5,"s":5},{"part":"leadLeg","x":0.8564,"y":0.39165,"z":0.018,"w":0.03167,"h":0.03167,"d":0.24,"c":5,"s":5},{"part":"leadLeg","x":0.88872,"y":0.39165,"z":0.018,"w":0.03167,"h":0.03167,"d":0.24,"c":5,"s":5},{"part":"leadLeg","x":0.92104,"y":0.39165,"z":0.018,"w":0.03167,"h":0.03167,"d":0.24,"c":11,"s":11},{"part":"leadLeg","x":0.95335,"y":0.39165,"z":0.018,"w":0.03167,"h":0.03167,"d":0.24,"c":11,"s":11},{"part":"leadLeg","x":0.98567,"y":0.39165,"z":0.018,"w":0.03167,"h":0.03167,"d":0.24,"c":11,"s":11},{"part":"leadLeg","x":1.01799,"y":0.39165,"z":0.018,"w":0.03167,"h":0.03167,"d":0.24,"c":11,"s":11},{"part":"rearLeg","x":-1.11494,"y":0.35933,"z":0.018,"w":0.03167,"h":0.03167,"d":0.24,"c":11,"s":11},{"part":"rearLeg","x":-1.08262,"y":0.35933,"z":0.018,"w":0.03167,"h":0.03167,"d":0.24,"c":5,"s":5},{"part":"rearLeg","x":-1.0503,"y":0.35933,"z":0.018,"w":0.03167,"h":0.03167,"d":0.24,"c":5,"s":5},{"part":"rearLeg","x":-1.01799,"y":0.35933,"z":0.018,"w":0.03167,"h":0.03167,"d":0.24,"c":7,"s":7},{"part":"rearLeg","x":-0.98567,"y":0.35933,"z":0.018,"w":0.03167,"h":0.03167,"d":0.24,"c":7,"s":7},{"part":"rearLeg","x":-0.95335,"y":0.35933,"z":0.018,"w":0.03167,"h":0.03167,"d":0.24,"c":7,"s":7},{"part":"rearLeg","x":-0.92104,"y":0.35933,"z":0.018,"w":0.03167,"h":0.03167,"d":0.24,"c":7,"s":7},{"part":"rearLeg","x":-0.88872,"y":0.35933,"z":0.018,"w":0.03167,"h":0.03167,"d":0.24,"c":5,"s":5},{"part":"rearLeg","x":-0.8564,"y":0.35933,"z":0.018,"w":0.03167,"h":0.03167,"d":0.24,"c":11,"s":11},{"part":"leadLeg","x":0.63018,"y":0.35933,"z":0.018,"w":0.03167,"h":0.03167,"d":0.24,"c":11,"s":11},{"part":"leadLeg","x":0.6625,"y":0.35933,"z":0.018,"w":0.03167,"h":0.03167,"d":0.24,"c":11,"s":11},{"part":"leadLeg","x":0.69482,"y":0.35933,"z":0.018,"w":0.03167,"h":0.03167,"d":0.24,"c":11,"s":11},{"part":"leadLeg","x":0.72713,"y":0.35933,"z":0.018,"w":0.03167,"h":0.03167,"d":0.24,"c":11,"s":11},{"part":"leadLeg","x":0.75945,"y":0.35933,"z":0.018,"w":0.03167,"h":0.03167,"d":0.24,"c":11,"s":11},{"part":"leadLeg","x":0.79177,"y":0.35933,"z":0.018,"w":0.03167,"h":0.03167,"d":0.24,"c":11,"s":11},{"part":"leadLeg","x":0.82409,"y":0.35933,"z":0.018,"w":0.03167,"h":0.03167,"d":0.24,"c":11,"s":11},{"part":"leadLeg","x":0.8564,"y":0.35933,"z":0.018,"w":0.03167,"h":0.03167,"d":0.24,"c":11,"s":11},{"part":"rearLeg","x":-1.11494,"y":0.32701,"z":0.018,"w":0.03167,"h":0.03167,"d":0.24,"c":11,"s":11},{"part":"rearLeg","x":-1.08262,"y":0.32701,"z":0.018,"w":0.03167,"h":0.03167,"d":0.24,"c":11,"s":11},{"part":"rearLeg","x":-1.0503,"y":0.32701,"z":0.018,"w":0.03167,"h":0.03167,"d":0.24,"c":5,"s":5},{"part":"rearLeg","x":-1.01799,"y":0.32701,"z":0.018,"w":0.03167,"h":0.03167,"d":0.24,"c":5,"s":5},{"part":"rearLeg","x":-0.98567,"y":0.32701,"z":0.018,"w":0.03167,"h":0.03167,"d":0.24,"c":5,"s":5},{"part":"rearLeg","x":-0.95335,"y":0.32701,"z":0.018,"w":0.03167,"h":0.03167,"d":0.24,"c":5,"s":5},{"part":"rearLeg","x":-0.92104,"y":0.32701,"z":0.018,"w":0.03167,"h":0.03167,"d":0.24,"c":11,"s":11},{"part":"rearLeg","x":-1.08262,"y":0.2947,"z":0.018,"w":0.03167,"h":0.03167,"d":0.24,"c":11,"s":11},{"part":"rearLeg","x":-1.0503,"y":0.2947,"z":0.018,"w":0.03167,"h":0.03167,"d":0.24,"c":11,"s":11},{"part":"rearLeg","x":-1.01799,"y":0.2947,"z":0.018,"w":0.03167,"h":0.03167,"d":0.24,"c":11,"s":11},{"part":"rearLeg","x":-0.98567,"y":0.2947,"z":0.018,"w":0.03167,"h":0.03167,"d":0.24,"c":11,"s":11},{"part":"rearLeg","x":-0.95335,"y":0.2947,"z":0.018,"w":0.03167,"h":0.03167,"d":0.24,"c":11,"s":11},{"part":"rearLeg","x":-0.92104,"y":0.2947,"z":0.018,"w":0.03167,"h":0.03167,"d":0.24,"c":11,"s":11},{"part":"rearLeg","x":-1.0503,"y":0.26238,"z":0.018,"w":0.03167,"h":0.03167,"d":0.24,"c":11,"s":11},{"part":"rearLeg","x":-1.01799,"y":0.26238,"z":0.018,"w":0.03167,"h":0.03167,"d":0.24,"c":11,"s":11},{"part":"rearLeg","x":-0.98567,"y":0.26238,"z":0.018,"w":0.03167,"h":0.03167,"d":0.24,"c":11,"s":11},{"part":"rearLeg","x":-0.95335,"y":0.26238,"z":0.018,"w":0.03167,"h":0.03167,"d":0.24,"c":11,"s":11},{"part":"rearLeg","x":-0.92104,"y":0.26238,"z":-0.012,"w":0.03167,"h":0.03167,"d":0.24,"c":12,"s":12},{"part":"rearLeg","x":-0.88872,"y":0.26238,"z":0.018,"w":0.03167,"h":0.03167,"d":0.24,"c":11,"s":11},{"part":"rearLeg","x":-0.95335,"y":0.23006,"z":0.018,"w":0.03167,"h":0.03167,"d":0.24,"c":11,"s":11},{"part":"rearLeg","x":-0.92104,"y":0.23006,"z":0.018,"w":0.03167,"h":0.03167,"d":0.24,"c":11,"s":11},{"part":"rearLeg","x":-1.08262,"y":0.06848,"z":-0.012,"w":0.03167,"h":0.03167,"d":0.24,"c":9,"s":9},{"part":"rearLeg","x":-1.0503,"y":0.06848,"z":-0.012,"w":0.03167,"h":0.03167,"d":0.24,"c":9,"s":9},{"part":"rearLeg","x":-1.01799,"y":0.06848,"z":-0.012,"w":0.03167,"h":0.03167,"d":0.24,"c":9,"s":9},{"part":"rearLeg","x":-0.98567,"y":0.06848,"z":-0.012,"w":0.03167,"h":0.03167,"d":0.24,"c":9,"s":9},{"part":"rearLeg","x":-1.08262,"y":0.03616,"z":0.018,"w":0.03167,"h":0.03167,"d":0.24,"c":8,"s":8},{"part":"rearLeg","x":-1.0503,"y":0.03616,"z":0.018,"w":0.03167,"h":0.03167,"d":0.24,"c":8,"s":8},{"part":"rearLeg","x":-1.01799,"y":0.03616,"z":0.018,"w":0.03167,"h":0.03167,"d":0.24,"c":8,"s":8},{"part":"rearLeg","x":-0.98567,"y":0.03616,"z":-0.012,"w":0.03167,"h":0.03167,"d":0.24,"c":10,"s":10}],"source":{"frame":"/characters/majin-buu/frames/frame-186.png","width":84,"height":47,"sampleStep":1,"foregroundWidth":82,"foregroundHeight":45,"baselineForegroundHeight":47,"modelHeight":1.45427,"modelHeightScale":1.0}}
