{"format":"kore-hd-voxels-v1","palette":["#7b0000","#ff6b00","#0000ff","#d63900","#ffde94","#ffffff","#39426b","#a5add6","#080808","#0084ff","#ffff00"],"voxels":[{"part":"head","x":0.11042,"y":1.89708,"z":-0.012,"w":0.07214,"h":0.07214,"d":0.24,"c":0,"s":0},{"part":"head","x":0.03681,"y":1.82347,"z":-0.012,"w":0.07214,"h":0.07214,"d":0.24,"c":0,"s":0},{"part":"head","x":0.11042,"y":1.82347,"z":-0.012,"w":0.07214,"h":0.07214,"d":0.24,"c":1,"s":1},{"part":"head","x":0.18403,"y":1.82347,"z":-0.012,"w":0.07214,"h":0.07214,"d":0.24,"c":0,"s":0},{"part":"head","x":1.06736,"y":1.82347,"z":-0.012,"w":0.07214,"h":0.07214,"d":0.24,"c":2,"s":2},{"part":"head","x":1.14097,"y":1.82347,"z":-0.012,"w":0.07214,"h":0.07214,"d":0.24,"c":2,"s":2},{"part":"head","x":0.03681,"y":1.74986,"z":-0.012,"w":0.07214,"h":0.07214,"d":0.24,"c":0,"s":0},{"part":"head","x":0.11042,"y":1.74986,"z":-0.012,"w":0.07214,"h":0.07214,"d":0.24,"c":1,"s":1},{"part":"head","x":0.18403,"y":1.74986,"z":-0.012,"w":0.07214,"h":0.07214,"d":0.24,"c":0,"s":0},{"part":"head","x":0.99375,"y":1.74986,"z":-0.012,"w":0.07214,"h":0.07214,"d":0.24,"c":2,"s":2},{"part":"head","x":1.06736,"y":1.74986,"z":-0.012,"w":0.07214,"h":0.07214,"d":0.24,"c":2,"s":2},{"part":"head","x":0.03681,"y":1.67625,"z":-0.012,"w":0.07214,"h":0.07214,"d":0.24,"c":0,"s":0},{"part":"head","x":0.11042,"y":1.67625,"z":-0.012,"w":0.07214,"h":0.07214,"d":0.24,"c":1,"s":1},{"part":"head","x":0.18403,"y":1.67625,"z":-0.012,"w":0.07214,"h":0.07214,"d":0.24,"c":1,"s":1},{"part":"head","x":0.25764,"y":1.67625,"z":-0.012,"w":0.07214,"h":0.07214,"d":0.24,"c":0,"s":0},{"part":"head","x":0.55208,"y":1.67625,"z":-0.012,"w":0.07214,"h":0.07214,"d":0.24,"c":2,"s":2},{"part":"head","x":0.62569,"y":1.67625,"z":-0.012,"w":0.07214,"h":0.07214,"d":0.24,"c":2,"s":2},{"part":"head","x":0.69931,"y":1.67625,"z":-0.012,"w":0.07214,"h":0.07214,"d":0.24,"c":2,"s":2},{"part":"head","x":0.92014,"y":1.67625,"z":-0.012,"w":0.07214,"h":0.07214,"d":0.24,"c":2,"s":2},{"part":"head","x":0.99375,"y":1.67625,"z":-0.012,"w":0.07214,"h":0.07214,"d":0.24,"c":2,"s":2},{"part":"head","x":1.06736,"y":1.67625,"z":-0.012,"w":0.07214,"h":0.07214,"d":0.24,"c":2,"s":2},{"part":"head","x":-0.11042,"y":1.60264,"z":-0.012,"w":0.07214,"h":0.07214,"d":0.24,"c":1,"s":1},{"part":"head","x":-0.03681,"y":1.60264,"z":-0.012,"w":0.07214,"h":0.07214,"d":0.24,"c":0,"s":0},{"part":"head","x":0.03681,"y":1.60264,"z":-0.012,"w":0.07214,"h":0.07214,"d":0.24,"c":3,"s":3},{"part":"head","x":0.11042,"y":1.60264,"z":-0.012,"w":0.07214,"h":0.07214,"d":0.24,"c":1,"s":1},{"part":"head","x":0.18403,"y":1.60264,"z":-0.012,"w":0.07214,"h":0.07214,"d":0.24,"c":1,"s":1},{"part":"head","x":0.25764,"y":1.60264,"z":-0.012,"w":0.07214,"h":0.07214,"d":0.24,"c":1,"s":1},{"part":"head","x":0.33125,"y":1.60264,"z":-0.012,"w":0.07214,"h":0.07214,"d":0.24,"c":0,"s":0},{"part":"head","x":0.55208,"y":1.60264,"z":-0.012,"w":0.07214,"h":0.07214,"d":0.24,"c":2,"s":2},{"part":"head","x":0.62569,"y":1.60264,"z":-0.012,"w":0.07214,"h":0.07214,"d":0.24,"c":2,"s":2},{"part":"head","x":0.84653,"y":1.60264,"z":-0.012,"w":0.07214,"h":0.07214,"d":0.24,"c":2,"s":2},{"part":"head","x":0.92014,"y":1.60264,"z":-0.012,"w":0.07214,"h":0.07214,"d":0.24,"c":2,"s":2},{"part":"head","x":0.99375,"y":1.60264,"z":-0.012,"w":0.07214,"h":0.07214,"d":0.24,"c":2,"s":2},{"part":"head","x":-0.18403,"y":1.52903,"z":0.018,"w":0.07214,"h":0.07214,"d":0.24,"c":4,"s":4},{"part":"head","x":-0.11042,"y":1.52903,"z":0.018,"w":0.07214,"h":0.07214,"d":0.24,"c":4,"s":4},{"part":"head","x":-0.03681,"y":1.52903,"z":0.018,"w":0.07214,"h":0.07214,"d":0.24,"c":4,"s":4},{"part":"head","x":0.03681,"y":1.52903,"z":-0.012,"w":0.07214,"h":0.07214,"d":0.24,"c":3,"s":3},{"part":"head","x":0.11042,"y":1.52903,"z":-0.012,"w":0.07214,"h":0.07214,"d":0.24,"c":3,"s":3},{"part":"head","x":0.18403,"y":1.52903,"z":-0.012,"w":0.07214,"h":0.07214,"d":0.24,"c":1,"s":1},{"part":"head","x":0.25764,"y":1.52903,"z":-0.012,"w":0.07214,"h":0.07214,"d":0.24,"c":1,"s":1},{"part":"head","x":0.33125,"y":1.52903,"z":-0.012,"w":0.07214,"h":0.07214,"d":0.24,"c":1,"s":1},{"part":"head","x":0.40486,"y":1.52903,"z":-0.012,"w":0.07214,"h":0.07214,"d":0.24,"c":0,"s":0},{"part":"head","x":0.55208,"y":1.52903,"z":-0.012,"w":0.07214,"h":0.07214,"d":0.24,"c":2,"s":2},{"part":"head","x":0.62569,"y":1.52903,"z":-0.012,"w":0.07214,"h":0.07214,"d":0.24,"c":2,"s":2},{"part":"head","x":0.77292,"y":1.52903,"z":-0.012,"w":0.07214,"h":0.07214,"d":0.24,"c":2,"s":2},{"part":"head","x":0.84653,"y":1.52903,"z":-0.012,"w":0.07214,"h":0.07214,"d":0.24,"c":2,"s":2},{"part":"head","x":0.92014,"y":1.52903,"z":-0.012,"w":0.07214,"h":0.07214,"d":0.24,"c":2,"s":2},{"part":"head","x":-0.18403,"y":1.45542,"z":-0.012,"w":0.07214,"h":0.07214,"d":0.24,"c":1,"s":1},{"part":"head","x":-0.11042,"y":1.45542,"z":-0.012,"w":0.07214,"h":0.07214,"d":0.24,"c":1,"s":1},{"part":"head","x":-0.03681,"y":1.45542,"z":-0.012,"w":0.07214,"h":0.07214,"d":0.24,"c":1,"s":1},{"part":"head","x":0.03681,"y":1.45542,"z":-0.012,"w":0.07214,"h":0.07214,"d":0.24,"c":0,"s":0},{"part":"head","x":0.11042,"y":1.45542,"z":-0.012,"w":0.07214,"h":0.07214,"d":0.24,"c":0,"s":0},{"part":"head","x":0.18403,"y":1.45542,"z":-0.012,"w":0.07214,"h":0.07214,"d":0.24,"c":0,"s":0},{"part":"head","x":0.25764,"y":1.45542,"z":-0.012,"w":0.07214,"h":0.07214,"d":0.24,"c":0,"s":0},{"part":"head","x":0.33125,"y":1.45542,"z":-0.012,"w":0.07214,"h":0.07214,"d":0.24,"c":0,"s":0},{"part":"head","x":0.40486,"y":1.45542,"z":-0.012,"w":0.07214,"h":0.07214,"d":0.24,"c":0,"s":0},{"part":"head","x":0.47847,"y":1.45542,"z":-0.012,"w":0.07214,"h":0.07214,"d":0.24,"c":0,"s":0},{"part":"head","x":0.55208,"y":1.45542,"z":-0.012,"w":0.07214,"h":0.07214,"d":0.24,"c":0,"s":0},{"part":"head","x":0.77292,"y":1.45542,"z":-0.012,"w":0.07214,"h":0.07214,"d":0.24,"c":2,"s":2},{"part":"head","x":0.84653,"y":1.45542,"z":-0.012,"w":0.07214,"h":0.07214,"d":0.24,"c":2,"s":2},{"part":"torso","x":-0.18403,"y":1.38181,"z":-0.012,"w":0.07214,"h":0.07214,"d":0.24,"c":3,"s":3},{"part":"torso","x":-0.11042,"y":1.38181,"z":-0.012,"w":0.07214,"h":0.07214,"d":0.24,"c":0,"s":0},{"part":"torso","x":-0.03681,"y":1.38181,"z":-0.012,"w":0.07214,"h":0.07214,"d":0.24,"c":0,"s":0},{"part":"torso","x":0.03681,"y":1.38181,"z":-0.012,"w":0.07214,"h":0.07214,"d":0.24,"c":3,"s":3},{"part":"torso","x":0.11042,"y":1.38181,"z":-0.012,"w":0.07214,"h":0.07214,"d":0.24,"c":3,"s":3},{"part":"torso","x":0.18403,"y":1.38181,"z":-0.012,"w":0.07214,"h":0.07214,"d":0.24,"c":1,"s":1},{"part":"torso","x":0.25764,"y":1.38181,"z":-0.012,"w":0.07214,"h":0.07214,"d":0.24,"c":1,"s":1},{"part":"torso","x":0.33125,"y":1.38181,"z":-0.012,"w":0.07214,"h":0.07214,"d":0.24,"c":1,"s":1},{"part":"torso","x":0.40486,"y":1.38181,"z":-0.012,"w":0.07214,"h":0.07214,"d":0.24,"c":1,"s":1},{"part":"torso","x":0.47847,"y":1.38181,"z":-0.012,"w":0.07214,"h":0.07214,"d":0.24,"c":1,"s":1},{"part":"torso","x":0.55208,"y":1.38181,"z":-0.012,"w":0.07214,"h":0.07214,"d":0.24,"c":3,"s":3},{"part":"torso","x":0.62569,"y":1.38181,"z":-0.012,"w":0.07214,"h":0.07214,"d":0.24,"c":0,"s":0},{"part":"torso","x":0.69931,"y":1.38181,"z":-0.012,"w":0.07214,"h":0.07214,"d":0.24,"c":0,"s":0},{"part":"torso","x":-0.25764,"y":1.30819,"z":-0.012,"w":0.07214,"h":0.07214,"d":0.24,"c":3,"s":3},{"part":"torso","x":-0.18403,"y":1.30819,"z":-0.012,"w":0.07214,"h":0.07214,"d":0.24,"c":0,"s":0},{"part":"torso","x":-0.11042,"y":1.30819,"z":-0.012,"w":0.07214,"h":0.07214,"d":0.24,"c":3,"s":3},{"part":"torso","x":-0.03681,"y":1.30819,"z":-0.012,"w":0.07214,"h":0.07214,"d":0.24,"c":1,"s":1},{"part":"torso","x":0.03681,"y":1.30819,"z":-0.012,"w":0.07214,"h":0.07214,"d":0.24,"c":1,"s":1},{"part":"torso","x":0.11042,"y":1.30819,"z":-0.012,"w":0.07214,"h":0.07214,"d":0.24,"c":1,"s":1},{"part":"torso","x":0.18403,"y":1.30819,"z":-0.012,"w":0.07214,"h":0.07214,"d":0.24,"c":1,"s":1},{"part":"torso","x":0.25764,"y":1.30819,"z":-0.012,"w":0.07214,"h":0.07214,"d":0.24,"c":1,"s":1},{"part":"torso","x":0.33125,"y":1.30819,"z":-0.012,"w":0.07214,"h":0.07214,"d":0.24,"c":1,"s":1},{"part":"torso","x":0.40486,"y":1.30819,"z":-0.012,"w":0.07214,"h":0.07214,"d":0.24,"c":1,"s":1},{"part":"torso","x":0.47847,"y":1.30819,"z":-0.012,"w":0.07214,"h":0.07214,"d":0.24,"c":1,"s":1},{"part":"torso","x":0.55208,"y":1.30819,"z":-0.012,"w":0.07214,"h":0.07214,"d":0.24,"c":1,"s":1},{"part":"torso","x":0.62569,"y":1.30819,"z":-0.012,"w":0.07214,"h":0.07214,"d":0.24,"c":1,"s":1},{"part":"torso","x":0.69931,"y":1.30819,"z":-0.012,"w":0.07214,"h":0.07214,"d":0.24,"c":3,"s":3},{"part":"torso","x":0.77292,"y":1.30819,"z":-0.012,"w":0.07214,"h":0.07214,"d":0.24,"c":0,"s":0},{"part":"torso","x":-0.84653,"y":1.23458,"z":-0.012,"w":0.07214,"h":0.07214,"d":0.24,"c":0,"s":0},{"part":"torso","x":-0.25764,"y":1.23458,"z":-0.012,"w":0.07214,"h":0.07214,"d":0.24,"c":0,"s":0},{"part":"torso","x":-0.18403,"y":1.23458,"z":-0.012,"w":0.07214,"h":0.07214,"d":0.24,"c":3,"s":3},{"part":"torso","x":-0.11042,"y":1.23458,"z":-0.012,"w":0.07214,"h":0.07214,"d":0.24,"c":1,"s":1},{"part":"torso","x":-0.03681,"y":1.23458,"z":-0.012,"w":0.07214,"h":0.07214,"d":0.24,"c":1,"s":1},{"part":"torso","x":0.03681,"y":1.23458,"z":-0.012,"w":0.07214,"h":0.07214,"d":0.24,"c":1,"s":1},{"part":"torso","x":0.11042,"y":1.23458,"z":-0.012,"w":0.07214,"h":0.07214,"d":0.24,"c":1,"s":1},{"part":"torso","x":0.18403,"y":1.23458,"z":-0.012,"w":0.07214,"h":0.07214,"d":0.24,"c":1,"s":1},{"part":"torso","x":0.25764,"y":1.23458,"z":-0.012,"w":0.07214,"h":0.07214,"d":0.24,"c":1,"s":1},{"part":"torso","x":0.33125,"y":1.23458,"z":-0.012,"w":0.07214,"h":0.07214,"d":0.24,"c":1,"s":1},{"part":"torso","x":0.40486,"y":1.23458,"z":-0.012,"w":0.07214,"h":0.07214,"d":0.24,"c":1,"s":1},{"part":"torso","x":0.47847,"y":1.23458,"z":-0.012,"w":0.07214,"h":0.07214,"d":0.24,"c":1,"s":1},{"part":"torso","x":0.55208,"y":1.23458,"z":-0.012,"w":0.07214,"h":0.07214,"d":0.24,"c":1,"s":1},{"part":"torso","x":0.62569,"y":1.23458,"z":-0.012,"w":0.07214,"h":0.07214,"d":0.24,"c":1,"s":1},{"part":"torso","x":0.69931,"y":1.23458,"z":-0.012,"w":0.07214,"h":0.07214,"d":0.24,"c":1,"s":1},{"part":"torso","x":0.77292,"y":1.23458,"z":-0.012,"w":0.07214,"h":0.07214,"d":0.24,"c":3,"s":3},{"part":"torso","x":0.84653,"y":1.23458,"z":-0.012,"w":0.07214,"h":0.07214,"d":0.24,"c":0,"s":0},{"part":"torso","x":-0.92014,"y":1.16097,"z":-0.012,"w":0.07214,"h":0.07214,"d":0.24,"c":3,"s":3},{"part":"torso","x":-0.84653,"y":1.16097,"z":-0.012,"w":0.07214,"h":0.07214,"d":0.24,"c":1,"s":1},{"part":"torso","x":-0.25764,"y":1.16097,"z":-0.012,"w":0.07214,"h":0.07214,"d":0.24,"c":3,"s":3},{"part":"torso","x":-0.18403,"y":1.16097,"z":-0.012,"w":0.07214,"h":0.07214,"d":0.24,"c":1,"s":1},{"part":"torso","x":-0.11042,"y":1.16097,"z":-0.012,"w":0.07214,"h":0.07214,"d":0.24,"c":1,"s":1},{"part":"torso","x":-0.03681,"y":1.16097,"z":-0.012,"w":0.07214,"h":0.07214,"d":0.24,"c":1,"s":1},{"part":"torso","x":0.03681,"y":1.16097,"z":-0.012,"w":0.07214,"h":0.07214,"d":0.24,"c":1,"s":1},{"part":"torso","x":0.11042,"y":1.16097,"z":-0.012,"w":0.07214,"h":0.07214,"d":0.24,"c":1,"s":1},{"part":"torso","x":0.18403,"y":1.16097,"z":-0.012,"w":0.07214,"h":0.07214,"d":0.24,"c":1,"s":1},{"part":"torso","x":0.25764,"y":1.16097,"z":-0.012,"w":0.07214,"h":0.07214,"d":0.24,"c":1,"s":1},{"part":"torso","x":0.33125,"y":1.16097,"z":-0.012,"w":0.07214,"h":0.07214,"d":0.24,"c":1,"s":1},{"part":"torso","x":0.40486,"y":1.16097,"z":-0.012,"w":0.07214,"h":0.07214,"d":0.24,"c":1,"s":1},{"part":"torso","x":0.47847,"y":1.16097,"z":-0.012,"w":0.07214,"h":0.07214,"d":0.24,"c":1,"s":1},{"part":"torso","x":0.55208,"y":1.16097,"z":-0.012,"w":0.07214,"h":0.07214,"d":0.24,"c":1,"s":1},{"part":"torso","x":0.62569,"y":1.16097,"z":-0.012,"w":0.07214,"h":0.07214,"d":0.24,"c":1,"s":1},{"part":"torso","x":0.69931,"y":1.16097,"z":-0.012,"w":0.07214,"h":0.07214,"d":0.24,"c":1,"s":1},{"part":"torso","x":0.77292,"y":1.16097,"z":-0.012,"w":0.07214,"h":0.07214,"d":0.24,"c":1,"s":1},{"part":"torso","x":0.84653,"y":1.16097,"z":-0.012,"w":0.07214,"h":0.07214,"d":0.24,"c":3,"s":3},{"part":"torso","x":0.92014,"y":1.16097,"z":-0.012,"w":0.07214,"h":0.07214,"d":0.24,"c":0,"s":0},{"part":"torso","x":-0.92014,"y":1.08736,"z":-0.012,"w":0.07214,"h":0.07214,"d":0.24,"c":0,"s":0},{"part":"torso","x":-0.33125,"y":1.08736,"z":-0.012,"w":0.07214,"h":0.07214,"d":0.24,"c":0,"s":0},{"part":"torso","x":-0.25764,"y":1.08736,"z":-0.012,"w":0.07214,"h":0.07214,"d":0.24,"c":1,"s":1},{"part":"torso","x":-0.18403,"y":1.08736,"z":-0.012,"w":0.07214,"h":0.07214,"d":0.24,"c":1,"s":1},{"part":"torso","x":-0.11042,"y":1.08736,"z":-0.012,"w":0.07214,"h":0.07214,"d":0.24,"c":1,"s":1},{"part":"torso","x":-0.03681,"y":1.08736,"z":-0.012,"w":0.07214,"h":0.07214,"d":0.24,"c":1,"s":1},{"part":"torso","x":0.03681,"y":1.08736,"z":-0.012,"w":0.07214,"h":0.07214,"d":0.24,"c":1,"s":1},{"part":"torso","x":0.11042,"y":1.08736,"z":-0.012,"w":0.07214,"h":0.07214,"d":0.24,"c":1,"s":1},{"part":"torso","x":0.18403,"y":1.08736,"z":-0.012,"w":0.07214,"h":0.07214,"d":0.24,"c":1,"s":1},{"part":"torso","x":0.25764,"y":1.08736,"z":-0.012,"w":0.07214,"h":0.07214,"d":0.24,"c":1,"s":1},{"part":"torso","x":0.33125,"y":1.08736,"z":-0.012,"w":0.07214,"h":0.07214,"d":0.24,"c":1,"s":1},{"part":"torso","x":0.40486,"y":1.08736,"z":-0.012,"w":0.07214,"h":0.07214,"d":0.24,"c":1,"s":1},{"part":"torso","x":0.47847,"y":1.08736,"z":-0.012,"w":0.07214,"h":0.07214,"d":0.24,"c":1,"s":1},{"part":"torso","x":0.55208,"y":1.08736,"z":-0.012,"w":0.07214,"h":0.07214,"d":0.24,"c":1,"s":1},{"part":"torso","x":0.62569,"y":1.08736,"z":-0.012,"w":0.07214,"h":0.07214,"d":0.24,"c":1,"s":1},{"part":"torso","x":0.69931,"y":1.08736,"z":-0.012,"w":0.07214,"h":0.07214,"d":0.24,"c":1,"s":1},{"part":"torso","x":0.77292,"y":1.08736,"z":-0.012,"w":0.07214,"h":0.07214,"d":0.24,"c":1,"s":1},{"part":"torso","x":0.84653,"y":1.08736,"z":-0.012,"w":0.07214,"h":0.07214,"d":0.24,"c":1,"s":1},{"part":"torso","x":0.92014,"y":1.08736,"z":-0.012,"w":0.07214,"h":0.07214,"d":0.24,"c":0,"s":0},{"part":"torso","x":1.21458,"y":1.08736,"z":0.018,"w":0.07214,"h":0.07214,"d":0.24,"c":5,"s":5},{"part":"torso","x":-0.33125,"y":1.01375,"z":-0.012,"w":0.07214,"h":0.07214,"d":0.24,"c":3,"s":3},{"part":"torso","x":-0.25764,"y":1.01375,"z":-0.012,"w":0.07214,"h":0.07214,"d":0.24,"c":1,"s":1},{"part":"torso","x":-0.18403,"y":1.01375,"z":-0.012,"w":0.07214,"h":0.07214,"d":0.24,"c":1,"s":1},{"part":"torso","x":-0.11042,"y":1.01375,"z":-0.012,"w":0.07214,"h":0.07214,"d":0.24,"c":1,"s":1},{"part":"torso","x":-0.03681,"y":1.01375,"z":-0.012,"w":0.07214,"h":0.07214,"d":0.24,"c":1,"s":1},{"part":"torso","x":0.03681,"y":1.01375,"z":-0.012,"w":0.07214,"h":0.07214,"d":0.24,"c":1,"s":1},{"part":"torso","x":0.11042,"y":1.01375,"z":-0.012,"w":0.07214,"h":0.07214,"d":0.24,"c":1,"s":1},{"part":"torso","x":0.18403,"y":1.01375,"z":-0.012,"w":0.07214,"h":0.07214,"d":0.24,"c":1,"s":1},{"part":"torso","x":0.25764,"y":1.01375,"z":-0.012,"w":0.07214,"h":0.07214,"d":0.24,"c":1,"s":1},{"part":"torso","x":0.33125,"y":1.01375,"z":-0.012,"w":0.07214,"h":0.07214,"d":0.24,"c":1,"s":1},{"part":"torso","x":0.40486,"y":1.01375,"z":-0.012,"w":0.07214,"h":0.07214,"d":0.24,"c":1,"s":1},{"part":"torso","x":0.47847,"y":1.01375,"z":-0.012,"w":0.07214,"h":0.07214,"d":0.24,"c":1,"s":1},{"part":"torso","x":0.55208,"y":1.01375,"z":-0.012,"w":0.07214,"h":0.07214,"d":0.24,"c":1,"s":1},{"part":"torso","x":0.62569,"y":1.01375,"z":-0.012,"w":0.07214,"h":0.07214,"d":0.24,"c":1,"s":1},{"part":"torso","x":0.69931,"y":1.01375,"z":-0.012,"w":0.07214,"h":0.07214,"d":0.24,"c":1,"s":1},{"part":"torso","x":0.77292,"y":1.01375,"z":-0.012,"w":0.07214,"h":0.07214,"d":0.24,"c":1,"s":1},{"part":"torso","x":0.84653,"y":1.01375,"z":-0.012,"w":0.07214,"h":0.07214,"d":0.24,"c":1,"s":1},{"part":"torso","x":0.92014,"y":1.01375,"z":-0.012,"w":0.07214,"h":0.07214,"d":0.24,"c":3,"s":3},{"part":"torso","x":0.99375,"y":1.01375,"z":-0.012,"w":0.07214,"h":0.07214,"d":0.24,"c":0,"s":0},{"part":"torso","x":1.21458,"y":1.01375,"z":0.018,"w":0.07214,"h":0.07214,"d":0.24,"c":5,"s":5},{"part":"torso","x":-0.40486,"y":0.94014,"z":-0.012,"w":0.07214,"h":0.07214,"d":0.24,"c":0,"s":0},{"part":"torso","x":-0.33125,"y":0.94014,"z":-0.012,"w":0.07214,"h":0.07214,"d":0.24,"c":3,"s":3},{"part":"torso","x":-0.25764,"y":0.94014,"z":-0.012,"w":0.07214,"h":0.07214,"d":0.24,"c":1,"s":1},{"part":"torso","x":-0.18403,"y":0.94014,"z":-0.012,"w":0.07214,"h":0.07214,"d":0.24,"c":1,"s":1},{"part":"torso","x":-0.11042,"y":0.94014,"z":-0.012,"w":0.07214,"h":0.07214,"d":0.24,"c":1,"s":1},{"part":"torso","x":-0.03681,"y":0.94014,"z":-0.012,"w":0.07214,"h":0.07214,"d":0.24,"c":1,"s":1},{"part":"torso","x":0.03681,"y":0.94014,"z":-0.012,"w":0.07214,"h":0.07214,"d":0.24,"c":1,"s":1},{"part":"torso","x":0.11042,"y":0.94014,"z":-0.012,"w":0.07214,"h":0.07214,"d":0.24,"c":1,"s":1},{"part":"torso","x":0.18403,"y":0.94014,"z":-0.012,"w":0.07214,"h":0.07214,"d":0.24,"c":1,"s":1},{"part":"torso","x":0.25764,"y":0.94014,"z":-0.012,"w":0.07214,"h":0.07214,"d":0.24,"c":1,"s":1},{"part":"torso","x":0.33125,"y":0.94014,"z":-0.012,"w":0.07214,"h":0.07214,"d":0.24,"c":1,"s":1},{"part":"torso","x":0.40486,"y":0.94014,"z":-0.012,"w":0.07214,"h":0.07214,"d":0.24,"c":1,"s":1},{"part":"torso","x":0.47847,"y":0.94014,"z":-0.012,"w":0.07214,"h":0.07214,"d":0.24,"c":1,"s":1},{"part":"torso","x":0.55208,"y":0.94014,"z":-0.012,"w":0.07214,"h":0.07214,"d":0.24,"c":1,"s":1},{"part":"torso","x":0.62569,"y":0.94014,"z":-0.012,"w":0.07214,"h":0.07214,"d":0.24,"c":1,"s":1},{"part":"torso","x":0.69931,"y":0.94014,"z":-0.012,"w":0.07214,"h":0.07214,"d":0.24,"c":1,"s":1},{"part":"torso","x":0.77292,"y":0.94014,"z":-0.012,"w":0.07214,"h":0.07214,"d":0.24,"c":1,"s":1},{"part":"torso","x":0.84653,"y":0.94014,"z":-0.012,"w":0.07214,"h":0.07214,"d":0.24,"c":1,"s":1},{"part":"torso","x":0.92014,"y":0.94014,"z":-0.012,"w":0.07214,"h":0.07214,"d":0.24,"c":3,"s":3},{"part":"torso","x":0.99375,"y":0.94014,"z":-0.012,"w":0.07214,"h":0.07214,"d":0.24,"c":0,"s":0},{"part":"torso","x":1.06736,"y":0.94014,"z":0.018,"w":0.07214,"h":0.07214,"d":0.24,"c":5,"s":5},{"part":"torso","x":1.21458,"y":0.94014,"z":0.018,"w":0.07214,"h":0.07214,"d":0.24,"c":5,"s":5},{"part":"torso","x":-0.40486,"y":0.86653,"z":-0.012,"w":0.07214,"h":0.07214,"d":0.24,"c":0,"s":0},{"part":"torso","x":-0.33125,"y":0.86653,"z":-0.012,"w":0.07214,"h":0.07214,"d":0.24,"c":3,"s":3},{"part":"torso","x":-0.25764,"y":0.86653,"z":-0.012,"w":0.07214,"h":0.07214,"d":0.24,"c":1,"s":1},{"part":"torso","x":-0.18403,"y":0.86653,"z":-0.012,"w":0.07214,"h":0.07214,"d":0.24,"c":1,"s":1},{"part":"torso","x":-0.11042,"y":0.86653,"z":-0.012,"w":0.07214,"h":0.07214,"d":0.24,"c":1,"s":1},{"part":"torso","x":-0.03681,"y":0.86653,"z":-0.012,"w":0.07214,"h":0.07214,"d":0.24,"c":1,"s":1},{"part":"torso","x":0.03681,"y":0.86653,"z":-0.012,"w":0.07214,"h":0.07214,"d":0.24,"c":1,"s":1},{"part":"torso","x":0.11042,"y":0.86653,"z":-0.012,"w":0.07214,"h":0.07214,"d":0.24,"c":1,"s":1},{"part":"torso","x":0.18403,"y":0.86653,"z":-0.012,"w":0.07214,"h":0.07214,"d":0.24,"c":1,"s":1},{"part":"torso","x":0.25764,"y":0.86653,"z":-0.012,"w":0.07214,"h":0.07214,"d":0.24,"c":1,"s":1},{"part":"torso","x":0.33125,"y":0.86653,"z":-0.012,"w":0.07214,"h":0.07214,"d":0.24,"c":1,"s":1},{"part":"torso","x":0.40486,"y":0.86653,"z":-0.012,"w":0.07214,"h":0.07214,"d":0.24,"c":1,"s":1},{"part":"torso","x":0.47847,"y":0.86653,"z":-0.012,"w":0.07214,"h":0.07214,"d":0.24,"c":1,"s":1},{"part":"torso","x":0.55208,"y":0.86653,"z":-0.012,"w":0.07214,"h":0.07214,"d":0.24,"c":1,"s":1},{"part":"torso","x":0.62569,"y":0.86653,"z":-0.012,"w":0.07214,"h":0.07214,"d":0.24,"c":1,"s":1},{"part":"torso","x":0.69931,"y":0.86653,"z":-0.012,"w":0.07214,"h":0.07214,"d":0.24,"c":1,"s":1},{"part":"torso","x":0.77292,"y":0.86653,"z":-0.012,"w":0.07214,"h":0.07214,"d":0.24,"c":1,"s":1},{"part":"torso","x":0.84653,"y":0.86653,"z":-0.012,"w":0.07214,"h":0.07214,"d":0.24,"c":1,"s":1},{"part":"torso","x":0.92014,"y":0.86653,"z":-0.012,"w":0.07214,"h":0.07214,"d":0.24,"c":1,"s":1},{"part":"torso","x":0.99375,"y":0.86653,"z":-0.012,"w":0.07214,"h":0.07214,"d":0.24,"c":0,"s":0},{"part":"torso","x":1.06736,"y":0.86653,"z":0.018,"w":0.07214,"h":0.07214,"d":0.24,"c":5,"s":5},{"part":"torso","x":1.21458,"y":0.86653,"z":0.018,"w":0.07214,"h":0.07214,"d":0.24,"c":5,"s":5},{"part":"torso","x":-1.06736,"y":0.79292,"z":-0.012,"w":0.07214,"h":0.07214,"d":0.24,"c":0,"s":0},{"part":"torso","x":-0.99375,"y":0.79292,"z":-0.012,"w":0.07214,"h":0.07214,"d":0.24,"c":0,"s":0},{"part":"torso","x":-0.92014,"y":0.79292,"z":-0.012,"w":0.07214,"h":0.07214,"d":0.24,"c":0,"s":0},{"part":"torso","x":-0.47847,"y":0.79292,"z":-0.012,"w":0.07214,"h":0.07214,"d":0.24,"c":3,"s":3},{"part":"torso","x":-0.40486,"y":0.79292,"z":-0.012,"w":0.07214,"h":0.07214,"d":0.24,"c":0,"s":0},{"part":"torso","x":-0.33125,"y":0.79292,"z":-0.012,"w":0.07214,"h":0.07214,"d":0.24,"c":3,"s":3},{"part":"torso","x":-0.25764,"y":0.79292,"z":-0.012,"w":0.07214,"h":0.07214,"d":0.24,"c":3,"s":3},{"part":"torso","x":-0.18403,"y":0.79292,"z":-0.012,"w":0.07214,"h":0.07214,"d":0.24,"c":1,"s":1},{"part":"torso","x":-0.11042,"y":0.79292,"z":-0.012,"w":0.07214,"h":0.07214,"d":0.24,"c":1,"s":1},{"part":"torso","x":-0.03681,"y":0.79292,"z":-0.012,"w":0.07214,"h":0.07214,"d":0.24,"c":1,"s":1},{"part":"torso","x":0.03681,"y":0.79292,"z":-0.012,"w":0.07214,"h":0.07214,"d":0.24,"c":1,"s":1},{"part":"torso","x":0.11042,"y":0.79292,"z":-0.012,"w":0.07214,"h":0.07214,"d":0.24,"c":1,"s":1},{"part":"torso","x":0.18403,"y":0.79292,"z":-0.012,"w":0.07214,"h":0.07214,"d":0.24,"c":1,"s":1},{"part":"torso","x":0.25764,"y":0.79292,"z":-0.012,"w":0.07214,"h":0.07214,"d":0.24,"c":1,"s":1},{"part":"torso","x":0.33125,"y":0.79292,"z":-0.012,"w":0.07214,"h":0.07214,"d":0.24,"c":1,"s":1},{"part":"torso","x":0.40486,"y":0.79292,"z":-0.012,"w":0.07214,"h":0.07214,"d":0.24,"c":1,"s":1},{"part":"torso","x":0.47847,"y":0.79292,"z":-0.012,"w":0.07214,"h":0.07214,"d":0.24,"c":1,"s":1},{"part":"torso","x":0.55208,"y":0.79292,"z":-0.012,"w":0.07214,"h":0.07214,"d":0.24,"c":1,"s":1},{"part":"torso","x":0.62569,"y":0.79292,"z":-0.012,"w":0.07214,"h":0.07214,"d":0.24,"c":1,"s":1},{"part":"torso","x":0.69931,"y":0.79292,"z":-0.012,"w":0.07214,"h":0.07214,"d":0.24,"c":1,"s":1},{"part":"torso","x":0.77292,"y":0.79292,"z":-0.012,"w":0.07214,"h":0.07214,"d":0.24,"c":1,"s":1},{"part":"torso","x":0.84653,"y":0.79292,"z":-0.012,"w":0.07214,"h":0.07214,"d":0.24,"c":1,"s":1},{"part":"torso","x":0.92014,"y":0.79292,"z":-0.012,"w":0.07214,"h":0.07214,"d":0.24,"c":1,"s":1},{"part":"torso","x":0.99375,"y":0.79292,"z":-0.012,"w":0.07214,"h":0.07214,"d":0.24,"c":0,"s":0},{"part":"torso","x":1.14097,"y":0.79292,"z":0.018,"w":0.07214,"h":0.07214,"d":0.24,"c":5,"s":5},{"part":"torso","x":1.28819,"y":0.79292,"z":0.018,"w":0.07214,"h":0.07214,"d":0.24,"c":5,"s":5},{"part":"arm","x":-1.14097,"y":0.71931,"z":-0.012,"w":0.07214,"h":0.07214,"d":0.24,"c":0,"s":0},{"part":"arm","x":-1.06736,"y":0.71931,"z":-0.012,"w":0.07214,"h":0.07214,"d":0.24,"c":0,"s":0},{"part":"arm","x":-0.99375,"y":0.71931,"z":-0.012,"w":0.07214,"h":0.07214,"d":0.24,"c":3,"s":3},{"part":"leg","x":-0.47847,"y":0.71931,"z":-0.012,"w":0.07214,"h":0.07214,"d":0.24,"c":3,"s":3},{"part":"leg","x":-0.40486,"y":0.71931,"z":-0.012,"w":0.07214,"h":0.07214,"d":0.24,"c":0,"s":0},{"part":"leg","x":-0.33125,"y":0.71931,"z":-0.012,"w":0.07214,"h":0.07214,"d":0.24,"c":3,"s":3},{"part":"leg","x":-0.25764,"y":0.71931,"z":-0.012,"w":0.07214,"h":0.07214,"d":0.24,"c":3,"s":3},{"part":"leg","x":-0.18403,"y":0.71931,"z":-0.012,"w":0.07214,"h":0.07214,"d":0.24,"c":1,"s":1},{"part":"leg","x":-0.11042,"y":0.71931,"z":-0.012,"w":0.07214,"h":0.07214,"d":0.24,"c":1,"s":1},{"part":"leg","x":-0.03681,"y":0.71931,"z":-0.012,"w":0.07214,"h":0.07214,"d":0.24,"c":1,"s":1},{"part":"leg","x":0.03681,"y":0.71931,"z":-0.012,"w":0.07214,"h":0.07214,"d":0.24,"c":1,"s":1},{"part":"leg","x":0.11042,"y":0.71931,"z":-0.012,"w":0.07214,"h":0.07214,"d":0.24,"c":1,"s":1},{"part":"leg","x":0.18403,"y":0.71931,"z":-0.012,"w":0.07214,"h":0.07214,"d":0.24,"c":1,"s":1},{"part":"leg","x":0.25764,"y":0.71931,"z":-0.012,"w":0.07214,"h":0.07214,"d":0.24,"c":1,"s":1},{"part":"leg","x":0.33125,"y":0.71931,"z":-0.012,"w":0.07214,"h":0.07214,"d":0.24,"c":6,"s":6},{"part":"leg","x":0.40486,"y":0.71931,"z":-0.012,"w":0.07214,"h":0.07214,"d":0.24,"c":6,"s":6},{"part":"leg","x":0.47847,"y":0.71931,"z":-0.012,"w":0.07214,"h":0.07214,"d":0.24,"c":1,"s":1},{"part":"leg","x":0.55208,"y":0.71931,"z":-0.012,"w":0.07214,"h":0.07214,"d":0.24,"c":1,"s":1},{"part":"leg","x":0.62569,"y":0.71931,"z":-0.012,"w":0.07214,"h":0.07214,"d":0.24,"c":1,"s":1},{"part":"arm","x":0.69931,"y":0.71931,"z":-0.012,"w":0.07214,"h":0.07214,"d":0.24,"c":1,"s":1},{"part":"arm","x":0.77292,"y":0.71931,"z":-0.012,"w":0.07214,"h":0.07214,"d":0.24,"c":1,"s":1},{"part":"arm","x":0.84653,"y":0.71931,"z":-0.012,"w":0.07214,"h":0.07214,"d":0.24,"c":1,"s":1},{"part":"arm","x":0.92014,"y":0.71931,"z":-0.012,"w":0.07214,"h":0.07214,"d":0.24,"c":1,"s":1},{"part":"arm","x":0.99375,"y":0.71931,"z":-0.012,"w":0.07214,"h":0.07214,"d":0.24,"c":0,"s":0},{"part":"arm","x":1.28819,"y":0.71931,"z":0.018,"w":0.07214,"h":0.07214,"d":0.24,"c":5,"s":5},{"part":"arm","x":-1.06736,"y":0.64569,"z":-0.012,"w":0.07214,"h":0.07214,"d":0.24,"c":0,"s":0},{"part":"arm","x":-0.99375,"y":0.64569,"z":-0.012,"w":0.07214,"h":0.07214,"d":0.24,"c":0,"s":0},{"part":"leg","x":-0.55208,"y":0.64569,"z":-0.012,"w":0.07214,"h":0.07214,"d":0.24,"c":1,"s":1},{"part":"leg","x":-0.47847,"y":0.64569,"z":-0.012,"w":0.07214,"h":0.07214,"d":0.24,"c":1,"s":1},{"part":"leg","x":-0.40486,"y":0.64569,"z":-0.012,"w":0.07214,"h":0.07214,"d":0.24,"c":0,"s":0},{"part":"leg","x":-0.33125,"y":0.64569,"z":-0.012,"w":0.07214,"h":0.07214,"d":0.24,"c":3,"s":3},{"part":"leg","x":-0.25764,"y":0.64569,"z":-0.012,"w":0.07214,"h":0.07214,"d":0.24,"c":3,"s":3},{"part":"leg","x":-0.18403,"y":0.64569,"z":-0.012,"w":0.07214,"h":0.07214,"d":0.24,"c":3,"s":3},{"part":"leg","x":-0.11042,"y":0.64569,"z":-0.012,"w":0.07214,"h":0.07214,"d":0.24,"c":1,"s":1},{"part":"leg","x":-0.03681,"y":0.64569,"z":-0.012,"w":0.07214,"h":0.07214,"d":0.24,"c":1,"s":1},{"part":"leg","x":0.03681,"y":0.64569,"z":-0.012,"w":0.07214,"h":0.07214,"d":0.24,"c":1,"s":1},{"part":"leg","x":0.11042,"y":0.64569,"z":-0.012,"w":0.07214,"h":0.07214,"d":0.24,"c":1,"s":1},{"part":"leg","x":0.18403,"y":0.64569,"z":-0.012,"w":0.07214,"h":0.07214,"d":0.24,"c":1,"s":1},{"part":"leg","x":0.25764,"y":0.64569,"z":-0.012,"w":0.07214,"h":0.07214,"d":0.24,"c":6,"s":6},{"part":"leg","x":0.33125,"y":0.64569,"z":0.018,"w":0.07214,"h":0.07214,"d":0.24,"c":5,"s":5},{"part":"leg","x":0.40486,"y":0.64569,"z":0.018,"w":0.07214,"h":0.07214,"d":0.24,"c":5,"s":5},{"part":"leg","x":0.47847,"y":0.64569,"z":-0.012,"w":0.07214,"h":0.07214,"d":0.24,"c":6,"s":6},{"part":"leg","x":0.55208,"y":0.64569,"z":-0.012,"w":0.07214,"h":0.07214,"d":0.24,"c":1,"s":1},{"part":"leg","x":0.62569,"y":0.64569,"z":-0.012,"w":0.07214,"h":0.07214,"d":0.24,"c":1,"s":1},{"part":"arm","x":0.69931,"y":0.64569,"z":-0.012,"w":0.07214,"h":0.07214,"d":0.24,"c":1,"s":1},{"part":"arm","x":0.77292,"y":0.64569,"z":-0.012,"w":0.07214,"h":0.07214,"d":0.24,"c":1,"s":1},{"part":"arm","x":0.84653,"y":0.64569,"z":-0.012,"w":0.07214,"h":0.07214,"d":0.24,"c":1,"s":1},{"part":"arm","x":0.92014,"y":0.64569,"z":-0.012,"w":0.07214,"h":0.07214,"d":0.24,"c":1,"s":1},{"part":"arm","x":0.99375,"y":0.64569,"z":-0.012,"w":0.07214,"h":0.07214,"d":0.24,"c":0,"s":0},{"part":"leg","x":-0.55208,"y":0.57208,"z":-0.012,"w":0.07214,"h":0.07214,"d":0.24,"c":3,"s":3},{"part":"leg","x":-0.47847,"y":0.57208,"z":-0.012,"w":0.07214,"h":0.07214,"d":0.24,"c":3,"s":3},{"part":"leg","x":-0.40486,"y":0.57208,"z":-0.012,"w":0.07214,"h":0.07214,"d":0.24,"c":0,"s":0},{"part":"leg","x":-0.33125,"y":0.57208,"z":-0.012,"w":0.07214,"h":0.07214,"d":0.24,"c":3,"s":3},{"part":"leg","x":-0.25764,"y":0.57208,"z":-0.012,"w":0.07214,"h":0.07214,"d":0.24,"c":3,"s":3},{"part":"leg","x":-0.18403,"y":0.57208,"z":-0.012,"w":0.07214,"h":0.07214,"d":0.24,"c":3,"s":3},{"part":"leg","x":-0.11042,"y":0.57208,"z":-0.012,"w":0.07214,"h":0.07214,"d":0.24,"c":3,"s":3},{"part":"leg","x":-0.03681,"y":0.57208,"z":-0.012,"w":0.07214,"h":0.07214,"d":0.24,"c":1,"s":1},{"part":"leg","x":0.03681,"y":0.57208,"z":-0.012,"w":0.07214,"h":0.07214,"d":0.24,"c":1,"s":1},{"part":"leg","x":0.11042,"y":0.57208,"z":-0.012,"w":0.07214,"h":0.07214,"d":0.24,"c":3,"s":3},{"part":"leg","x":0.18403,"y":0.57208,"z":-0.012,"w":0.07214,"h":0.07214,"d":0.24,"c":6,"s":6},{"part":"leg","x":0.25764,"y":0.57208,"z":0.018,"w":0.07214,"h":0.07214,"d":0.24,"c":5,"s":5},{"part":"leg","x":0.33125,"y":0.57208,"z":0.018,"w":0.07214,"h":0.07214,"d":0.24,"c":7,"s":7},{"part":"leg","x":0.40486,"y":0.57208,"z":-0.012,"w":0.07214,"h":0.07214,"d":0.24,"c":6,"s":6},{"part":"leg","x":0.47847,"y":0.57208,"z":-0.012,"w":0.07214,"h":0.07214,"d":0.24,"c":6,"s":6},{"part":"leg","x":0.55208,"y":0.57208,"z":-0.012,"w":0.07214,"h":0.07214,"d":0.24,"c":1,"s":1},{"part":"leg","x":0.62569,"y":0.57208,"z":-0.012,"w":0.07214,"h":0.07214,"d":0.24,"c":1,"s":1},{"part":"arm","x":0.69931,"y":0.57208,"z":-0.012,"w":0.07214,"h":0.07214,"d":0.24,"c":1,"s":1},{"part":"arm","x":0.77292,"y":0.57208,"z":-0.012,"w":0.07214,"h":0.07214,"d":0.24,"c":1,"s":1},{"part":"arm","x":0.84653,"y":0.57208,"z":-0.012,"w":0.07214,"h":0.07214,"d":0.24,"c":1,"s":1},{"part":"arm","x":0.92014,"y":0.57208,"z":-0.012,"w":0.07214,"h":0.07214,"d":0.24,"c":1,"s":1},{"part":"arm","x":0.99375,"y":0.57208,"z":-0.012,"w":0.07214,"h":0.07214,"d":0.24,"c":0,"s":0},{"part":"leg","x":-0.47847,"y":0.49847,"z":-0.012,"w":0.07214,"h":0.07214,"d":0.24,"c":3,"s":3},{"part":"leg","x":-0.40486,"y":0.49847,"z":-0.012,"w":0.07214,"h":0.07214,"d":0.24,"c":0,"s":0},{"part":"leg","x":-0.33125,"y":0.49847,"z":-0.012,"w":0.07214,"h":0.07214,"d":0.24,"c":3,"s":3},{"part":"leg","x":-0.25764,"y":0.49847,"z":-0.012,"w":0.07214,"h":0.07214,"d":0.24,"c":3,"s":3},{"part":"leg","x":-0.18403,"y":0.49847,"z":-0.012,"w":0.07214,"h":0.07214,"d":0.24,"c":3,"s":3},{"part":"leg","x":-0.11042,"y":0.49847,"z":-0.012,"w":0.07214,"h":0.07214,"d":0.24,"c":3,"s":3},{"part":"leg","x":-0.03681,"y":0.49847,"z":-0.012,"w":0.07214,"h":0.07214,"d":0.24,"c":3,"s":3},{"part":"leg","x":0.03681,"y":0.49847,"z":-0.012,"w":0.07214,"h":0.07214,"d":0.24,"c":3,"s":3},{"part":"leg","x":0.11042,"y":0.49847,"z":-0.012,"w":0.07214,"h":0.07214,"d":0.24,"c":6,"s":6},{"part":"leg","x":0.18403,"y":0.49847,"z":0.018,"w":0.07214,"h":0.07214,"d":0.24,"c":5,"s":5},{"part":"leg","x":0.25764,"y":0.49847,"z":0.018,"w":0.07214,"h":0.07214,"d":0.24,"c":7,"s":7},{"part":"leg","x":0.33125,"y":0.49847,"z":-0.012,"w":0.07214,"h":0.07214,"d":0.24,"c":6,"s":6},{"part":"leg","x":0.40486,"y":0.49847,"z":-0.012,"w":0.07214,"h":0.07214,"d":0.24,"c":1,"s":1},{"part":"leg","x":0.47847,"y":0.49847,"z":-0.012,"w":0.07214,"h":0.07214,"d":0.24,"c":1,"s":1},{"part":"leg","x":0.55208,"y":0.49847,"z":-0.012,"w":0.07214,"h":0.07214,"d":0.24,"c":0,"s":0},{"part":"leg","x":0.62569,"y":0.49847,"z":-0.012,"w":0.07214,"h":0.07214,"d":0.24,"c":3,"s":3},{"part":"arm","x":0.69931,"y":0.49847,"z":-0.012,"w":0.07214,"h":0.07214,"d":0.24,"c":3,"s":3},{"part":"arm","x":0.77292,"y":0.49847,"z":-0.012,"w":0.07214,"h":0.07214,"d":0.24,"c":3,"s":3},{"part":"arm","x":0.84653,"y":0.49847,"z":-0.012,"w":0.07214,"h":0.07214,"d":0.24,"c":3,"s":3},{"part":"arm","x":0.92014,"y":0.49847,"z":-0.012,"w":0.07214,"h":0.07214,"d":0.24,"c":3,"s":3},{"part":"arm","x":0.99375,"y":0.49847,"z":-0.012,"w":0.07214,"h":0.07214,"d":0.24,"c":0,"s":0},{"part":"leg","x":-0.40486,"y":0.42486,"z":-0.012,"w":0.07214,"h":0.07214,"d":0.24,"c":0,"s":0},{"part":"leg","x":-0.33125,"y":0.42486,"z":-0.012,"w":0.07214,"h":0.07214,"d":0.24,"c":0,"s":0},{"part":"leg","x":-0.25764,"y":0.42486,"z":-0.012,"w":0.07214,"h":0.07214,"d":0.24,"c":3,"s":3},{"part":"leg","x":-0.18403,"y":0.42486,"z":-0.012,"w":0.07214,"h":0.07214,"d":0.24,"c":3,"s":3},{"part":"leg","x":-0.11042,"y":0.42486,"z":-0.012,"w":0.07214,"h":0.07214,"d":0.24,"c":3,"s":3},{"part":"leg","x":-0.03681,"y":0.42486,"z":-0.012,"w":0.07214,"h":0.07214,"d":0.24,"c":3,"s":3},{"part":"leg","x":0.03681,"y":0.42486,"z":-0.012,"w":0.07214,"h":0.07214,"d":0.24,"c":6,"s":6},{"part":"leg","x":0.11042,"y":0.42486,"z":0.018,"w":0.07214,"h":0.07214,"d":0.24,"c":5,"s":5},{"part":"leg","x":0.18403,"y":0.42486,"z":0.018,"w":0.07214,"h":0.07214,"d":0.24,"c":7,"s":7},{"part":"leg","x":0.25764,"y":0.42486,"z":-0.012,"w":0.07214,"h":0.07214,"d":0.24,"c":6,"s":6},{"part":"leg","x":0.33125,"y":0.42486,"z":-0.012,"w":0.07214,"h":0.07214,"d":0.24,"c":1,"s":1},{"part":"leg","x":0.40486,"y":0.42486,"z":-0.012,"w":0.07214,"h":0.07214,"d":0.24,"c":1,"s":1},{"part":"leg","x":0.47847,"y":0.42486,"z":-0.012,"w":0.07214,"h":0.07214,"d":0.24,"c":8,"s":8},{"part":"leg","x":0.55208,"y":0.42486,"z":0.018,"w":0.07214,"h":0.07214,"d":0.24,"c":5,"s":5},{"part":"leg","x":0.62569,"y":0.42486,"z":0.018,"w":0.07214,"h":0.07214,"d":0.24,"c":5,"s":5},{"part":"arm","x":0.69931,"y":0.42486,"z":0.018,"w":0.07214,"h":0.07214,"d":0.24,"c":5,"s":5},{"part":"arm","x":0.77292,"y":0.42486,"z":0.018,"w":0.07214,"h":0.07214,"d":0.24,"c":5,"s":5},{"part":"arm","x":0.84653,"y":0.42486,"z":-0.012,"w":0.07214,"h":0.07214,"d":0.24,"c":9,"s":9},{"part":"arm","x":0.92014,"y":0.42486,"z":-0.012,"w":0.07214,"h":0.07214,"d":0.24,"c":0,"s":0},{"part":"leg","x":-0.47847,"y":0.35125,"z":-0.012,"w":0.07214,"h":0.07214,"d":0.24,"c":3,"s":3},{"part":"leg","x":-0.40486,"y":0.35125,"z":-0.012,"w":0.07214,"h":0.07214,"d":0.24,"c":3,"s":3},{"part":"leg","x":-0.33125,"y":0.35125,"z":-0.012,"w":0.07214,"h":0.07214,"d":0.24,"c":0,"s":0},{"part":"leg","x":-0.25764,"y":0.35125,"z":-0.012,"w":0.07214,"h":0.07214,"d":0.24,"c":3,"s":3},{"part":"leg","x":-0.18403,"y":0.35125,"z":-0.012,"w":0.07214,"h":0.07214,"d":0.24,"c":3,"s":3},{"part":"leg","x":-0.11042,"y":0.35125,"z":-0.012,"w":0.07214,"h":0.07214,"d":0.24,"c":3,"s":3},{"part":"leg","x":-0.03681,"y":0.35125,"z":-0.012,"w":0.07214,"h":0.07214,"d":0.24,"c":6,"s":6},{"part":"leg","x":0.03681,"y":0.35125,"z":0.018,"w":0.07214,"h":0.07214,"d":0.24,"c":5,"s":5},{"part":"leg","x":0.11042,"y":0.35125,"z":0.018,"w":0.07214,"h":0.07214,"d":0.24,"c":5,"s":5},{"part":"leg","x":0.18403,"y":0.35125,"z":-0.012,"w":0.07214,"h":0.07214,"d":0.24,"c":6,"s":6},{"part":"leg","x":0.25764,"y":0.35125,"z":-0.012,"w":0.07214,"h":0.07214,"d":0.24,"c":3,"s":3},{"part":"leg","x":0.33125,"y":0.35125,"z":-0.012,"w":0.07214,"h":0.07214,"d":0.24,"c":3,"s":3},{"part":"leg","x":0.40486,"y":0.35125,"z":-0.012,"w":0.07214,"h":0.07214,"d":0.24,"c":1,"s":1},{"part":"leg","x":0.47847,"y":0.35125,"z":-0.012,"w":0.07214,"h":0.07214,"d":0.24,"c":1,"s":1},{"part":"leg","x":0.55208,"y":0.35125,"z":-0.012,"w":0.07214,"h":0.07214,"d":0.24,"c":8,"s":8},{"part":"leg","x":0.62569,"y":0.35125,"z":-0.012,"w":0.07214,"h":0.07214,"d":0.24,"c":8,"s":8},{"part":"arm","x":0.69931,"y":0.35125,"z":0.018,"w":0.07214,"h":0.07214,"d":0.24,"c":5,"s":5},{"part":"arm","x":0.77292,"y":0.35125,"z":0.018,"w":0.07214,"h":0.07214,"d":0.24,"c":5,"s":5},{"part":"arm","x":0.84653,"y":0.35125,"z":-0.012,"w":0.07214,"h":0.07214,"d":0.24,"c":2,"s":2},{"part":"arm","x":0.92014,"y":0.35125,"z":-0.012,"w":0.07214,"h":0.07214,"d":0.24,"c":0,"s":0},{"part":"arm","x":-1.28819,"y":0.27764,"z":0.018,"w":0.07214,"h":0.07214,"d":0.24,"c":5,"s":5},{"part":"arm","x":-1.21458,"y":0.27764,"z":0.018,"w":0.07214,"h":0.07214,"d":0.24,"c":5,"s":5},{"part":"arm","x":-1.06736,"y":0.27764,"z":0.018,"w":0.07214,"h":0.07214,"d":0.24,"c":5,"s":5},{"part":"leg","x":-0.47847,"y":0.27764,"z":-0.012,"w":0.07214,"h":0.07214,"d":0.24,"c":3,"s":3},{"part":"leg","x":-0.40486,"y":0.27764,"z":-0.012,"w":0.07214,"h":0.07214,"d":0.24,"c":3,"s":3},{"part":"leg","x":-0.33125,"y":0.27764,"z":-0.012,"w":0.07214,"h":0.07214,"d":0.24,"c":3,"s":3},{"part":"leg","x":-0.25764,"y":0.27764,"z":-0.012,"w":0.07214,"h":0.07214,"d":0.24,"c":6,"s":6},{"part":"leg","x":-0.18403,"y":0.27764,"z":-0.012,"w":0.07214,"h":0.07214,"d":0.24,"c":6,"s":6},{"part":"leg","x":-0.11042,"y":0.27764,"z":-0.012,"w":0.07214,"h":0.07214,"d":0.24,"c":6,"s":6},{"part":"leg","x":-0.03681,"y":0.27764,"z":0.018,"w":0.07214,"h":0.07214,"d":0.24,"c":5,"s":5},{"part":"leg","x":0.03681,"y":0.27764,"z":0.018,"w":0.07214,"h":0.07214,"d":0.24,"c":5,"s":5},{"part":"leg","x":0.11042,"y":0.27764,"z":-0.012,"w":0.07214,"h":0.07214,"d":0.24,"c":6,"s":6},{"part":"leg","x":0.18403,"y":0.27764,"z":-0.012,"w":0.07214,"h":0.07214,"d":0.24,"c":3,"s":3},{"part":"leg","x":0.25764,"y":0.27764,"z":-0.012,"w":0.07214,"h":0.07214,"d":0.24,"c":3,"s":3},{"part":"leg","x":0.33125,"y":0.27764,"z":-0.012,"w":0.07214,"h":0.07214,"d":0.24,"c":3,"s":3},{"part":"leg","x":0.40486,"y":0.27764,"z":-0.012,"w":0.07214,"h":0.07214,"d":0.24,"c":3,"s":3},{"part":"leg","x":0.47847,"y":0.27764,"z":-0.012,"w":0.07214,"h":0.07214,"d":0.24,"c":3,"s":3},{"part":"leg","x":0.55208,"y":0.27764,"z":-0.012,"w":0.07214,"h":0.07214,"d":0.24,"c":1,"s":1},{"part":"leg","x":0.62569,"y":0.27764,"z":-0.012,"w":0.07214,"h":0.07214,"d":0.24,"c":1,"s":1},{"part":"arm","x":0.69931,"y":0.27764,"z":-0.012,"w":0.07214,"h":0.07214,"d":0.24,"c":8,"s":8},{"part":"arm","x":0.77292,"y":0.27764,"z":-0.012,"w":0.07214,"h":0.07214,"d":0.24,"c":8,"s":8},{"part":"arm","x":0.84653,"y":0.27764,"z":-0.012,"w":0.07214,"h":0.07214,"d":0.24,"c":0,"s":0},{"part":"arm","x":-1.06736,"y":0.20403,"z":0.018,"w":0.07214,"h":0.07214,"d":0.24,"c":5,"s":5},{"part":"leg","x":-0.25764,"y":0.20403,"z":0.018,"w":0.07214,"h":0.07214,"d":0.24,"c":5,"s":5},{"part":"leg","x":-0.18403,"y":0.20403,"z":0.018,"w":0.07214,"h":0.07214,"d":0.24,"c":5,"s":5},{"part":"leg","x":-0.11042,"y":0.20403,"z":0.018,"w":0.07214,"h":0.07214,"d":0.24,"c":5,"s":5},{"part":"leg","x":-0.03681,"y":0.20403,"z":0.018,"w":0.07214,"h":0.07214,"d":0.24,"c":5,"s":5},{"part":"leg","x":0.03681,"y":0.20403,"z":-0.012,"w":0.07214,"h":0.07214,"d":0.24,"c":6,"s":6},{"part":"leg","x":0.11042,"y":0.20403,"z":-0.012,"w":0.07214,"h":0.07214,"d":0.24,"c":3,"s":3},{"part":"leg","x":0.18403,"y":0.20403,"z":-0.012,"w":0.07214,"h":0.07214,"d":0.24,"c":3,"s":3},{"part":"leg","x":0.25764,"y":0.20403,"z":-0.012,"w":0.07214,"h":0.07214,"d":0.24,"c":1,"s":1},{"part":"leg","x":0.33125,"y":0.20403,"z":-0.012,"w":0.07214,"h":0.07214,"d":0.24,"c":1,"s":1},{"part":"leg","x":0.40486,"y":0.20403,"z":0.018,"w":0.07214,"h":0.07214,"d":0.24,"c":10,"s":10},{"part":"leg","x":0.47847,"y":0.20403,"z":0.018,"w":0.07214,"h":0.07214,"d":0.24,"c":10,"s":10},{"part":"leg","x":0.55208,"y":0.20403,"z":-0.012,"w":0.07214,"h":0.07214,"d":0.24,"c":3,"s":3},{"part":"leg","x":0.62569,"y":0.20403,"z":-0.012,"w":0.07214,"h":0.07214,"d":0.24,"c":3,"s":3},{"part":"arm","x":0.69931,"y":0.20403,"z":-0.012,"w":0.07214,"h":0.07214,"d":0.24,"c":1,"s":1},{"part":"arm","x":0.77292,"y":0.20403,"z":-0.012,"w":0.07214,"h":0.07214,"d":0.24,"c":0,"s":0},{"part":"leg","x":-0.47847,"y":0.13042,"z":0.018,"w":0.07214,"h":0.07214,"d":0.24,"c":5,"s":5},{"part":"leg","x":-0.40486,"y":0.13042,"z":0.018,"w":0.07214,"h":0.07214,"d":0.24,"c":5,"s":5},{"part":"leg","x":-0.33125,"y":0.13042,"z":0.018,"w":0.07214,"h":0.07214,"d":0.24,"c":5,"s":5},{"part":"leg","x":0.03681,"y":0.13042,"z":-0.012,"w":0.07214,"h":0.07214,"d":0.24,"c":3,"s":3},{"part":"leg","x":0.11042,"y":0.13042,"z":-0.012,"w":0.07214,"h":0.07214,"d":0.24,"c":3,"s":3},{"part":"leg","x":0.18403,"y":0.13042,"z":-0.012,"w":0.07214,"h":0.07214,"d":0.24,"c":3,"s":3},{"part":"leg","x":0.25764,"y":0.13042,"z":-0.012,"w":0.07214,"h":0.07214,"d":0.24,"c":3,"s":3},{"part":"leg","x":0.33125,"y":0.13042,"z":-0.012,"w":0.07214,"h":0.07214,"d":0.24,"c":3,"s":3},{"part":"leg","x":0.40486,"y":0.13042,"z":-0.012,"w":0.07214,"h":0.07214,"d":0.24,"c":3,"s":3},{"part":"leg","x":0.47847,"y":0.13042,"z":-0.012,"w":0.07214,"h":0.07214,"d":0.24,"c":3,"s":3},{"part":"leg","x":0.55208,"y":0.13042,"z":0.018,"w":0.07214,"h":0.07214,"d":0.24,"c":10,"s":10},{"part":"leg","x":0.62569,"y":0.13042,"z":-0.012,"w":0.07214,"h":0.07214,"d":0.24,"c":0,"s":0},{"part":"arm","x":0.69931,"y":0.13042,"z":-0.012,"w":0.07214,"h":0.07214,"d":0.24,"c":0,"s":0},{"part":"leg","x":-0.18403,"y":0.05681,"z":-0.012,"w":0.07214,"h":0.07214,"d":0.24,"c":0,"s":0},{"part":"leg","x":-0.11042,"y":0.05681,"z":-0.012,"w":0.07214,"h":0.07214,"d":0.24,"c":0,"s":0},{"part":"leg","x":-0.03681,"y":0.05681,"z":-0.012,"w":0.07214,"h":0.07214,"d":0.24,"c":0,"s":0},{"part":"leg","x":0.03681,"y":0.05681,"z":-0.012,"w":0.07214,"h":0.07214,"d":0.24,"c":0,"s":0},{"part":"leg","x":0.11042,"y":0.05681,"z":-0.012,"w":0.07214,"h":0.07214,"d":0.24,"c":0,"s":0},{"part":"leg","x":0.18403,"y":0.05681,"z":-0.012,"w":0.07214,"h":0.07214,"d":0.24,"c":0,"s":0},{"part":"leg","x":0.25764,"y":0.05681,"z":-0.012,"w":0.07214,"h":0.07214,"d":0.24,"c":0,"s":0},{"part":"leg","x":0.33125,"y":0.05681,"z":-0.012,"w":0.07214,"h":0.07214,"d":0.24,"c":0,"s":0},{"part":"leg","x":0.40486,"y":0.05681,"z":-0.012,"w":0.07214,"h":0.07214,"d":0.24,"c":0,"s":0},{"part":"leg","x":0.47847,"y":0.05681,"z":-0.012,"w":0.07214,"h":0.07214,"d":0.24,"c":0,"s":0},{"part":"leg","x":0.55208,"y":0.05681,"z":-0.012,"w":0.07214,"h":0.07214,"d":0.24,"c":0,"s":0}],"source":{"frame":"/characters/don-patch-poppa-rocks/frames/frame-153.png","width":38,"height":28,"sampleStep":1,"foregroundWidth":36,"foregroundHeight":26,"baselineForegroundHeight":28,"modelHeight":1.91389,"modelHeightScale":1.0}}
